Workbook

Sheet final_manifest
A1: decision_date | B1: year | C1: case_numbers | D1: decision_label | E1: decision_title | F1: source | G1: source_native_id | H1: source_record_id | I1: case_numbers_raw | J1: date_caseno_key | K1: date_caseno_source_key | L1: has_downloadable_url | M1: is_downloaded | N1: download_status | O1: source_urls | P1: download_urls | Q1: download_paths | R1: successful_download_paths | S1: source_manifest_file
A2: 23447 | B2: =YEAR(A2) -> 1964 | C2: 61 | D2: Negative Clearance | Negative Clearance Decision | E2: Grosfillex & Fillistorf | Grosfillex | Fillistorf | F2: andrea | com_legacy | G2: 1 | com_legacy_1964_line_14 | H2: andrea:1 | com_legacy:com_legacy_1964_line_14 | I2: 61 | IV/61 | J2: 1964/11/03/61 | K2: 1964/11/03/61/andrea | 1964/11/03/61/com_legacy | L2: TRUE | M2: TRUE | N2: reference_only | already_downloaded | O2: http://ec.europa.eu/competition/antitrust/closed/en/1964.html | P2: https://eur-lex.europa.eu/legal-content/EN/TXT/HTML/?uri=CELEX:31964D0233 | https://eur-lex.europa.eu/legal-content/EN/TXT/PDF/?uri=CELEX:31964D0233 | https://eur-lex.europa.eu/legal-content/DE/TXT/HTML/?uri=CELEX:31964D0233 | https://eur-lex.europa.eu/legal-content/DE/TXT/PDF/?uri=CELEX:31964D0233 | http://ec.europa.eu/competition/search.html | http://ec.europa.eu/competition/antitrust/closed/en/1964.html#top | Q2: /home/edik/projects/eccjeu/data/raw/com_legacy/files/html/31964D0233_DE.html | /home/edik/projects/eccjeu/data/raw/com_legacy/files/pdfs/31964D0233_DE.pdf | /home/edik/projects/eccjeu/data/raw/com_legacy/files/html/search.html | /home/edik/projects/eccjeu/data/raw/com_legacy/files/html/1964.html | R2: /home/edik/projects/eccjeu/data/raw/com_legacy/files/html/31964D0233_DE.html | /home/edik/projects/eccjeu/data/raw/com_legacy/files/pdfs/31964D0233_DE.pdf | /home/edik/projects/eccjeu/data/raw/com_legacy/files/html/search.html | /home/edik/projects/eccjeu/data/raw/com_legacy/files/html/1964.html | S2: /home/edik/projects/eccjeu/input/andrea_input.csv | /home/edik/projects/eccjeu/output/com_legacy/download_case_manifest.csv
A3: 23529 | B3: =YEAR(A3) -> 1964 | C3: 12868 | D3: Negative Clearance | Negative Clearance Decision | E3: Bendix & Meertens and Straet | Bendix | Mertens and Straat | F3: andrea | com_legacy | G3: 2 | com_legacy_1964_line_11 | H3: andrea:2 | com_legacy:com_legacy_1964_line_11 | I3: 12868 | IV/12868 | J3: 1964/01/06/12868 | K3: 1964/01/06/12868/andrea | 1964/01/06/12868/com_legacy | L3: TRUE | M3: TRUE | N3: reference_only | already_downloaded | O3: http://ec.europa.eu/competition/antitrust/closed/en/1964.html | P3: https://eur-lex.europa.eu/legal-content/EN/TXT/HTML/?uri=CELEX:31964D0344 | https://eur-lex.europa.eu/legal-content/EN/TXT/PDF/?uri=CELEX:31964D0344 | https://eur-lex.europa.eu/legal-content/DE/TXT/HTML/?uri=CELEX:31964D0344 | https://eur-lex.europa.eu/legal-content/DE/TXT/PDF/?uri=CELEX:31964D0344 | Q3: /home/edik/projects/eccjeu/data/raw/com_legacy/files/html/31964D0344_DE.html | /home/edik/projects/eccjeu/data/raw/com_legacy/files/pdfs/31964D0344_DE.pdf | R3: /home/edik/projects/eccjeu/data/raw/com_legacy/files/html/31964D0344_DE.html | /home/edik/projects/eccjeu/data/raw/com_legacy/files/pdfs/31964D0344_DE.pdf | S3: /home/edik/projects/eccjeu/input/andrea_input.csv | /home/edik/projects/eccjeu/output/com_legacy/download_case_manifest.csv
A4: 23588 | B4: =YEAR(A4) -> 1964 | C4: 95 | D4: Negative Clearance | not_exclusion_candidate | Negative Clearance Decision | E4: Nicholas Frères & Vitapro | Nicholas Freres/Vitapro | Nicholas Freres | Vitapro | F4: andrea | com_db_comp | com_legacy | G4: 3 | 1801 | com_legacy_1964_line_8 | H4: andrea:3 | com_db_comp:1801 | com_legacy:com_legacy_1964_line_8 | I4: 95 | IV/95 | J4: 1964/07/30/95 | K4: 1964/07/30/95/andrea | 1964/07/30/95/com_db_comp | 1964/07/30/95/com_legacy | L4: TRUE | M4: TRUE | N4: reference_only | already_downloaded | O4: https://db-comp.eu/document_1801.download | http://ec.europa.eu/competition/antitrust/closed/en/1964.html | P4: https://db-comp.eu/document_1801.download | https://eur-lex.europa.eu/legal-content/EN/TXT/HTML/?uri=CELEX:31964D0502 | https://eur-lex.europa.eu/legal-content/EN/TXT/PDF/?uri=CELEX:31964D0502 | https://eur-lex.europa.eu/legal-content/DE/TXT/HTML/?uri=CELEX:31964D0502 | https://eur-lex.europa.eu/legal-content/DE/TXT/PDF/?uri=CELEX:31964D0502 | Q4: /home/edik/projects/eccjeu/data/raw/com_db_comp/files/00093-EMO-_Dec-1988_.pdf | /home/edik/projects/eccjeu/data/raw/com_legacy/files/html/31964D0502_DE.html | /home/edik/projects/eccjeu/data/raw/com_legacy/files/pdfs/31964D0502_DE.pdf | R4: /home/edik/projects/eccjeu/data/raw/com_db_comp/files/00093-EMO-_Dec-1988_.pdf | /home/edik/projects/eccjeu/data/raw/com_legacy/files/html/31964D0502_DE.html | /home/edik/projects/eccjeu/data/raw/com_legacy/files/pdfs/31964D0502_DE.pdf | S4: /home/edik/projects/eccjeu/input/andrea_input.csv | /home/edik/projects/eccjeu/output/com_db_comp/db_comp_metadata_manifest.csv | /home/edik/projects/eccjeu/output/com_legacy/download_case_manifest.csv
A5: 23643 | B5: =YEAR(A5) -> 1964 | C5: 3344; 4 | D5: Infringement | Prohibition Decision | E5: Grundig-Consten | F5: andrea | com_legacy | G5: 4 | com_legacy_1964_line_5 | H5: andrea:4 | com_legacy:com_legacy_1964_line_5 | I5: 3344 | IV/3344 | IV/4 | J5: 1964/09/23/3344 | 1964/09/23/4/3344 | K5: 1964/09/23/3344/andrea | 1964/09/23/4/3344/com_legacy | L5: TRUE | M5: TRUE | N5: reference_only | already_downloaded | O5: http://ec.europa.eu/competition/antitrust/closed/en/1964.html | P5: https://eur-lex.europa.eu/legal-content/EN/TXT/HTML/?uri=CELEX:31964D0566 | https://eur-lex.europa.eu/legal-content/EN/TXT/PDF/?uri=CELEX:31964D0566 | https://eur-lex.europa.eu/legal-content/DE/TXT/HTML/?uri=CELEX:31964D0566 | https://eur-lex.europa.eu/legal-content/DE/TXT/PDF/?uri=CELEX:31964D0566 | Q5: /home/edik/projects/eccjeu/data/raw/com_legacy/files/html/31964D0566_DE.html | /home/edik/projects/eccjeu/data/raw/com_legacy/files/pdfs/31964D0566_DE.pdf | R5: /home/edik/projects/eccjeu/data/raw/com_legacy/files/html/31964D0566_DE.html | /home/edik/projects/eccjeu/data/raw/com_legacy/files/pdfs/31964D0566_DE.pdf | S5: /home/edik/projects/eccjeu/input/andrea_input.csv | /home/edik/projects/eccjeu/output/com_legacy/download_case_manifest.csv
A6: 23672 | B6: =YEAR(A6) -> 1964 | C6: 71 | D6: Negative Clearance | Negative Clearance Decision | E6: Deca | F6: andrea | com_legacy | G6: 5 | com_legacy_1964_line_2 | H6: andrea:5 | com_legacy:com_legacy_1964_line_2 | I6: 71 | IV/71 | J6: 1964/10/22/71 | K6: 1964/10/22/71/andrea | 1964/10/22/71/com_legacy | L6: TRUE | M6: TRUE | N6: reference_only | already_downloaded | O6: http://ec.europa.eu/competition/antitrust/closed/en/1964.html | P6: https://eur-lex.europa.eu/legal-content/EN/TXT/HTML/?uri=CELEX:31964D0599 | https://eur-lex.europa.eu/legal-content/EN/TXT/PDF/?uri=CELEX:31964D0599 | https://eur-lex.europa.eu/legal-content/DE/TXT/HTML/?uri=CELEX:31964D0599 | https://eur-lex.europa.eu/legal-content/DE/TXT/PDF/?uri=CELEX:31964D0599 | Q6: /home/edik/projects/eccjeu/data/raw/com_legacy/files/html/31964D0599_DE.html | /home/edik/projects/eccjeu/data/raw/com_legacy/files/pdfs/31964D0599_DE.pdf | R6: /home/edik/projects/eccjeu/data/raw/com_legacy/files/html/31964D0599_DE.html | /home/edik/projects/eccjeu/data/raw/com_legacy/files/pdfs/31964D0599_DE.pdf | S6: /home/edik/projects/eccjeu/input/andrea_input.csv | /home/edik/projects/eccjeu/output/com_legacy/download_case_manifest.csv
A7: 23931 | B7: =YEAR(A7) -> 1965 | C7: 3036 | D7: Exemption | not_exclusion_candidate | Exemption Decision | E7: Dru-Blondel | D.R.U./Blondel | F7: andrea | com_db_comp | com_legacy | G7: 6 | 1754 | com_legacy_1965_line_8 | H7: andrea:6 | com_db_comp:1754 | com_legacy:com_legacy_1965_line_8 | I7: 3036 | IV/3036 | J7: 1965/08/07/3036 | K7: 1965/08/07/3036/andrea | 1965/08/07/3036/com_db_comp | 1965/08/07/3036/com_legacy | L7: TRUE | M7: TRUE | N7: reference_only | already_downloaded | O7: https://db-comp.eu/document_1754.download | http://ec.europa.eu/competition/antitrust/closed/en/1965.html | P7: https://db-comp.eu/document_1754.download | https://eur-lex.europa.eu/legal-content/EN/TXT/HTML/?uri=CELEX:31965D0366 | https://eur-lex.europa.eu/legal-content/EN/TXT/PDF/?uri=CELEX:31965D0366 | https://eur-lex.europa.eu/legal-content/DE/TXT/HTML/?uri=CELEX:31965D0366 | https://eur-lex.europa.eu/legal-content/DE/TXT/PDF/?uri=CELEX:31965D0366 | http://ec.europa.eu/competition/search.html | http://ec.europa.eu/competition/antitrust/closed/en/1965.html#top | Q7: /home/edik/projects/eccjeu/data/raw/com_db_comp/files/3036-D.R.U.-Blondel-_July-1965_.pdf | /home/edik/projects/eccjeu/data/raw/com_legacy/files/html/31965D0366_DE.html | /home/edik/projects/eccjeu/data/raw/com_legacy/files/pdfs/31965D0366_DE.pdf | /home/edik/projects/eccjeu/data/raw/com_legacy/files/html/search.html | /home/edik/projects/eccjeu/data/raw/com_legacy/files/html/1965.html | R7: /home/edik/projects/eccjeu/data/raw/com_db_comp/files/3036-D.R.U.-Blondel-_July-1965_.pdf | /home/edik/projects/eccjeu/data/raw/com_legacy/files/html/31965D0366_DE.html | /home/edik/projects/eccjeu/data/raw/com_legacy/files/pdfs/31965D0366_DE.pdf | /home/edik/projects/eccjeu/data/raw/com_legacy/files/html/search.html | /home/edik/projects/eccjeu/data/raw/com_legacy/files/html/1965.html | S7: /home/edik/projects/eccjeu/input/andrea_input.csv | /home/edik/projects/eccjeu/output/com_db_comp/db_comp_metadata_manifest.csv | /home/edik/projects/eccjeu/output/com_legacy/download_case_manifest.csv
A8: 24002 | B8: =YEAR(A8) -> 1965 | C8: 2702 | D8: Exemption | Exemption Decision | E8: Hummel-Isbecque | Hummel - Isbecque | F8: andrea | com_legacy | G8: 7 | com_legacy_1965_line_5 | H8: andrea:7 | com_legacy:com_legacy_1965_line_5 | I8: 2702 | IV/2702 | J8: 1965/09/17/2702 | K8: 1965/09/17/2702/andrea | 1965/09/17/2702/com_legacy | L8: TRUE | M8: TRUE | N8: reference_only | already_downloaded | O8: http://ec.europa.eu/competition/antitrust/closed/en/1965.html | P8: https://eur-lex.europa.eu/legal-content/EN/TXT/HTML/?uri=CELEX:31965D0426 | https://eur-lex.europa.eu/legal-content/EN/TXT/PDF/?uri=CELEX:31965D0426 | https://eur-lex.europa.eu/legal-content/DE/TXT/HTML/?uri=CELEX:31965D0426 | https://eur-lex.europa.eu/legal-content/DE/TXT/PDF/?uri=CELEX:31965D0426 | Q8: /home/edik/projects/eccjeu/data/raw/com_legacy/files/html/31965D0426_DE.html | /home/edik/projects/eccjeu/data/raw/com_legacy/files/pdfs/31965D0426_DE.pdf | R8: /home/edik/projects/eccjeu/data/raw/com_legacy/files/html/31965D0426_DE.html | /home/edik/projects/eccjeu/data/raw/com_legacy/files/pdfs/31965D0426_DE.pdf | S8: /home/edik/projects/eccjeu/input/andrea_input.csv | /home/edik/projects/eccjeu/output/com_legacy/download_case_manifest.csv
A9: 24093 | B9: =YEAR(A9) -> 1965 | C9: 22491 | D9: Exemption | Exemption Decision | E9: Maison Jallatte | Maison Jalatte | F9: andrea | com_legacy | G9: 8 | com_legacy_1965_line_2 | H9: andrea:8 | com_legacy:com_legacy_1965_line_2 | I9: 22491 | IV/22491 | J9: 1965/12/17/22491 | K9: 1965/12/17/22491/andrea | 1965/12/17/22491/com_legacy | L9: TRUE | M9: TRUE | N9: reference_only | already_downloaded | O9: http://ec.europa.eu/competition/antitrust/closed/en/1965.html | P9: https://eur-lex.europa.eu/legal-content/EN/TXT/HTML/?uri=CELEX:31966D0005 | https://eur-lex.europa.eu/legal-content/EN/TXT/PDF/?uri=CELEX:31966D0005 | https://eur-lex.europa.eu/legal-content/DE/TXT/HTML/?uri=CELEX:31966D0005 | https://eur-lex.europa.eu/legal-content/DE/TXT/PDF/?uri=CELEX:31966D0005 | Q9: /home/edik/projects/eccjeu/data/raw/com_legacy/files/html/31966D0005_DE.html | /home/edik/projects/eccjeu/data/raw/com_legacy/files/pdfs/31966D0005_DE.pdf | R9: /home/edik/projects/eccjeu/data/raw/com_legacy/files/html/31966D0005_DE.html | /home/edik/projects/eccjeu/data/raw/com_legacy/files/pdfs/31966D0005_DE.pdf | S9: /home/edik/projects/eccjeu/input/andrea_input.csv | /home/edik/projects/eccjeu/output/com_legacy/download_case_manifest.csv
A10: 24650 | B10: =YEAR(A10) -> 1967 | C10: 223 | D10: Exemption | Exemption Decision | E10: Transocean Marine Paint Association | F10: andrea | com_legacy | G10: 9 | com_legacy_1967_line_2 | H10: andrea:9 | com_legacy:com_legacy_1967_line_2 | I10: 223 | IV/223 | J10: 1967/06/27/223 | K10: 1967/06/27/223/andrea | 1967/06/27/223/com_legacy | L10: TRUE | M10: TRUE | N10: reference_only | already_downloaded | O10: http://ec.europa.eu/competition/antitrust/closed/en/1967.html | P10: https://eur-lex.europa.eu/legal-content/EN/TXT/HTML/?uri=CELEX:31967D0454 | https://eur-lex.europa.eu/legal-content/EN/TXT/PDF/?uri=CELEX:31967D0454 | https://eur-lex.europa.eu/legal-content/DE/TXT/HTML/?uri=CELEX:31967D0454 | https://eur-lex.europa.eu/legal-content/DE/TXT/PDF/?uri=CELEX:31967D0454 | http://ec.europa.eu/competition/search.html | http://ec.europa.eu/competition/antitrust/closed/en/1967.html#top | Q10: /home/edik/projects/eccjeu/data/raw/com_legacy/files/html/31967D0454_DE.html | /home/edik/projects/eccjeu/data/raw/com_legacy/files/pdfs/31967D0454_DE.pdf | /home/edik/projects/eccjeu/data/raw/com_legacy/files/html/search.html | /home/edik/projects/eccjeu/data/raw/com_legacy/files/html/1967.html | R10: /home/edik/projects/eccjeu/data/raw/com_legacy/files/html/31967D0454_DE.html | /home/edik/projects/eccjeu/data/raw/com_legacy/files/pdfs/31967D0454_DE.pdf | /home/edik/projects/eccjeu/data/raw/com_legacy/files/html/search.html | /home/edik/projects/eccjeu/data/raw/com_legacy/files/html/1967.html | S10: /home/edik/projects/eccjeu/input/andrea_input.csv | /home/edik/projects/eccjeu/output/com_legacy/download_case_manifest.csv
A11: 24894 | B11: =YEAR(A11) -> 1968 | C11: 26352 | D11: Negative Clearance | Negative Clearance Decision | E11: Eurogypsum | F11: andrea | com_legacy | G11: 10 | com_legacy_1968_line_23 | H11: andrea:10 | com_legacy:com_legacy_1968_line_23 | I11: 26352 | IV/26352 | J11: 1968/02/26/26352 | K11: 1968/02/26/26352/andrea | 1968/02/26/26352/com_legacy | L11: TRUE | M11: TRUE | N11: reference_only | already_downloaded | O11: http://ec.europa.eu/competition/antitrust/closed/en/1968.html | P11: https://eur-lex.europa.eu/legal-content/EN/TXT/HTML/?uri=CELEX:31968D0128 | https://eur-lex.europa.eu/legal-content/EN/TXT/PDF/?uri=CELEX:31968D0128 | https://eur-lex.europa.eu/legal-content/DE/TXT/HTML/?uri=CELEX:31968D0128 | https://eur-lex.europa.eu/legal-content/DE/TXT/PDF/?uri=CELEX:31968D0128 | http://ec.europa.eu/competition/search.html | http://ec.europa.eu/competition/antitrust/closed/en/1968.html#top | Q11: /home/edik/projects/eccjeu/data/raw/com_legacy/files/html/31968D0128_DE.html | /home/edik/projects/eccjeu/data/raw/com_legacy/files/pdfs/31968D0128_DE.pdf | /home/edik/projects/eccjeu/data/raw/com_legacy/files/html/search.html | /home/edik/projects/eccjeu/data/raw/com_legacy/files/html/1968.html | R11: /home/edik/projects/eccjeu/data/raw/com_legacy/files/html/31968D0128_DE.html | /home/edik/projects/eccjeu/data/raw/com_legacy/files/pdfs/31968D0128_DE.pdf | /home/edik/projects/eccjeu/data/raw/com_legacy/files/html/search.html | /home/edik/projects/eccjeu/data/raw/com_legacy/files/html/1968.html | S11: /home/edik/projects/eccjeu/input/andrea_input.csv | /home/edik/projects/eccjeu/output/com_legacy/download_case_manifest.csv
A12: 25036 | B12: =YEAR(A12) -> 1968 | C12: 129 | D12: Negative Clearance | Negative Clearance Decision | E12: Socemas | F12: andrea | com_legacy | G12: 12 | com_legacy_1968_line_20 | H12: andrea:12 | com_legacy:com_legacy_1968_line_20 | I12: 129 | IV/129 | J12: 1968/07/17/129 | K12: 1968/07/17/129/andrea | 1968/07/17/129/com_legacy | L12: TRUE | M12: TRUE | N12: reference_only | already_downloaded | O12: http://ec.europa.eu/competition/antitrust/closed/en/1968.html | P12: https://eur-lex.europa.eu/legal-content/EN/TXT/HTML/?uri=CELEX:31968D0318 | https://eur-lex.europa.eu/legal-content/EN/TXT/PDF/?uri=CELEX:31968D0318 | https://eur-lex.europa.eu/legal-content/DE/TXT/HTML/?uri=CELEX:31968D0318 | https://eur-lex.europa.eu/legal-content/DE/TXT/PDF/?uri=CELEX:31968D0318 | Q12: /home/edik/projects/eccjeu/data/raw/com_legacy/files/html/31968D0318_DE.html | /home/edik/projects/eccjeu/data/raw/com_legacy/files/pdfs/31968D0318_DE.pdf | R12: /home/edik/projects/eccjeu/data/raw/com_legacy/files/html/31968D0318_DE.html | /home/edik/projects/eccjeu/data/raw/com_legacy/files/pdfs/31968D0318_DE.pdf | S12: /home/edik/projects/eccjeu/input/andrea_input.csv | /home/edik/projects/eccjeu/output/com_legacy/download_case_manifest.csv
A13: 25036 | B13: =YEAR(A13) -> 1968 | C13: 25140 | D13: Negative Clearance | Negative Clearance Decision | E13: Alliance Constructeurs Francais de Machines-Outils | Constructeurs Français de Machines-Outils | F13: andrea | com_legacy | G13: 11 | com_legacy_1968_line_17 | H13: andrea:11 | com_legacy:com_legacy_1968_line_17 | I13: 25140 | IV/25140 | J13: 1968/07/17/25140 | K13: 1968/07/17/25140/andrea | 1968/07/17/25140/com_legacy | L13: TRUE | M13: TRUE | N13: reference_only | already_downloaded | O13: http://ec.europa.eu/competition/antitrust/closed/en/1968.html | P13: https://eur-lex.europa.eu/legal-content/EN/TXT/HTML/?uri=CELEX:31968D0317 | https://eur-lex.europa.eu/legal-content/EN/TXT/PDF/?uri=CELEX:31968D0317 | https://eur-lex.europa.eu/legal-content/DE/TXT/HTML/?uri=CELEX:31968D0317 | https://eur-lex.europa.eu/legal-content/DE/TXT/PDF/?uri=CELEX:31968D0317 | Q13: /home/edik/projects/eccjeu/data/raw/com_legacy/files/html/31968D0317_DE.html | /home/edik/projects/eccjeu/data/raw/com_legacy/files/pdfs/31968D0317_DE.pdf | R13: /home/edik/projects/eccjeu/data/raw/com_legacy/files/html/31968D0317_DE.html | /home/edik/projects/eccjeu/data/raw/com_legacy/files/pdfs/31968D0317_DE.pdf | S13: /home/edik/projects/eccjeu/input/andrea_input.csv | /home/edik/projects/eccjeu/output/com_legacy/download_case_manifest.csv
... A173: 29929 | B173: =YEAR(A173) -> 1981 | C173: 30307 | D173: Infringement | Procedural Decision | E173: FIRE INSURANCE (D) | F173: andrea | com_legacy | G173: 170 | com_legacy_1981_line_11 | H173: andrea:170 | com_legacy:com_legacy_1981_line_11 | I173: 30307 | IV/30307 | J173: 1981/09/12/30307 | K173: 1981/09/12/30307/andrea | 1981/09/12/30307/com_legacy | L173: TRUE | M173: TRUE | N173: reference_only | already_downloaded | O173: http://ec.europa.eu/competition/antitrust/closed/en/1981.html | P173: https://eur-lex.europa.eu/legal-content/EN/TXT/HTML/?uri=CELEX:31982D0174 | https://eur-lex.europa.eu/legal-content/EN/TXT/PDF/?uri=CELEX:31982D0174 | https://eur-lex.europa.eu/legal-content/DE/TXT/HTML/?uri=CELEX:31982D0174 | https://eur-lex.europa.eu/legal-content/DE/TXT/PDF/?uri=CELEX:31982D0174 | Q173: /home/edik/projects/eccjeu/data/raw/com_legacy/files/html/31982D0174_EN.html | /home/edik/projects/eccjeu/data/raw/com_legacy/files/pdfs/31982D0174_EN.pdf | /home/edik/projects/eccjeu/data/raw/com_legacy/files/html/31982D0174_DE.html | R173: /home/edik/projects/eccjeu/data/raw/com_legacy/files/html/31982D0174_EN.html | /home/edik/projects/eccjeu/data/raw/com_legacy/files/pdfs/31982D0174_EN.pdf | /home/edik/projects/eccjeu/data/raw/com_legacy/files/html/31982D0174_DE.html | S173: /home/edik/projects/eccjeu/input/andrea_input.csv | /home/edik/projects/eccjeu/output/com_legacy/download_case_manifest.csv
A174: 29931 | B174: =YEAR(A174) -> 1981 | C174: 511 | D174: Infringement | E174: National Panasonic France | F174: andrea | manual | G174: 172 | manual_000001 | H174: andrea:172 | manual:manual_000001 | I174: 511 | IV/511 | J174: 1981/11/12/511 | K174: 1981/11/12/511/andrea | 1981/11/12/511/manual | L174: TRUE | M174: FALSE | N174: reference_only | manual_injection | P174: https://eur-lex.europa.eu/legal-content/EN/TXT/HTML/?uri=CELEX:31982D0465&qid=1783330337429 | S174: /home/edik/projects/eccjeu/input/andrea_input.csv | /home/edik/projects/eccjeu/input/commission_manual_injection.csv
A175: 29931 | B175: =YEAR(A175) -> 1981 | C175: 512 | D175: Infringement | Decision imposing fines | E175: National Panasonic (Belgique) | Panasonic (France) | F175: andrea | com_legacy | G175: 171 | com_legacy_1981_line_5 | com_legacy_1981_line_8 | H175: andrea:171 | com_legacy:com_legacy_1981_line_5 | com_legacy:com_legacy_1981_line_8 | I175: 512 | IV/512 | J175: 1981/11/12/512 | K175: 1981/11/12/512/andrea | 1981/11/12/512/com_legacy | L175: TRUE | M175: TRUE | N175: reference_only | already_downloaded | O175: http://ec.europa.eu/competition/antitrust/closed/en/1981.html | P175: https://eur-lex.europa.eu/legal-content/EN/TXT/HTML/?uri=CELEX:31982D0260 | https://eur-lex.europa.eu/legal-content/EN/TXT/PDF/?uri=CELEX:31982D0260 | https://eur-lex.europa.eu/legal-content/DE/TXT/HTML/?uri=CELEX:31982D0260 | https://eur-lex.europa.eu/legal-content/DE/TXT/PDF/?uri=CELEX:31982D0260 | https://eur-lex.europa.eu/legal-content/EN/TXT/HTML/?uri=CELEX:31982D0465 | https://eur-lex.europa.eu/legal-content/EN/TXT/PDF/?uri=CELEX:31982D0465 | https://eur-lex.europa.eu/legal-content/DE/TXT/HTML/?uri=CELEX:31982D0465 | https://eur-lex.europa.eu/legal-content/DE/TXT/PDF/?uri=CELEX:31982D0465 | Q175: /home/edik/projects/eccjeu/data/raw/com_legacy/files/html/31982D0260_EN.html | /home/edik/projects/eccjeu/data/raw/com_legacy/files/pdfs/31982D0260_EN.pdf | /home/edik/projects/eccjeu/data/raw/com_legacy/files/html/31982D0260_DE.html | /home/edik/projects/eccjeu/data/raw/com_legacy/files/html/31982D0465_EN.html | /home/edik/projects/eccjeu/data/raw/com_legacy/files/pdfs/31982D0465_EN.pdf | /home/edik/projects/eccjeu/data/raw/com_legacy/files/html/31982D0465_DE.html | R175: /home/edik/projects/eccjeu/data/raw/com_legacy/files/html/31982D0260_EN.html | /home/edik/projects/eccjeu/data/raw/com_legacy/files/pdfs/31982D0260_EN.pdf | /home/edik/projects/eccjeu/data/raw/com_legacy/files/html/31982D0260_DE.html | /home/edik/projects/eccjeu/data/raw/com_legacy/files/html/31982D0465_EN.html | /home/edik/projects/eccjeu/data/raw/com_legacy/files/pdfs/31982D0465_EN.pdf | /home/edik/projects/eccjeu/data/raw/com_legacy/files/html/31982D0465_DE.html | S175: /home/edik/projects/eccjeu/input/andrea_input.csv | /home/edik/projects/eccjeu/output/com_legacy/download_case_manifest.csv
A176: 29937 | B176: =YEAR(A176) -> 1981 | C176: 29995 | D176: Infringement | not_exclusion_candidate | Prohibition Decision | E176: NAVEWA - ANSEAU | NA VEWA-ANSEAU | NAVEWA-ANSEAU | F176: andrea | com_db_comp | com_legacy | G176: 173 | 1622 | com_legacy_1981_line_2 | H176: andrea:173 | com_db_comp:1622 | com_legacy:com_legacy_1981_line_2 | I176: 29995 | IV/29995 | J176: 1981/12/17/29995 | K176: 1981/12/17/29995/andrea | 1981/12/17/29995/com_db_comp | 1981/12/17/29995/com_legacy | L176: TRUE | M176: TRUE | N176: reference_only | already_downloaded | O176: https://db-comp.eu/document_1622.download | http://ec.europa.eu/competition/antitrust/closed/en/1981.html | P176: https://db-comp.eu/document_1622.download | https://eur-lex.europa.eu/legal-content/EN/TXT/HTML/?uri=CELEX:31982D0371 | https://eur-lex.europa.eu/legal-content/EN/TXT/PDF/?uri=CELEX:31982D0371 | https://eur-lex.europa.eu/legal-content/DE/TXT/HTML/?uri=CELEX:31982D0371 | https://eur-lex.europa.eu/legal-content/DE/TXT/PDF/?uri=CELEX:31982D0371 | Q176: /home/edik/projects/eccjeu/data/raw/com_db_comp/files/29995-NAVEWA-ANSEAU-_Dec-1981_.pdf | /home/edik/projects/eccjeu/data/raw/com_legacy/files/html/31982D0371_EN.html | /home/edik/projects/eccjeu/data/raw/com_legacy/files/pdfs/31982D0371_EN.pdf | /home/edik/projects/eccjeu/data/raw/com_legacy/files/html/31982D0371_DE.html | R176: /home/edik/projects/eccjeu/data/raw/com_db_comp/files/29995-NAVEWA-ANSEAU-_Dec-1981_.pdf | /home/edik/projects/eccjeu/data/raw/com_legacy/files/html/31982D0371_EN.html | /home/edik/projects/eccjeu/data/raw/com_legacy/files/pdfs/31982D0371_EN.pdf | /home/edik/projects/eccjeu/data/raw/com_legacy/files/html/31982D0371_DE.html | S176: /home/edik/projects/eccjeu/input/andrea_input.csv | /home/edik/projects/eccjeu/output/com_db_comp/db_comp_metadata_manifest.csv | /home/edik/projects/eccjeu/output/com_legacy/download_case_manifest.csv
A177: 29957 | B177: =YEAR(A177) -> 1982 | C177: 28748 | D177: Infringement | not_exclusion_candidate | Prohibition Decision | E177: AEG-Telefunken | AEG - Telefunken | F177: andrea | com_db_comp | com_legacy | G177: 174 | 1677 | com_legacy_1982_line_38 | H177: andrea:174 | com_db_comp:1677 | com_legacy:com_legacy_1982_line_38 | I177: 28748 | IV/28748 | J177: 1982/06/01/28748 | K177: 1982/06/01/28748/andrea | 1982/06/01/28748/com_db_comp | 1982/06/01/28748/com_legacy | L177: TRUE | M177: TRUE | N177: reference_only | already_downloaded | O177: https://db-comp.eu/document_1677.download | http://ec.europa.eu/competition/antitrust/closed/en/1982.html | P177: https://db-comp.eu/document_1677.download | https://eur-lex.europa.eu/legal-content/EN/TXT/HTML/?uri=CELEX:31982D0267 | https://eur-lex.europa.eu/legal-content/EN/TXT/PDF/?uri=CELEX:31982D0267 | https://eur-lex.europa.eu/legal-content/DE/TXT/HTML/?uri=CELEX:31982D0267 | https://eur-lex.europa.eu/legal-content/DE/TXT/PDF/?uri=CELEX:31982D0267 | http://ec.europa.eu/competition/search.html | http://ec.europa.eu/competition/antitrust/closed/en/1982.html#top | Q177: /home/edik/projects/eccjeu/data/raw/com_db_comp/files/28748-AEG-Telefunken-_Jan-1982_.pdf | /home/edik/projects/eccjeu/data/raw/com_legacy/files/html/31982D0267_EN.html | /home/edik/projects/eccjeu/data/raw/com_legacy/files/pdfs/31982D0267_EN.pdf | /home/edik/projects/eccjeu/data/raw/com_legacy/files/html/31982D0267_DE.html | /home/edik/projects/eccjeu/data/raw/com_legacy/files/html/search.html | /home/edik/projects/eccjeu/data/raw/com_legacy/files/html/1982.html | R177: /home/edik/projects/eccjeu/data/raw/com_db_comp/files/28748-AEG-Telefunken-_Jan-1982_.pdf | /home/edik/projects/eccjeu/data/raw/com_legacy/files/html/31982D0267_EN.html | /home/edik/projects/eccjeu/data/raw/com_legacy/files/pdfs/31982D0267_EN.pdf | /home/edik/projects/eccjeu/data/raw/com_legacy/files/html/31982D0267_DE.html | /home/edik/projects/eccjeu/data/raw/com_legacy/files/html/search.html | /home/edik/projects/eccjeu/data/raw/com_legacy/files/html/1982.html | S177: /home/edik/projects/eccjeu/input/andrea_input.csv | /home/edik/projects/eccjeu/output/com_db_comp/db_comp_metadata_manifest.csv | /home/edik/projects/eccjeu/output/com_legacy/download_case_manifest.csv
A178: 30071 | B178: =YEAR(A178) -> 1982 | C178: 417 | D178: Exemption | Exemption Decision | E178: BPICA | F178: andrea | com_legacy | G178: 175 | com_legacy_1982_line_35 | H178: andrea:175 | com_legacy:com_legacy_1982_line_35 | I178: 417 | IV/417 | J178: 1982/04/30/417 | K178: 1982/04/30/417/andrea | 1982/04/30/417/com_legacy | L178: TRUE | M178: TRUE | N178: reference_only | already_downloaded | O178: http://ec.europa.eu/competition/antitrust/closed/en/1982.html | P178: https://eur-lex.europa.eu/legal-content/EN/TXT/HTML/?uri=CELEX:31982D0349 | https://eur-lex.europa.eu/legal-content/EN/TXT/PDF/?uri=CELEX:31982D0349 | https://eur-lex.europa.eu/legal-content/DE/TXT/HTML/?uri=CELEX:31982D0349 | https://eur-lex.europa.eu/legal-content/DE/TXT/PDF/?uri=CELEX:31982D0349 | Q178: /home/edik/projects/eccjeu/data/raw/com_legacy/files/html/31982D0349_EN.html | /home/edik/projects/eccjeu/data/raw/com_legacy/files/pdfs/31982D0349_EN.pdf | /home/edik/projects/eccjeu/data/raw/com_legacy/files/html/31982D0349_DE.html | R178: /home/edik/projects/eccjeu/data/raw/com_legacy/files/html/31982D0349_EN.html | /home/edik/projects/eccjeu/data/raw/com_legacy/files/pdfs/31982D0349_EN.pdf | /home/edik/projects/eccjeu/data/raw/com_legacy/files/html/31982D0349_DE.html | S178: /home/edik/projects/eccjeu/input/andrea_input.csv | /home/edik/projects/eccjeu/output/com_legacy/download_case_manifest.csv
A179: 30147 | B179: =YEAR(A179) -> 1982 | C179: 29525; 30000 | D179: Infringement | not_exclusion_candidate | Prohibition Decision | E179: SSI | F179: andrea | com_db_comp | com_legacy | G179: 176 | 1638 | com_legacy_1982_line_32 | H179: andrea:176 | com_db_comp:1638 | com_legacy:com_legacy_1982_line_32 | I179: 29525, 30000 | 29525 | 30000 | IV/29525 | IV/30000 | J179: 1982/07/15/29525/30000 | K179: 1982/07/15/29525/30000/andrea | 1982/07/15/29525/30000/com_db_comp | 1982/07/15/29525/30000/com_legacy | L179: TRUE | M179: TRUE | N179: reference_only | already_downloaded | O179: https://db-comp.eu/document_1638.download | http://ec.europa.eu/competition/antitrust/closed/en/1982.html | P179: https://db-comp.eu/document_1638.download | https://eur-lex.europa.eu/legal-content/EN/TXT/HTML/?uri=CELEX:31982D0506 | https://eur-lex.europa.eu/legal-content/EN/TXT/PDF/?uri=CELEX:31982D0506 | https://eur-lex.europa.eu/legal-content/DE/TXT/HTML/?uri=CELEX:31982D0506 | https://eur-lex.europa.eu/legal-content/DE/TXT/PDF/?uri=CELEX:31982D0506 | Q179: /home/edik/projects/eccjeu/data/raw/com_db_comp/files/29525-30000-SSI-_July-1982_.pdf | /home/edik/projects/eccjeu/data/raw/com_legacy/files/html/31982D0506_EN.html | /home/edik/projects/eccjeu/data/raw/com_legacy/files/pdfs/31982D0506_EN.pdf | /home/edik/projects/eccjeu/data/raw/com_legacy/files/html/31982D0506_DE.html | R179: /home/edik/projects/eccjeu/data/raw/com_db_comp/files/29525-30000-SSI-_July-1982_.pdf | /home/edik/projects/eccjeu/data/raw/com_legacy/files/html/31982D0506_EN.html | /home/edik/projects/eccjeu/data/raw/com_legacy/files/pdfs/31982D0506_EN.pdf | /home/edik/projects/eccjeu/data/raw/com_legacy/files/html/31982D0506_DE.html | S179: /home/edik/projects/eccjeu/input/andrea_input.csv | /home/edik/projects/eccjeu/output/com_db_comp/db_comp_metadata_manifest.csv | /home/edik/projects/eccjeu/output/com_legacy/download_case_manifest.csv
A180: 30181 | B180: =YEAR(A180) -> 1982 | C180: 30696 | D180: Interim Measures Decision | E180: FORD WERKE AG. | F180: com_legacy | G180: com_legacy_1982_line_29 | H180: com_legacy:com_legacy_1982_line_29 | I180: IV/30696 | J180: 1982/08/18/30696 | K180: 1982/08/18/30696/com_legacy | L180: TRUE | M180: TRUE | N180: already_downloaded | O180: http://ec.europa.eu/competition/antitrust/closed/en/1982.html | P180: https://eur-lex.europa.eu/legal-content/EN/TXT/HTML/?uri=CELEX:31982D0628 | https://eur-lex.europa.eu/legal-content/EN/TXT/PDF/?uri=CELEX:31982D0628 | https://eur-lex.europa.eu/legal-content/DE/TXT/HTML/?uri=CELEX:31982D0628 | https://eur-lex.europa.eu/legal-content/DE/TXT/PDF/?uri=CELEX:31982D0628 | Q180: /home/edik/projects/eccjeu/data/raw/com_legacy/files/html/31982D0628_EN.html | /home/edik/projects/eccjeu/data/raw/com_legacy/files/pdfs/31982D0628_EN.pdf | R180: /home/edik/projects/eccjeu/data/raw/com_legacy/files/html/31982D0628_EN.html | /home/edik/projects/eccjeu/data/raw/com_legacy/files/pdfs/31982D0628_EN.pdf | S180: /home/edik/projects/eccjeu/output/com_legacy/download_case_manifest.csv
A181: 30251 | B181: =YEAR(A181) -> 1982 | C181: 528 | D181: Infringement | Decision imposing fines | E181: Federation Nationale Chaussure de France | F181: andrea | com_legacy | G181: 177 | com_legacy_1982_line_26 | H181: andrea:177 | com_legacy:com_legacy_1982_line_26 | I181: 528 | IV/528 | J181: 1982/10/27/528 | K181: 1982/10/27/528/andrea | 1982/10/27/528/com_legacy | L181: TRUE | M181: TRUE | N181: reference_only | already_downloaded | O181: http://ec.europa.eu/competition/antitrust/closed/en/1982.html | P181: https://eur-lex.europa.eu/legal-content/EN/TXT/HTML/?uri=CELEX:31982D0756 | https://eur-lex.europa.eu/legal-content/EN/TXT/PDF/?uri=CELEX:31982D0756 | https://eur-lex.europa.eu/legal-content/DE/TXT/HTML/?uri=CELEX:31982D0756 | https://eur-lex.europa.eu/legal-content/DE/TXT/PDF/?uri=CELEX:31982D0756 | Q181: /home/edik/projects/eccjeu/data/raw/com_legacy/files/html/31982D0756_EN.html | /home/edik/projects/eccjeu/data/raw/com_legacy/files/pdfs/31982D0756_EN.pdf | /home/edik/projects/eccjeu/data/raw/com_legacy/files/html/31982D0756_DE.html | R181: /home/edik/projects/eccjeu/data/raw/com_legacy/files/html/31982D0756_EN.html | /home/edik/projects/eccjeu/data/raw/com_legacy/files/pdfs/31982D0756_EN.pdf | /home/edik/projects/eccjeu/data/raw/com_legacy/files/html/31982D0756_DE.html | S181: /home/edik/projects/eccjeu/input/andrea_input.csv | /home/edik/projects/eccjeu/output/com_legacy/download_case_manifest.csv
A182: 30253 | B182: =YEAR(A182) -> 1982 | C182: 30517 | D182: Exemption | not_exclusion_candidate | Exemption Decision | E182: AMERSHAM BUCHLER | Amersham Buchler | F182: andrea | com_db_comp | com_legacy | G182: 178 | 1599 | com_legacy_1982_line_23 | H182: andrea:178 | com_db_comp:1599 | com_legacy:com_legacy_1982_line_23 | I182: 30517 | IV/30517 | J182: 1982/10/29/30517 | K182: 1982/10/29/30517/andrea | 1982/10/29/30517/com_db_comp | 1982/10/29/30517/com_legacy | L182: TRUE | M182: TRUE | N182: reference_only | already_downloaded | O182: https://db-comp.eu/document_1599.download | http://ec.europa.eu/competition/antitrust/closed/en/1982.html | P182: https://db-comp.eu/document_1599.download | https://eur-lex.europa.eu/legal-content/EN/TXT/HTML/?uri=CELEX:31982D0742 | https://eur-lex.europa.eu/legal-content/EN/TXT/PDF/?uri=CELEX:31982D0742 | https://eur-lex.europa.eu/legal-content/DE/TXT/HTML/?uri=CELEX:31982D0742 | https://eur-lex.europa.eu/legal-content/DE/TXT/PDF/?uri=CELEX:31982D0742 | Q182: /home/edik/projects/eccjeu/data/raw/com_db_comp/files/30517-Amersham-Buchler-_Oct-1982_.pdf | /home/edik/projects/eccjeu/data/raw/com_legacy/files/html/31982D0742_EN.html | /home/edik/projects/eccjeu/data/raw/com_legacy/files/pdfs/31982D0742_EN.pdf | /home/edik/projects/eccjeu/data/raw/com_legacy/files/html/31982D0742_DE.html | R182: /home/edik/projects/eccjeu/data/raw/com_db_comp/files/30517-Amersham-Buchler-_Oct-1982_.pdf | /home/edik/projects/eccjeu/data/raw/com_legacy/files/html/31982D0742_EN.html | /home/edik/projects/eccjeu/data/raw/com_legacy/files/pdfs/31982D0742_EN.pdf | /home/edik/projects/eccjeu/data/raw/com_legacy/files/html/31982D0742_DE.html | S182: /home/edik/projects/eccjeu/input/andrea_input.csv | /home/edik/projects/eccjeu/output/com_db_comp/db_comp_metadata_manifest.csv | /home/edik/projects/eccjeu/output/com_legacy/download_case_manifest.csv
A183: 30259 | B183: =YEAR(A183) -> 1982 | C183: 29995 | D183: Amending Decision | E183: NAVEWA-ANSEAU (BOSCH) | F183: com_legacy | G183: com_legacy_1982_line_20 | H183: com_legacy:com_legacy_1982_line_20 | I183: IV/29995 | J183: 1982/04/11/29995 | K183: 1982/04/11/29995/com_legacy | L183: TRUE | M183: TRUE | N183: already_downloaded | O183: http://ec.europa.eu/competition/antitrust/closed/en/1982.html | P183: https://eur-lex.europa.eu/legal-content/EN/TXT/HTML/?uri=CELEX:31982D0777 | https://eur-lex.europa.eu/legal-content/EN/TXT/PDF/?uri=CELEX:31982D0777 | https://eur-lex.europa.eu/legal-content/DE/TXT/HTML/?uri=CELEX:31982D0777 | https://eur-lex.europa.eu/legal-content/DE/TXT/PDF/?uri=CELEX:31982D0777 | Q183: /home/edik/projects/eccjeu/data/raw/com_legacy/files/html/31982D0777_EN.html | /home/edik/projects/eccjeu/data/raw/com_legacy/files/pdfs/31982D0777_EN.pdf | /home/edik/projects/eccjeu/data/raw/com_legacy/files/html/31982D0777_DE.html | R183: /home/edik/projects/eccjeu/data/raw/com_legacy/files/html/31982D0777_EN.html | /home/edik/projects/eccjeu/data/raw/com_legacy/files/pdfs/31982D0777_EN.pdf | /home/edik/projects/eccjeu/data/raw/com_legacy/files/html/31982D0777_DE.html | S183: /home/edik/projects/eccjeu/output/com_legacy/download_case_manifest.csv
A184: 30292 | B184: =YEAR(A184) -> 1982 | C184: 30070 | D184: Infringement | not_exclusion_candidate | Prohibition Decision | E184: National Panasonic | F184: andrea | com_db_comp | com_legacy | G184: 179 | 1618 | com_legacy_1982_line_17 | H184: andrea:179 | com_db_comp:1618 | com_legacy:com_legacy_1982_line_17 | I184: 30070 | IV/30070 | J184: 1982/07/12/30070 | K184: 1982/07/12/30070/andrea | 1982/07/12/30070/com_db_comp | 1982/07/12/30070/com_legacy | L184: TRUE | M184: TRUE | N184: reference_only | already_downloaded | O184: https://db-comp.eu/document_1618.download | http://ec.europa.eu/competition/antitrust/closed/en/1982.html | P184: https://db-comp.eu/document_1618.download | https://eur-lex.europa.eu/legal-content/EN/TXT/HTML/?uri=CELEX:31982D0853 | https://eur-lex.europa.eu/legal-content/EN/TXT/PDF/?uri=CELEX:31982D0853 | https://eur-lex.europa.eu/legal-content/DE/TXT/HTML/?uri=CELEX:31982D0853 | https://eur-lex.europa.eu/legal-content/DE/TXT/PDF/?uri=CELEX:31982D0853 | Q184: /home/edik/projects/eccjeu/data/raw/com_db_comp/files/30070-National-Panasonic-_Dec-1982_.pdf | /home/edik/projects/eccjeu/data/raw/com_legacy/files/html/31982D0853_EN.html | /home/edik/projects/eccjeu/data/raw/com_legacy/files/pdfs/31982D0853_EN.pdf | /home/edik/projects/eccjeu/data/raw/com_legacy/files/html/31982D0853_DE.html | R184: /home/edik/projects/eccjeu/data/raw/com_db_comp/files/30070-National-Panasonic-_Dec-1982_.pdf | /home/edik/projects/eccjeu/data/raw/com_legacy/files/html/31982D0853_EN.html | /home/edik/projects/eccjeu/data/raw/com_legacy/files/pdfs/31982D0853_EN.pdf | /home/edik/projects/eccjeu/data/raw/com_legacy/files/html/31982D0853_DE.html | S184: /home/edik/projects/eccjeu/input/andrea_input.csv | /home/edik/projects/eccjeu/output/com_db_comp/db_comp_metadata_manifest.csv | /home/edik/projects/eccjeu/output/com_legacy/download_case_manifest.csv
A185: 30295 | B185: =YEAR(A185) -> 1982 | C185: 29877 | D185: Infringement | not_exclusion_candidate | Prohibition Decision | E185: British Telecommunications | F185: andrea | com_db_comp | com_legacy | G185: 181 | 1817 | com_legacy_1982_line_11 | H185: andrea:181 | com_db_comp:1817 | com_legacy:com_legacy_1982_line_11 | I185: 29877 | IV/29877 | J185: 1982/10/12/29877 | K185: 1982/10/12/29877/andrea | 1982/10/12/29877/com_db_comp | 1982/10/12/29877/com_legacy | L185: TRUE | M185: TRUE | N185: reference_only | already_downloaded | O185: https://db-comp.eu/document_1817.download | http://ec.europa.eu/competition/antitrust/closed/en/1982.html | P185: https://db-comp.eu/document_1817.download | https://eur-lex.europa.eu/legal-content/EN/TXT/HTML/?uri=CELEX:31982D0861 | https://eur-lex.europa.eu/legal-content/EN/TXT/PDF/?uri=CELEX:31982D0861 | https://eur-lex.europa.eu/legal-content/DE/TXT/HTML/?uri=CELEX:31982D0861 | https://eur-lex.europa.eu/legal-content/DE/TXT/PDF/?uri=CELEX:31982D0861 | Q185: /home/edik/projects/eccjeu/data/raw/com_db_comp/files/29877-British-Telecommunications.pdf | /home/edik/projects/eccjeu/data/raw/com_legacy/files/html/31982D0861_EN.html | /home/edik/projects/eccjeu/data/raw/com_legacy/files/pdfs/31982D0861_EN.pdf | /home/edik/projects/eccjeu/data/raw/com_legacy/files/html/31982D0861_DE.html | R185: /home/edik/projects/eccjeu/data/raw/com_db_comp/files/29877-British-Telecommunications.pdf | /home/edik/projects/eccjeu/data/raw/com_legacy/files/html/31982D0861_EN.html | /home/edik/projects/eccjeu/data/raw/com_legacy/files/pdfs/31982D0861_EN.pdf | /home/edik/projects/eccjeu/data/raw/com_legacy/files/html/31982D0861_DE.html | S185: /home/edik/projects/eccjeu/input/andrea_input.csv | /home/edik/projects/eccjeu/output/com_db_comp/db_comp_metadata_manifest.csv | /home/edik/projects/eccjeu/output/com_legacy/download_case_manifest.csv
A186: 30295 | B186: =YEAR(A186) -> 1982 | C186: 30077 | D186: Infringement | not_exclusion_candidate | Prohibition Decision | E186: Cafeteros de Colombia (FNC) | Cafeteros de Colombia | Cafeteros de Colomba | F186: andrea | com_db_comp | com_legacy | G186: 180 | 1617 | com_legacy_1982_line_14 | H186: andrea:180 | com_db_comp:1617 | com_legacy:com_legacy_1982_line_14 | I186: 30077 | IV/30077 | J186: 1982/10/12/30077 | K186: 1982/10/12/30077/andrea | 1982/10/12/30077/com_db_comp | 1982/10/12/30077/com_legacy | L186: TRUE | M186: TRUE | N186: reference_only | already_downloaded | O186: https://db-comp.eu/document_1617.download | http://ec.europa.eu/competition/antitrust/closed/en/1982.html | P186: https://db-comp.eu/document_1617.download | https://eur-lex.europa.eu/legal-content/EN/TXT/HTML/?uri=CELEX:31982D0860 | https://eur-lex.europa.eu/legal-content/EN/TXT/PDF/?uri=CELEX:31982D0860 | https://eur-lex.europa.eu/legal-content/DE/TXT/HTML/?uri=CELEX:31982D0860 | https://eur-lex.europa.eu/legal-content/DE/TXT/PDF/?uri=CELEX:31982D0860 | Q186: /home/edik/projects/eccjeu/data/raw/com_db_comp/files/30077-Cafeteros-de-Colombia-_Dec-1982_.pdf | /home/edik/projects/eccjeu/data/raw/com_legacy/files/html/31982D0860_EN.html | /home/edik/projects/eccjeu/data/raw/com_legacy/files/pdfs/31982D0860_EN.pdf | /home/edik/projects/eccjeu/data/raw/com_legacy/files/html/31982D0860_DE.html | R186: /home/edik/projects/eccjeu/data/raw/com_db_comp/files/30077-Cafeteros-de-Colombia-_Dec-1982_.pdf | /home/edik/projects/eccjeu/data/raw/com_legacy/files/html/31982D0860_EN.html | /home/edik/projects/eccjeu/data/raw/com_legacy/files/pdfs/31982D0860_EN.pdf | /home/edik/projects/eccjeu/data/raw/com_legacy/files/html/31982D0860_DE.html | S186: /home/edik/projects/eccjeu/input/andrea_input.csv | /home/edik/projects/eccjeu/output/com_db_comp/db_comp_metadata_manifest.csv | /home/edik/projects/eccjeu/output/com_legacy/download_case_manifest.csv
... A227: 31070 | B227: =YEAR(A227) -> 1985 | C227: 31163 | D227: Infringement | Procedural Decision | E227: OLYMPIC AIRWAYS | F227: andrea | com_legacy | G227: 221 | com_legacy_1985_line_50 | H227: andrea:221 | com_legacy:com_legacy_1985_line_50 | I227: 31163 | IV/31163 | J227: 1985/01/23/31163 | K227: 1985/01/23/31163/andrea | 1985/01/23/31163/com_legacy | L227: TRUE | M227: TRUE | N227: reference_only | already_downloaded | O227: http://ec.europa.eu/competition/antitrust/closed/en/1985.html | P227: https://eur-lex.europa.eu/legal-content/EN/TXT/HTML/?uri=CELEX:31985D0121 | https://eur-lex.europa.eu/legal-content/EN/TXT/PDF/?uri=CELEX:31985D0121 | https://eur-lex.europa.eu/legal-content/DE/TXT/HTML/?uri=CELEX:31985D0121 | https://eur-lex.europa.eu/legal-content/DE/TXT/PDF/?uri=CELEX:31985D0121 | http://ec.europa.eu/competition/search.html | http://ec.europa.eu/competition/antitrust/closed/en/1985.html#top | Q227: /home/edik/projects/eccjeu/data/raw/com_legacy/files/html/31985D0121_EN.html | /home/edik/projects/eccjeu/data/raw/com_legacy/files/pdfs/31985D0121_EN.pdf | /home/edik/projects/eccjeu/data/raw/com_legacy/files/html/31985D0121_DE.html | /home/edik/projects/eccjeu/data/raw/com_legacy/files/html/search.html | /home/edik/projects/eccjeu/data/raw/com_legacy/files/html/1985.html | R227: /home/edik/projects/eccjeu/data/raw/com_legacy/files/html/31985D0121_EN.html | /home/edik/projects/eccjeu/data/raw/com_legacy/files/pdfs/31985D0121_EN.pdf | /home/edik/projects/eccjeu/data/raw/com_legacy/files/html/31985D0121_DE.html | /home/edik/projects/eccjeu/data/raw/com_legacy/files/html/search.html | /home/edik/projects/eccjeu/data/raw/com_legacy/files/html/1985.html | S227: /home/edik/projects/eccjeu/input/andrea_input.csv | /home/edik/projects/eccjeu/output/com_legacy/download_case_manifest.csv
A228: 31161 | B228: =YEAR(A228) -> 1985 | D228: Infringement | E228: Greek Insurance | F228: andrea | manual | G228: 222 | manual_000004 | H228: andrea:222 | manual:manual_000004 | J228: 1985/04/24/missing_case | K228: 1985/04/24/missing_case/andrea | 1985/04/24/missing_case/manual | L228: TRUE | M228: FALSE | N228: reference_only | manual_injection | P228: https://eur-lex.europa.eu/legal-content/EN/TXT/HTML/?uri=CELEX%3A31985D0276 | S228: /home/edik/projects/eccjeu/input/andrea_input.csv | /home/edik/projects/eccjeu/input/commission_manual_injection.csv
A229: 31238 | B229: =YEAR(A229) -> 1985 | C229: 29420 | D229: Exemption | not_exclusion_candidate | Exemption Decision | E229: GRUNDIG | Grundig's EEC distribution system | F229: andrea | com_db_comp | com_legacy | G229: 224 | 1644 | com_legacy_1985_line_47 | H229: andrea:224 | com_db_comp:1644 | com_legacy:com_legacy_1985_line_47 | I229: 29420 | J229: 1985/10/07/29420 | 1985/10/07/4 | K229: 1985/10/07/29420/andrea | 1985/10/07/29420/com_db_comp | 1985/10/07/4/com_legacy | L229: TRUE | M229: TRUE | N229: reference_only | already_downloaded | O229: https://db-comp.eu/document_1644.download | http://ec.europa.eu/competition/antitrust/closed/en/1985.html | P229: https://db-comp.eu/document_1644.download | https://eur-lex.europa.eu/legal-content/EN/TXT/HTML/?uri=CELEX:31985D0404 | https://eur-lex.europa.eu/legal-content/EN/TXT/PDF/?uri=CELEX:31985D0404 | https://eur-lex.europa.eu/legal-content/DE/TXT/HTML/?uri=CELEX:31985D0404 | https://eur-lex.europa.eu/legal-content/DE/TXT/PDF/?uri=CELEX:31985D0404 | Q229: /home/edik/projects/eccjeu/data/raw/com_db_comp/files/29420-Grundig-s-EEC-distribution-system-_July-1985_.pdf | /home/edik/projects/eccjeu/data/raw/com_legacy/files/html/31985D0404_EN.html | /home/edik/projects/eccjeu/data/raw/com_legacy/files/pdfs/31985D0404_EN.pdf | /home/edik/projects/eccjeu/data/raw/com_legacy/files/html/31985D0404_DE.html | R229: /home/edik/projects/eccjeu/data/raw/com_db_comp/files/29420-Grundig-s-EEC-distribution-system-_July-1985_.pdf | /home/edik/projects/eccjeu/data/raw/com_legacy/files/html/31985D0404_EN.html | /home/edik/projects/eccjeu/data/raw/com_legacy/files/pdfs/31985D0404_EN.pdf | /home/edik/projects/eccjeu/data/raw/com_legacy/files/html/31985D0404_DE.html | S229: /home/edik/projects/eccjeu/input/andrea_input.csv | /home/edik/projects/eccjeu/output/com_db_comp/db_comp_metadata_manifest.csv | /home/edik/projects/eccjeu/output/com_legacy/download_case_manifest.csv
A230: 31238 | B230: =YEAR(A230) -> 1985 | C230: 31029 | D230: Infringement | not_exclusion_candidate | Prohibition Decision | E230: EATE LEVY | French inland waterway charter traffic: EATE levy | F230: andrea | com_db_comp | com_legacy | G230: 223 | 1570 | com_legacy_1985_line_44 | H230: andrea:223 | com_db_comp:1570 | com_legacy:com_legacy_1985_line_44 | I230: 31029 | IV/31029 | J230: 1985/10/07/31029 | K230: 1985/10/07/31029/andrea | 1985/10/07/31029/com_db_comp | 1985/10/07/31029/com_legacy | L230: TRUE | M230: TRUE | N230: reference_only | already_downloaded | O230: https://db-comp.eu/document_1570.download | http://ec.europa.eu/competition/antitrust/closed/en/1985.html | P230: https://db-comp.eu/document_1570.download | https://eur-lex.europa.eu/legal-content/EN/TXT/HTML/?uri=CELEX:31985D0383 | https://eur-lex.europa.eu/legal-content/EN/TXT/PDF/?uri=CELEX:31985D0383 | https://eur-lex.europa.eu/legal-content/DE/TXT/HTML/?uri=CELEX:31985D0383 | https://eur-lex.europa.eu/legal-content/DE/TXT/PDF/?uri=CELEX:31985D0383 | Q230: /home/edik/projects/eccjeu/data/raw/com_db_comp/files/31029-French-inland-waterway-charter-traffic-EATE-levy-_July-1985_.pdf | /home/edik/projects/eccjeu/data/raw/com_legacy/files/html/31985D0383_EN.html | /home/edik/projects/eccjeu/data/raw/com_legacy/files/pdfs/31985D0383_EN.pdf | /home/edik/projects/eccjeu/data/raw/com_legacy/files/html/31985D0383_DE.html | R230: /home/edik/projects/eccjeu/data/raw/com_db_comp/files/31029-French-inland-waterway-charter-traffic-EATE-levy-_July-1985_.pdf | /home/edik/projects/eccjeu/data/raw/com_legacy/files/html/31985D0383_EN.html | /home/edik/projects/eccjeu/data/raw/com_legacy/files/pdfs/31985D0383_EN.pdf | /home/edik/projects/eccjeu/data/raw/com_legacy/files/html/31985D0383_DE.html | S230: /home/edik/projects/eccjeu/input/andrea_input.csv | /home/edik/projects/eccjeu/output/com_db_comp/db_comp_metadata_manifest.csv | /home/edik/projects/eccjeu/output/com_legacy/download_case_manifest.csv
A231: 31240 | B231: =YEAR(A231) -> 1985 | C231: 4204 | D231: Infringement | not_exclusion_candidate | Prohibition Decision | E231: VELCRO-APLIX | Velcro/Aplix | F231: andrea | com_db_comp | com_legacy | G231: 225 | 1753 | com_legacy_1985_line_41 | H231: andrea:225 | com_db_comp:1753 | com_legacy:com_legacy_1985_line_41 | I231: 4204 | IV/4204 | J231: 1985/12/07/4204 | K231: 1985/12/07/4204/andrea | 1985/12/07/4204/com_db_comp | 1985/12/07/4204/com_legacy | L231: TRUE | M231: TRUE | N231: reference_only | already_downloaded | O231: https://db-comp.eu/document_1753.download | http://ec.europa.eu/competition/antitrust/closed/en/1985.html | P231: https://db-comp.eu/document_1753.download | https://eur-lex.europa.eu/legal-content/EN/TXT/HTML/?uri=CELEX:31985D0410 | https://eur-lex.europa.eu/legal-content/EN/TXT/PDF/?uri=CELEX:31985D0410 | https://eur-lex.europa.eu/legal-content/DE/TXT/HTML/?uri=CELEX:31985D0410 | https://eur-lex.europa.eu/legal-content/DE/TXT/PDF/?uri=CELEX:31985D0410 | Q231: /home/edik/projects/eccjeu/data/raw/com_db_comp/files/4204-Velcro-Aplix-_July-1985_.pdf | /home/edik/projects/eccjeu/data/raw/com_legacy/files/html/31985D0410_EN.html | /home/edik/projects/eccjeu/data/raw/com_legacy/files/pdfs/31985D0410_EN.pdf | /home/edik/projects/eccjeu/data/raw/com_legacy/files/html/31985D0410_DE.html | R231: /home/edik/projects/eccjeu/data/raw/com_db_comp/files/4204-Velcro-Aplix-_July-1985_.pdf | /home/edik/projects/eccjeu/data/raw/com_legacy/files/html/31985D0410_EN.html | /home/edik/projects/eccjeu/data/raw/com_legacy/files/pdfs/31985D0410_EN.pdf | /home/edik/projects/eccjeu/data/raw/com_legacy/files/html/31985D0410_DE.html | S231: /home/edik/projects/eccjeu/input/andrea_input.csv | /home/edik/projects/eccjeu/output/com_db_comp/db_comp_metadata_manifest.csv | /home/edik/projects/eccjeu/output/com_legacy/download_case_manifest.csv
A232: 31378 | B232: =YEAR(A232) -> 1985 | C232: 30846 | D232: Exemption | not_exclusion_candidate | Exemption Decision | E232: IVOCLAR | lvoclar | F232: andrea | com_db_comp | com_legacy | G232: 226 | 1579 | com_legacy_1985_line_38 | H232: andrea:226 | com_db_comp:1579 | com_legacy:com_legacy_1985_line_38 | I232: 30846 | IV/30846 | J232: 1985/11/27/30846 | K232: 1985/11/27/30846/andrea | 1985/11/27/30846/com_db_comp | 1985/11/27/30846/com_legacy | L232: TRUE | M232: TRUE | N232: reference_only | already_downloaded | O232: https://db-comp.eu/document_1579.download | http://ec.europa.eu/competition/antitrust/closed/en/1985.html | P232: https://db-comp.eu/document_1579.download | https://eur-lex.europa.eu/legal-content/EN/TXT/HTML/?uri=CELEX:31985D0559 | https://eur-lex.europa.eu/legal-content/EN/TXT/PDF/?uri=CELEX:31985D0559 | https://eur-lex.europa.eu/legal-content/DE/TXT/HTML/?uri=CELEX:31985D0559 | https://eur-lex.europa.eu/legal-content/DE/TXT/PDF/?uri=CELEX:31985D0559 | Q232: /home/edik/projects/eccjeu/data/raw/com_db_comp/files/30846-Ivoclar-_Nov-1985_.pdf | /home/edik/projects/eccjeu/data/raw/com_legacy/files/html/31985D0559_EN.html | /home/edik/projects/eccjeu/data/raw/com_legacy/files/pdfs/31985D0559_EN.pdf | /home/edik/projects/eccjeu/data/raw/com_legacy/files/html/31985D0559_DE.html | R232: /home/edik/projects/eccjeu/data/raw/com_db_comp/files/30846-Ivoclar-_Nov-1985_.pdf | /home/edik/projects/eccjeu/data/raw/com_legacy/files/html/31985D0559_EN.html | /home/edik/projects/eccjeu/data/raw/com_legacy/files/pdfs/31985D0559_EN.pdf | /home/edik/projects/eccjeu/data/raw/com_legacy/files/html/31985D0559_DE.html | S232: /home/edik/projects/eccjeu/input/andrea_input.csv | /home/edik/projects/eccjeu/output/com_db_comp/db_comp_metadata_manifest.csv | /home/edik/projects/eccjeu/output/com_legacy/download_case_manifest.csv
A233: 31383 | B233: =YEAR(A233) -> 1985 | C233: 30971 | D233: Exemption | not_exclusion_candidate | Exemption Decision | E233: BP/KELLOGG | BP/Kellogg | F233: andrea | com_db_comp | com_legacy | G233: 227 | 1574 | com_legacy_1985_line_35 | H233: andrea:227 | com_db_comp:1574 | com_legacy:com_legacy_1985_line_35 | I233: 30971 | IV/30971 | J233: 1985/02/12/30971 | K233: 1985/02/12/30971/andrea | 1985/02/12/30971/com_db_comp | 1985/02/12/30971/com_legacy | L233: TRUE | M233: TRUE | N233: reference_only | already_downloaded | O233: https://db-comp.eu/document_1574.download | http://ec.europa.eu/competition/antitrust/closed/en/1985.html | P233: https://db-comp.eu/document_1574.download | https://eur-lex.europa.eu/legal-content/EN/TXT/HTML/?uri=CELEX:31985D0560 | https://eur-lex.europa.eu/legal-content/EN/TXT/PDF/?uri=CELEX:31985D0560 | https://eur-lex.europa.eu/legal-content/DE/TXT/HTML/?uri=CELEX:31985D0560 | https://eur-lex.europa.eu/legal-content/DE/TXT/PDF/?uri=CELEX:31985D0560 | Q233: /home/edik/projects/eccjeu/data/raw/com_db_comp/files/30971-BP-Kellogg-_Dec-1985_.pdf | /home/edik/projects/eccjeu/data/raw/com_legacy/files/html/31985D0560_EN.html | /home/edik/projects/eccjeu/data/raw/com_legacy/files/pdfs/31985D0560_EN.pdf | /home/edik/projects/eccjeu/data/raw/com_legacy/files/html/31985D0560_DE.html | R233: /home/edik/projects/eccjeu/data/raw/com_db_comp/files/30971-BP-Kellogg-_Dec-1985_.pdf | /home/edik/projects/eccjeu/data/raw/com_legacy/files/html/31985D0560_EN.html | /home/edik/projects/eccjeu/data/raw/com_legacy/files/pdfs/31985D0560_EN.pdf | /home/edik/projects/eccjeu/data/raw/com_legacy/files/html/31985D0560_DE.html | S233: /home/edik/projects/eccjeu/input/andrea_input.csv | /home/edik/projects/eccjeu/output/com_db_comp/db_comp_metadata_manifest.csv | /home/edik/projects/eccjeu/output/com_legacy/download_case_manifest.csv
A234: 31394 | B234: =YEAR(A234) -> 1985 | C234: 27590 | D234: Negative Clearance | not_exclusion_candidate | Negative Clearance Decision | E234: London Sugar Futures Market Ltd | London Sugar Futures Market Limited | F234: andrea | com_db_comp | com_legacy | G234: 230 | 1687 | com_legacy_1985_line_29 | H234: andrea:230 | com_db_comp:1687 | com_legacy:com_legacy_1985_line_29 | I234: 27590 | IV/27590 | J234: 1985/12/13/27590 | K234: 1985/12/13/27590/andrea | 1985/12/13/27590/com_db_comp | 1985/12/13/27590/com_legacy | L234: TRUE | M234: TRUE | N234: reference_only | already_downloaded | O234: https://db-comp.eu/document_1687.download | http://ec.europa.eu/competition/antitrust/closed/en/1985.html | P234: https://db-comp.eu/document_1687.download | https://eur-lex.europa.eu/legal-content/EN/TXT/HTML/?uri=CELEX:31985D0563 | https://eur-lex.europa.eu/legal-content/EN/TXT/PDF/?uri=CELEX:31985D0563 | https://eur-lex.europa.eu/legal-content/DE/TXT/HTML/?uri=CELEX:31985D0563 | https://eur-lex.europa.eu/legal-content/DE/TXT/PDF/?uri=CELEX:31985D0563 | Q234: /home/edik/projects/eccjeu/data/raw/com_db_comp/files/27590-London-Sugar-Futures-Market-Limited-_Dec-1985_.pdf | /home/edik/projects/eccjeu/data/raw/com_legacy/files/html/31985D0563_EN.html | /home/edik/projects/eccjeu/data/raw/com_legacy/files/pdfs/31985D0563_EN.pdf | /home/edik/projects/eccjeu/data/raw/com_legacy/files/html/31985D0563_DE.html | R234: /home/edik/projects/eccjeu/data/raw/com_db_comp/files/27590-London-Sugar-Futures-Market-Limited-_Dec-1985_.pdf | /home/edik/projects/eccjeu/data/raw/com_legacy/files/html/31985D0563_EN.html | /home/edik/projects/eccjeu/data/raw/com_legacy/files/pdfs/31985D0563_EN.pdf | /home/edik/projects/eccjeu/data/raw/com_legacy/files/html/31985D0563_DE.html | S234: /home/edik/projects/eccjeu/input/andrea_input.csv | /home/edik/projects/eccjeu/output/com_db_comp/db_comp_metadata_manifest.csv | /home/edik/projects/eccjeu/output/com_legacy/download_case_manifest.csv
A235: 31394 | B235: =YEAR(A235) -> 1985 | C235: 27591 | D235: Negative Clearance | not_exclusion_candidate | Negative Clearance Decision | E235: London Cocoa Terminal Market Association Ltd | London Cocoa Terminal Market Association Limited | F235: andrea | com_db_comp | com_legacy | G235: 231 | 1686 | com_legacy_1985_line_23 | H235: andrea:231 | com_db_comp:1686 | com_legacy:com_legacy_1985_line_23 | I235: 27591 | IV/27591 | J235: 1985/12/13/27591 | K235: 1985/12/13/27591/andrea | 1985/12/13/27591/com_db_comp | 1985/12/13/27591/com_legacy | L235: TRUE | M235: TRUE | N235: reference_only | already_downloaded | O235: https://db-comp.eu/document_1686.download | http://ec.europa.eu/competition/antitrust/closed/en/1985.html | P235: https://db-comp.eu/document_1686.download | https://eur-lex.europa.eu/legal-content/EN/TXT/HTML/?uri=CELEX:31985D0564 | https://eur-lex.europa.eu/legal-content/EN/TXT/PDF/?uri=CELEX:31985D0564 | https://eur-lex.europa.eu/legal-content/DE/TXT/HTML/?uri=CELEX:31985D0564 | https://eur-lex.europa.eu/legal-content/DE/TXT/PDF/?uri=CELEX:31985D0564 | Q235: /home/edik/projects/eccjeu/data/raw/com_db_comp/files/27591-London-Cocoa-Terminal-Market-Association-Limited-_Dec-1985_.pdf | /home/edik/projects/eccjeu/data/raw/com_legacy/files/html/31985D0564_EN.html | /home/edik/projects/eccjeu/data/raw/com_legacy/files/pdfs/31985D0564_EN.pdf | /home/edik/projects/eccjeu/data/raw/com_legacy/files/html/31985D0564_DE.html | R235: /home/edik/projects/eccjeu/data/raw/com_db_comp/files/27591-London-Cocoa-Terminal-Market-Association-Limited-_Dec-1985_.pdf | /home/edik/projects/eccjeu/data/raw/com_legacy/files/html/31985D0564_EN.html | /home/edik/projects/eccjeu/data/raw/com_legacy/files/pdfs/31985D0564_EN.pdf | /home/edik/projects/eccjeu/data/raw/com_legacy/files/html/31985D0564_DE.html | S235: /home/edik/projects/eccjeu/input/andrea_input.csv | /home/edik/projects/eccjeu/output/com_db_comp/db_comp_metadata_manifest.csv | /home/edik/projects/eccjeu/output/com_legacy/download_case_manifest.csv
A236: 31394 | B236: =YEAR(A236) -> 1985 | C236: 27592 | D236: Negative Clearance | not_exclusion_candidate | Negative Clearance Decision | E236: Coffee Terminal Market Association Ltd | London Rubber Terminal Market Association Limited | Coffee Terminal Market Association of London Ltd | F236: andrea | com_db_comp | com_legacy | G236: 232 | 1685 | com_legacy_1985_line_20 | H236: andrea:232 | com_db_comp:1685 | com_legacy:com_legacy_1985_line_20 | I236: 27592 | IV/27592 | J236: 1985/12/13/27592 | K236: 1985/12/13/27592/andrea | 1985/12/13/27592/com_db_comp | 1985/12/13/27592/com_legacy | L236: TRUE | M236: TRUE | N236: reference_only | already_downloaded | O236: https://db-comp.eu/document_1685.download | http://ec.europa.eu/competition/antitrust/closed/en/1985.html | P236: https://db-comp.eu/document_1685.download | https://eur-lex.europa.eu/legal-content/EN/TXT/HTML/?uri=CELEX:31985D0565 | https://eur-lex.europa.eu/legal-content/EN/TXT/PDF/?uri=CELEX:31985D0565 | https://eur-lex.europa.eu/legal-content/DE/TXT/HTML/?uri=CELEX:31985D0565 | https://eur-lex.europa.eu/legal-content/DE/TXT/PDF/?uri=CELEX:31985D0565 | Q236: /home/edik/projects/eccjeu/data/raw/com_db_comp/files/27592-Coffee-Terminal-Market-Association-of-London-Limited-_Dec-1985_.pdf | /home/edik/projects/eccjeu/data/raw/com_legacy/files/html/31985D0565_EN.html | /home/edik/projects/eccjeu/data/raw/com_legacy/files/pdfs/31985D0565_EN.pdf | /home/edik/projects/eccjeu/data/raw/com_legacy/files/html/31985D0565_DE.html | R236: /home/edik/projects/eccjeu/data/raw/com_db_comp/files/27592-Coffee-Terminal-Market-Association-of-London-Limited-_Dec-1985_.pdf | /home/edik/projects/eccjeu/data/raw/com_legacy/files/html/31985D0565_EN.html | /home/edik/projects/eccjeu/data/raw/com_legacy/files/pdfs/31985D0565_EN.pdf | /home/edik/projects/eccjeu/data/raw/com_legacy/files/html/31985D0565_DE.html | S236: /home/edik/projects/eccjeu/input/andrea_input.csv | /home/edik/projects/eccjeu/output/com_db_comp/db_comp_metadata_manifest.csv | /home/edik/projects/eccjeu/output/com_legacy/download_case_manifest.csv
A237: 31394 | B237: =YEAR(A237) -> 1985 | C237: 27593 | D237: Negative Clearance | Unknown | E237: London Rubber Terminal Market Association Ltd | F237: andrea | com_legacy | G237: 233 | com_legacy_1985_line_26 | H237: andrea:233 | com_legacy:com_legacy_1985_line_26 | I237: 27593 | IV/27593 | J237: 1985/12/13/27593 | missing_date/27593 | K237: 1985/12/13/27593/andrea | missing_date/27593/com_legacy | L237: TRUE | M237: TRUE | N237: reference_only | already_downloaded | O237: http://ec.europa.eu/competition/antitrust/closed/en/1985.html | P237: https://eur-lex.europa.eu/legal-content/EN/TXT/HTML/?uri=CELEX:31985D0566 | https://eur-lex.europa.eu/legal-content/EN/TXT/PDF/?uri=CELEX:31985D0566 | https://eur-lex.europa.eu/legal-content/DE/TXT/HTML/?uri=CELEX:31985D0566 | https://eur-lex.europa.eu/legal-content/DE/TXT/PDF/?uri=CELEX:31985D0566 | Q237: /home/edik/projects/eccjeu/data/raw/com_legacy/files/html/31985D0566_EN.html | /home/edik/projects/eccjeu/data/raw/com_legacy/files/pdfs/31985D0566_EN.pdf | /home/edik/projects/eccjeu/data/raw/com_legacy/files/html/31985D0566_DE.html | R237: /home/edik/projects/eccjeu/data/raw/com_legacy/files/html/31985D0566_EN.html | /home/edik/projects/eccjeu/data/raw/com_legacy/files/pdfs/31985D0566_EN.pdf | /home/edik/projects/eccjeu/data/raw/com_legacy/files/html/31985D0566_DE.html | S237: /home/edik/projects/eccjeu/input/andrea_input.csv | /home/edik/projects/eccjeu/output/com_legacy/download_case_manifest.csv
A238: 31394 | B238: =YEAR(A238) -> 1985 | C238: 30017 | D238: Infringement | not_exclusion_candidate | Prohibition Decision | E238: Breeders's Right | Breeders' rights: roses | Breeders's Rights | F238: andrea | com_db_comp | com_legacy | G238: 228 | 1620 | com_legacy_1985_line_17 | H238: andrea:228 | com_db_comp:1620 | com_legacy:com_legacy_1985_line_17 | I238: 30017 | IV/30017 | J238: 1985/12/13/30017 | K238: 1985/12/13/30017/andrea | 1985/12/13/30017/com_db_comp | 1985/12/13/30017/com_legacy | L238: TRUE | M238: TRUE | N238: reference_only | already_downloaded | O238: https://db-comp.eu/document_1620.download | http://ec.europa.eu/competition/antitrust/closed/en/1985.html | P238: https://db-comp.eu/document_1620.download | https://eur-lex.europa.eu/legal-content/EN/TXT/HTML/?uri=CELEX:31985D0561 | https://eur-lex.europa.eu/legal-content/EN/TXT/PDF/?uri=CELEX:31985D0561 | https://eur-lex.europa.eu/legal-content/DE/TXT/HTML/?uri=CELEX:31985D0561 | https://eur-lex.europa.eu/legal-content/DE/TXT/PDF/?uri=CELEX:31985D0561 | Q238: /home/edik/projects/eccjeu/data/raw/com_db_comp/files/30017-Breeders-rights-roses-_Dec-1985_.pdf | /home/edik/projects/eccjeu/data/raw/com_legacy/files/html/31985D0561_EN.html | /home/edik/projects/eccjeu/data/raw/com_legacy/files/pdfs/31985D0561_EN.pdf | /home/edik/projects/eccjeu/data/raw/com_legacy/files/html/31985D0561_DE.html | R238: /home/edik/projects/eccjeu/data/raw/com_db_comp/files/30017-Breeders-rights-roses-_Dec-1985_.pdf | /home/edik/projects/eccjeu/data/raw/com_legacy/files/html/31985D0561_EN.html | /home/edik/projects/eccjeu/data/raw/com_legacy/files/pdfs/31985D0561_EN.pdf | /home/edik/projects/eccjeu/data/raw/com_legacy/files/html/31985D0561_DE.html | S238: /home/edik/projects/eccjeu/input/andrea_input.csv | /home/edik/projects/eccjeu/output/com_db_comp/db_comp_metadata_manifest.csv | /home/edik/projects/eccjeu/output/com_legacy/download_case_manifest.csv
A239: 31394 | B239: =YEAR(A239) -> 1985 | C239: 30570 | D239: Exemption | not_exclusion_candidate | Exemption Decision | E239: Whiskey and Gin | Sole distribution agreements for whisky and gin | Whisky and Gin | F239: andrea | com_db_comp | com_legacy | G239: 229 | 1594 | com_legacy_1985_line_32 | H239: andrea:229 | com_db_comp:1594 | com_legacy:com_legacy_1985_line_32 | I239: 30570 | IV/30570 | J239: 1985/12/13/30570 | K239: 1985/12/13/30570/andrea | 1985/12/13/30570/com_db_comp | 1985/12/13/30570/com_legacy | L239: TRUE | M239: TRUE | N239: reference_only | already_downloaded | O239: https://db-comp.eu/document_1594.download | http://ec.europa.eu/competition/antitrust/closed/en/1985.html | P239: https://db-comp.eu/document_1594.download | https://eur-lex.europa.eu/legal-content/EN/TXT/HTML/?uri=CELEX:31985D0562 | https://eur-lex.europa.eu/legal-content/EN/TXT/PDF/?uri=CELEX:31985D0562 | https://eur-lex.europa.eu/legal-content/DE/TXT/HTML/?uri=CELEX:31985D0562 | https://eur-lex.europa.eu/legal-content/DE/TXT/PDF/?uri=CELEX:31985D0562 | Q239: /home/edik/projects/eccjeu/data/raw/com_db_comp/files/30570-Sole-distribution-agreements-for-whisky-and-gin-_Dec-1985_.pdf | /home/edik/projects/eccjeu/data/raw/com_legacy/files/html/31985D0562_EN.html | /home/edik/projects/eccjeu/data/raw/com_legacy/files/pdfs/31985D0562_EN.pdf | /home/edik/projects/eccjeu/data/raw/com_legacy/files/html/31985D0562_DE.html | R239: /home/edik/projects/eccjeu/data/raw/com_db_comp/files/30570-Sole-distribution-agreements-for-whisky-and-gin-_Dec-1985_.pdf | /home/edik/projects/eccjeu/data/raw/com_legacy/files/html/31985D0562_EN.html | /home/edik/projects/eccjeu/data/raw/com_legacy/files/pdfs/31985D0562_EN.pdf | /home/edik/projects/eccjeu/data/raw/com_legacy/files/html/31985D0562_DE.html | S239: /home/edik/projects/eccjeu/input/andrea_input.csv | /home/edik/projects/eccjeu/output/com_db_comp/db_comp_metadata_manifest.csv | /home/edik/projects/eccjeu/output/com_legacy/download_case_manifest.csv
A240: 31395 | B240: =YEAR(A240) -> 1985 | C240: 30698 | D240: Infringement | not_exclusion_candidate | Prohibition Decision | E240: ECS / AKZO CHEMIE | ECS/AKZO | ECS/AKZO CHEMIE | F240: andrea | com_db_comp | com_legacy | G240: 234 | 1821 | com_legacy_1985_line_14 | H240: andrea:234 | com_db_comp:1821 | com_legacy:com_legacy_1985_line_14 | I240: 30698 | IV/30698 | J240: 1985/12/14/30698 | K240: 1985/12/14/30698/andrea | 1985/12/14/30698/com_db_comp | 1985/12/14/30698/com_legacy | L240: TRUE | M240: TRUE | N240: reference_only | already_downloaded | O240: https://db-comp.eu/document_1821.download | http://ec.europa.eu/competition/antitrust/closed/en/1985.html | P240: https://db-comp.eu/document_1821.download | https://eur-lex.europa.eu/legal-content/EN/TXT/HTML/?uri=CELEX:31985D0609 | https://eur-lex.europa.eu/legal-content/EN/TXT/PDF/?uri=CELEX:31985D0609 | https://eur-lex.europa.eu/legal-content/DE/TXT/HTML/?uri=CELEX:31985D0609 | https://eur-lex.europa.eu/legal-content/DE/TXT/PDF/?uri=CELEX:31985D0609 | Q240: /home/edik/projects/eccjeu/data/raw/com_db_comp/files/30698-AKZO.pdf | /home/edik/projects/eccjeu/data/raw/com_legacy/files/html/31985D0609_EN.html | /home/edik/projects/eccjeu/data/raw/com_legacy/files/pdfs/31985D0609_EN.pdf | /home/edik/projects/eccjeu/data/raw/com_legacy/files/html/31985D0609_DE.html | R240: /home/edik/projects/eccjeu/data/raw/com_db_comp/files/30698-AKZO.pdf | /home/edik/projects/eccjeu/data/raw/com_legacy/files/html/31985D0609_EN.html | /home/edik/projects/eccjeu/data/raw/com_legacy/files/pdfs/31985D0609_EN.pdf | /home/edik/projects/eccjeu/data/raw/com_legacy/files/html/31985D0609_DE.html | S240: /home/edik/projects/eccjeu/input/andrea_input.csv | /home/edik/projects/eccjeu/output/com_db_comp/db_comp_metadata_manifest.csv | /home/edik/projects/eccjeu/output/com_legacy/download_case_manifest.csv
... A265: 31763 | B265: =YEAR(A265) -> 1986 | C265: 31428; 31429; 31430; 31431; 31432 | D265: Exemption | not_exclusion_candidate | Exemption Decision | E265: YVES ROCHER | Yves Rocher | F265: andrea | com_db_comp | com_legacy | G265: 257 | 1551 | com_legacy_1986_line_8 | H265: andrea:257 | com_db_comp:1551 | com_legacy:com_legacy_1986_line_8 | I265: 31428, 31429, 31430, 31431, 31432 | 31428 | 31429 | 31430 | 31431 | 31432 | IV/31428 | IV/31429 | IV/31430 | IV/31431 | IV/31432 | J265: 1986/12/17/31428/31429/31430/31431/31432 | K265: 1986/12/17/31428/31429/31430/31431/31432/andrea | 1986/12/17/31428/31429/31430/31431/31432/com_db_comp | 1986/12/17/31428/31429/31430/31431/31432/com_legacy | L265: TRUE | M265: TRUE | N265: reference_only | already_downloaded | O265: https://db-comp.eu/document_1551.download | http://ec.europa.eu/competition/antitrust/closed/en/1986.html | P265: https://db-comp.eu/document_1551.download | https://eur-lex.europa.eu/legal-content/EN/TXT/HTML/?uri=CELEX:31987D0014 | https://eur-lex.europa.eu/legal-content/EN/TXT/PDF/?uri=CELEX:31987D0014 | https://eur-lex.europa.eu/legal-content/DE/TXT/HTML/?uri=CELEX:31987D0014 | https://eur-lex.europa.eu/legal-content/DE/TXT/PDF/?uri=CELEX:31987D0014 | Q265: /home/edik/projects/eccjeu/data/raw/com_db_comp/files/31428-31429-31430-31431-31432-Yves-Rocher-_Dec-1986_.pdf | /home/edik/projects/eccjeu/data/raw/com_legacy/files/html/31987D0014_EN.html | /home/edik/projects/eccjeu/data/raw/com_legacy/files/pdfs/31987D0014_EN.pdf | /home/edik/projects/eccjeu/data/raw/com_legacy/files/html/31987D0014_DE.html | R265: /home/edik/projects/eccjeu/data/raw/com_db_comp/files/31428-31429-31430-31431-31432-Yves-Rocher-_Dec-1986_.pdf | /home/edik/projects/eccjeu/data/raw/com_legacy/files/html/31987D0014_EN.html | /home/edik/projects/eccjeu/data/raw/com_legacy/files/pdfs/31987D0014_EN.pdf | /home/edik/projects/eccjeu/data/raw/com_legacy/files/html/31987D0014_DE.html | S265: /home/edik/projects/eccjeu/input/andrea_input.csv | /home/edik/projects/eccjeu/output/com_db_comp/db_comp_metadata_manifest.csv | /home/edik/projects/eccjeu/output/com_legacy/download_case_manifest.csv
A266: 31950 | B266: =YEAR(A266) -> 1987 | D266: Infringement | E266: Canary Islands | F266: andrea | manual | G266: 260 | manual_000005 | H266: andrea:260 | manual:manual_000005 | J266: 1987/06/22/missing_case | K266: 1987/06/22/missing_case/andrea | 1987/06/22/missing_case/manual | L266: TRUE | M266: FALSE | N266: reference_only | manual_injection | P266: https://eur-lex.europa.eu/legal-content/EN/TXT/HTML/?uri=CELEX:31987D0359 | S266: /home/edik/projects/eccjeu/input/andrea_input.csv | /home/edik/projects/eccjeu/input/commission_manual_injection.csv
A267: 31968 | B267: =YEAR(A267) -> 1987 | C267: 31192; 31507 | D267: Infringement | not_exclusion_candidate | Prohibition Decision | E267: TIPP-EX | Tipp-Ex | F267: andrea | com_db_comp | com_legacy | G267: 261 | 1564 | com_legacy_1987_line_44 | H267: andrea:261 | com_db_comp:1564 | com_legacy:com_legacy_1987_line_44 | I267: 31192, 31507 | 31192 | 31507 | IV/31192 | IV/31507 | J267: 1987/10/07/31192/31507 | K267: 1987/10/07/31192/31507/andrea | 1987/10/07/31192/31507/com_db_comp | 1987/10/07/31192/31507/com_legacy | L267: TRUE | M267: TRUE | N267: reference_only | already_downloaded | O267: https://db-comp.eu/document_1564.download | http://ec.europa.eu/competition/antitrust/closed/en/1987.html | P267: https://db-comp.eu/document_1564.download | https://eur-lex.europa.eu/legal-content/EN/TXT/HTML/?uri=CELEX:31987D0406 | https://eur-lex.europa.eu/legal-content/EN/TXT/PDF/?uri=CELEX:31987D0406 | https://eur-lex.europa.eu/legal-content/DE/TXT/HTML/?uri=CELEX:31987D0406 | https://eur-lex.europa.eu/legal-content/DE/TXT/PDF/?uri=CELEX:31987D0406 | http://ec.europa.eu/competition/search.html | http://ec.europa.eu/competition/antitrust/closed/en/1987.html#top | Q267: /home/edik/projects/eccjeu/data/raw/com_db_comp/files/31192-31507-Tipp-Ex-_July-1987_.pdf | /home/edik/projects/eccjeu/data/raw/com_legacy/files/html/31987D0406_EN.html | /home/edik/projects/eccjeu/data/raw/com_legacy/files/pdfs/31987D0406_EN.pdf | /home/edik/projects/eccjeu/data/raw/com_legacy/files/html/31987D0406_DE.html | /home/edik/projects/eccjeu/data/raw/com_legacy/files/html/search.html | /home/edik/projects/eccjeu/data/raw/com_legacy/files/html/1987.html | R267: /home/edik/projects/eccjeu/data/raw/com_db_comp/files/31192-31507-Tipp-Ex-_July-1987_.pdf | /home/edik/projects/eccjeu/data/raw/com_legacy/files/html/31987D0406_EN.html | /home/edik/projects/eccjeu/data/raw/com_legacy/files/pdfs/31987D0406_EN.pdf | /home/edik/projects/eccjeu/data/raw/com_legacy/files/html/31987D0406_DE.html | /home/edik/projects/eccjeu/data/raw/com_legacy/files/html/search.html | /home/edik/projects/eccjeu/data/raw/com_legacy/files/html/1987.html | S267: /home/edik/projects/eccjeu/input/andrea_input.csv | /home/edik/projects/eccjeu/output/com_db_comp/db_comp_metadata_manifest.csv | /home/edik/projects/eccjeu/output/com_legacy/download_case_manifest.csv
A268: 31971 | B268: =YEAR(A268) -> 1987 | C268: 31741 | D268: Infringement | not_exclusion_candidate | Prohibition Decision | E268: SANDOZ | Sandoz | F268: andrea | com_db_comp | com_legacy | G268: 264 | 1534 | com_legacy_1987_line_41 | H268: andrea:264 | com_db_comp:1534 | com_legacy:com_legacy_1987_line_41 | I268: 31741 | IV/31741 | J268: 1987/07/13/31741 | K268: 1987/07/13/31741/andrea | 1987/07/13/31741/com_db_comp | 1987/07/13/31741/com_legacy | L268: TRUE | M268: TRUE | N268: reference_only | already_downloaded | O268: https://db-comp.eu/document_1534.download | http://ec.europa.eu/competition/antitrust/closed/en/1987.html | P268: https://db-comp.eu/document_1534.download | https://eur-lex.europa.eu/legal-content/EN/TXT/HTML/?uri=CELEX:31987D0409 | https://eur-lex.europa.eu/legal-content/EN/TXT/PDF/?uri=CELEX:31987D0409 | https://eur-lex.europa.eu/legal-content/DE/TXT/HTML/?uri=CELEX:31987D0409 | https://eur-lex.europa.eu/legal-content/DE/TXT/PDF/?uri=CELEX:31987D0409 | Q268: /home/edik/projects/eccjeu/data/raw/com_db_comp/files/31741-Sandoz-_July-1987_.pdf | /home/edik/projects/eccjeu/data/raw/com_legacy/files/html/31987D0409_EN.html | /home/edik/projects/eccjeu/data/raw/com_legacy/files/pdfs/31987D0409_EN.pdf | /home/edik/projects/eccjeu/data/raw/com_legacy/files/html/31987D0409_DE.html | R268: /home/edik/projects/eccjeu/data/raw/com_db_comp/files/31741-Sandoz-_July-1987_.pdf | /home/edik/projects/eccjeu/data/raw/com_legacy/files/html/31987D0409_EN.html | /home/edik/projects/eccjeu/data/raw/com_legacy/files/pdfs/31987D0409_EN.pdf | /home/edik/projects/eccjeu/data/raw/com_legacy/files/html/31987D0409_DE.html | S268: /home/edik/projects/eccjeu/input/andrea_input.csv | /home/edik/projects/eccjeu/output/com_db_comp/db_comp_metadata_manifest.csv | /home/edik/projects/eccjeu/output/com_legacy/download_case_manifest.csv
A269: 31971 | B269: =YEAR(A269) -> 1987 | C269: 31764 | D269: Unknown | Negative Clearance | not_exclusion_candidate | E269: Baltic International Freight Futures Exchange Ltd | Baltic International Freight Futures Exchange Limited | F269: com_legacy | andrea | com_db_comp | G269: com_legacy_1987_line_35 | 263 | 1533 | H269: com_legacy:com_legacy_1987_line_35 | andrea:263 | com_db_comp:1533 | I269: IV/31764 | 31764 | J269: missing_date/31764 | 1987/07/13/31764 | K269: missing_date/31764/com_legacy | 1987/07/13/31764/andrea | 1987/07/13/31764/com_db_comp | L269: TRUE | M269: TRUE | N269: already_downloaded | reference_only | O269: http://ec.europa.eu/competition/antitrust/closed/en/1987.html | https://db-comp.eu/document_1533.download | P269: https://eur-lex.europa.eu/legal-content/EN/TXT/HTML/?uri=CELEX:31987D0408 | https://eur-lex.europa.eu/legal-content/EN/TXT/PDF/?uri=CELEX:31987D0408 | https://eur-lex.europa.eu/legal-content/DE/TXT/HTML/?uri=CELEX:31987D0408 | https://eur-lex.europa.eu/legal-content/DE/TXT/PDF/?uri=CELEX:31987D0408 | https://db-comp.eu/document_1533.download | Q269: /home/edik/projects/eccjeu/data/raw/com_legacy/files/html/31987D0408_EN.html | /home/edik/projects/eccjeu/data/raw/com_legacy/files/pdfs/31987D0408_EN.pdf | /home/edik/projects/eccjeu/data/raw/com_legacy/files/html/31987D0408_DE.html | /home/edik/projects/eccjeu/data/raw/com_db_comp/files/31764-Baltic-International-Freight-Futures-Exchange-Limited-_July-1978_.pdf | R269: /home/edik/projects/eccjeu/data/raw/com_legacy/files/html/31987D0408_EN.html | /home/edik/projects/eccjeu/data/raw/com_legacy/files/pdfs/31987D0408_EN.pdf | /home/edik/projects/eccjeu/data/raw/com_legacy/files/html/31987D0408_DE.html | /home/edik/projects/eccjeu/data/raw/com_db_comp/files/31764-Baltic-International-Freight-Futures-Exchange-Limited-_July-1978_.pdf | S269: /home/edik/projects/eccjeu/output/com_legacy/download_case_manifest.csv | /home/edik/projects/eccjeu/input/andrea_input.csv | /home/edik/projects/eccjeu/output/com_db_comp/db_comp_metadata_manifest.csv
A270: 31971 | B270: =YEAR(A270) -> 1987 | C270: 32034 | D270: Exemption | not_exclusion_candidate | Exemption Decision | E270: COMPUTERLAND | Computerland | F270: andrea | com_db_comp | com_legacy | G270: 262 | 1521 | com_legacy_1987_line_38 | H270: andrea:262 | com_db_comp:1521 | com_legacy:com_legacy_1987_line_38 | I270: 32034 | IV/32034 | J270: 1987/07/13/32034 | K270: 1987/07/13/32034/andrea | 1987/07/13/32034/com_db_comp | 1987/07/13/32034/com_legacy | L270: TRUE | M270: TRUE | N270: reference_only | already_downloaded | O270: https://db-comp.eu/document_1521.download | http://ec.europa.eu/competition/antitrust/closed/en/1987.html | P270: https://db-comp.eu/document_1521.download | https://eur-lex.europa.eu/legal-content/EN/TXT/HTML/?uri=CELEX:31987D0407 | https://eur-lex.europa.eu/legal-content/EN/TXT/PDF/?uri=CELEX:31987D0407 | https://eur-lex.europa.eu/legal-content/DE/TXT/HTML/?uri=CELEX:31987D0407 | https://eur-lex.europa.eu/legal-content/DE/TXT/PDF/?uri=CELEX:31987D0407 | Q270: /home/edik/projects/eccjeu/data/raw/com_db_comp/files/32034-Computerland-_July-1987_.pdf | /home/edik/projects/eccjeu/data/raw/com_legacy/files/html/31987D0407_EN.html | /home/edik/projects/eccjeu/data/raw/com_legacy/files/pdfs/31987D0407_EN.pdf | /home/edik/projects/eccjeu/data/raw/com_legacy/files/html/31987D0407_DE.html | R270: /home/edik/projects/eccjeu/data/raw/com_db_comp/files/32034-Computerland-_July-1987_.pdf | /home/edik/projects/eccjeu/data/raw/com_legacy/files/html/31987D0407_EN.html | /home/edik/projects/eccjeu/data/raw/com_legacy/files/pdfs/31987D0407_EN.pdf | /home/edik/projects/eccjeu/data/raw/com_legacy/files/html/31987D0407_DE.html | S270: /home/edik/projects/eccjeu/input/andrea_input.csv | /home/edik/projects/eccjeu/output/com_db_comp/db_comp_metadata_manifest.csv | /home/edik/projects/eccjeu/output/com_legacy/download_case_manifest.csv
A271: 31987 | B271: =YEAR(A271) -> 1987 | C271: 32279 | D271: Interim Measures Decision | E271: BBI/BOOSEY and HAWKES | F271: com_legacy | G271: com_legacy_1987_line_32 | H271: com_legacy:com_legacy_1987_line_32 | I271: IV/32279 | J271: 1987/07/29/32279 | K271: 1987/07/29/32279/com_legacy | L271: TRUE | M271: TRUE | N271: already_downloaded | O271: http://ec.europa.eu/competition/antitrust/closed/en/1987.html | P271: https://eur-lex.europa.eu/legal-content/EN/TXT/HTML/?uri=CELEX:31987D0500 | https://eur-lex.europa.eu/legal-content/EN/TXT/PDF/?uri=CELEX:31987D0500 | https://eur-lex.europa.eu/legal-content/DE/TXT/HTML/?uri=CELEX:31987D0500 | https://eur-lex.europa.eu/legal-content/DE/TXT/PDF/?uri=CELEX:31987D0500 | Q271: /home/edik/projects/eccjeu/data/raw/com_legacy/files/html/31987D0500_EN.html | /home/edik/projects/eccjeu/data/raw/com_legacy/files/pdfs/31987D0500_EN.pdf | /home/edik/projects/eccjeu/data/raw/com_legacy/files/html/31987D0500_DE.html | R271: /home/edik/projects/eccjeu/data/raw/com_legacy/files/html/31987D0500_EN.html | /home/edik/projects/eccjeu/data/raw/com_legacy/files/pdfs/31987D0500_EN.pdf | /home/edik/projects/eccjeu/data/raw/com_legacy/files/html/31987D0500_DE.html | S271: /home/edik/projects/eccjeu/output/com_legacy/download_case_manifest.csv
A272: 32038 | B272: =YEAR(A272) -> 1987 | C272: 31739 | D272: Exemption | not_exclusion_candidate | Exemption Decision | E272: INTERNATIONALE DENTALSCHAU | Internationale Dentalschau | F272: andrea | com_db_comp | com_legacy | G272: 265 | 1535 | com_legacy_1987_line_29 | H272: andrea:265 | com_db_comp:1535 | com_legacy:com_legacy_1987_line_29 | I272: 31739 | IV/31739 | J272: 1987/09/18/31739 | K272: 1987/09/18/31739/andrea | 1987/09/18/31739/com_db_comp | 1987/09/18/31739/com_legacy | L272: TRUE | M272: TRUE | N272: reference_only | already_downloaded | O272: https://db-comp.eu/document_1535.download | http://ec.europa.eu/competition/antitrust/closed/en/1987.html | P272: https://db-comp.eu/document_1535.download | https://eur-lex.europa.eu/legal-content/EN/TXT/HTML/?uri=CELEX:31987D0509 | https://eur-lex.europa.eu/legal-content/EN/TXT/PDF/?uri=CELEX:31987D0509 | https://eur-lex.europa.eu/legal-content/DE/TXT/HTML/?uri=CELEX:31987D0509 | https://eur-lex.europa.eu/legal-content/DE/TXT/PDF/?uri=CELEX:31987D0509 | Q272: /home/edik/projects/eccjeu/data/raw/com_db_comp/files/31739-Internationale-Dentalschau-_Sep-1987_.pdf | /home/edik/projects/eccjeu/data/raw/com_legacy/files/html/31987D0509_EN.html | /home/edik/projects/eccjeu/data/raw/com_legacy/files/pdfs/31987D0509_EN.pdf | /home/edik/projects/eccjeu/data/raw/com_legacy/files/html/31987D0509_DE.html | R272: /home/edik/projects/eccjeu/data/raw/com_db_comp/files/31739-Internationale-Dentalschau-_Sep-1987_.pdf | /home/edik/projects/eccjeu/data/raw/com_legacy/files/html/31987D0509_EN.html | /home/edik/projects/eccjeu/data/raw/com_legacy/files/pdfs/31987D0509_EN.pdf | /home/edik/projects/eccjeu/data/raw/com_legacy/files/html/31987D0509_DE.html | S272: /home/edik/projects/eccjeu/input/andrea_input.csv | /home/edik/projects/eccjeu/output/com_db_comp/db_comp_metadata_manifest.csv | /home/edik/projects/eccjeu/output/com_legacy/download_case_manifest.csv
A273: 32129 | B273: =YEAR(A273) -> 1987 | C273: 31017 | D273: Infringement | not_exclusion_candidate | Prohibition Decision | E273: Fisher Price / Quaker Oats Ltd Toyco | Fisher-Price/Quaker Oats Ltd - Toyco | Fisher Price / Quaker Oats Ltd - Toyco | F273: andrea | com_db_comp | com_legacy | G273: 268 | 1571 | com_legacy_1987_line_20 | H273: andrea:268 | com_db_comp:1571 | com_legacy:com_legacy_1987_line_20 | I273: 31017 | IV/31017 | J273: 1987/12/18/31017 | K273: 1987/12/18/31017/andrea | 1987/12/18/31017/com_db_comp | 1987/12/18/31017/com_legacy | L273: TRUE | M273: TRUE | N273: reference_only | already_downloaded | O273: https://db-comp.eu/document_1571.download | http://ec.europa.eu/competition/antitrust/closed/en/1987.html | P273: https://db-comp.eu/document_1571.download | https://eur-lex.europa.eu/legal-content/EN/TXT/HTML/?uri=CELEX:31988D0086 | https://eur-lex.europa.eu/legal-content/EN/TXT/PDF/?uri=CELEX:31988D0086 | https://eur-lex.europa.eu/legal-content/DE/TXT/HTML/?uri=CELEX:31988D0086 | https://eur-lex.europa.eu/legal-content/DE/TXT/PDF/?uri=CELEX:31988D0086 | Q273: /home/edik/projects/eccjeu/data/raw/com_db_comp/files/31017-Fisher-Price-Quaker-Oats-Ltd-Toyco-_Dec-1987_.pdf | /home/edik/projects/eccjeu/data/raw/com_legacy/files/html/31988D0086_EN.html | /home/edik/projects/eccjeu/data/raw/com_legacy/files/pdfs/31988D0086_EN.pdf | /home/edik/projects/eccjeu/data/raw/com_legacy/files/html/31988D0086_DE.html | R273: /home/edik/projects/eccjeu/data/raw/com_db_comp/files/31017-Fisher-Price-Quaker-Oats-Ltd-Toyco-_Dec-1987_.pdf | /home/edik/projects/eccjeu/data/raw/com_legacy/files/html/31988D0086_EN.html | /home/edik/projects/eccjeu/data/raw/com_legacy/files/pdfs/31988D0086_EN.pdf | /home/edik/projects/eccjeu/data/raw/com_legacy/files/html/31988D0086_DE.html | S273: /home/edik/projects/eccjeu/input/andrea_input.csv | /home/edik/projects/eccjeu/output/com_db_comp/db_comp_metadata_manifest.csv | /home/edik/projects/eccjeu/output/com_legacy/download_case_manifest.csv
A274: 32129 | B274: =YEAR(A274) -> 1987 | C274: 31503 | D274: Infringement | not_exclusion_candidate | Prohibition Decision | E274: KONICA | Konica | F274: andrea | com_db_comp | com_legacy | G274: 267 | 1547 | com_legacy_1987_line_23 | H274: andrea:267 | com_db_comp:1547 | com_legacy:com_legacy_1987_line_23 | I274: 31503 | IV/31503 | J274: 1987/12/18/31503 | K274: 1987/12/18/31503/andrea | 1987/12/18/31503/com_db_comp | 1987/12/18/31503/com_legacy | L274: TRUE | M274: TRUE | N274: reference_only | already_downloaded | O274: https://db-comp.eu/document_1547.download | http://ec.europa.eu/competition/antitrust/closed/en/1987.html | P274: https://db-comp.eu/document_1547.download | https://eur-lex.europa.eu/legal-content/EN/TXT/HTML/?uri=CELEX:31988D0172 | https://eur-lex.europa.eu/legal-content/EN/TXT/PDF/?uri=CELEX:31988D0172 | https://eur-lex.europa.eu/legal-content/DE/TXT/HTML/?uri=CELEX:31988D0172 | https://eur-lex.europa.eu/legal-content/DE/TXT/PDF/?uri=CELEX:31988D0172 | Q274: /home/edik/projects/eccjeu/data/raw/com_db_comp/files/31503-Konica-_Dec-1987_.pdf | /home/edik/projects/eccjeu/data/raw/com_legacy/files/html/31988D0172_EN.html | /home/edik/projects/eccjeu/data/raw/com_legacy/files/pdfs/31988D0172_EN.pdf | /home/edik/projects/eccjeu/data/raw/com_legacy/files/html/31988D0172_DE.html | R274: /home/edik/projects/eccjeu/data/raw/com_db_comp/files/31503-Konica-_Dec-1987_.pdf | /home/edik/projects/eccjeu/data/raw/com_legacy/files/html/31988D0172_EN.html | /home/edik/projects/eccjeu/data/raw/com_legacy/files/pdfs/31988D0172_EN.pdf | /home/edik/projects/eccjeu/data/raw/com_legacy/files/html/31988D0172_DE.html | S274: /home/edik/projects/eccjeu/input/andrea_input.csv | /home/edik/projects/eccjeu/output/com_db_comp/db_comp_metadata_manifest.csv | /home/edik/projects/eccjeu/output/com_legacy/download_case_manifest.csv
A275: 32129 | B275: =YEAR(A275) -> 1987 | C275: 31735 | D275: Negative Clearance | not_exclusion_candidate | Negative Clearance Decision | E275: NEW POTATOES | New potatoes | NEW PATATOES | F275: andrea | com_db_comp | com_legacy | G275: 266 | 1536 | com_legacy_1987_line_26 | H275: andrea:266 | com_db_comp:1536 | com_legacy:com_legacy_1987_line_26 | I275: 31735 | IV/31735 | J275: 1987/12/18/31735 | K275: 1987/12/18/31735/andrea | 1987/12/18/31735/com_db_comp | 1987/12/18/31735/com_legacy | L275: TRUE | M275: TRUE | N275: reference_only | already_downloaded | O275: https://db-comp.eu/document_1536.download | http://ec.europa.eu/competition/antitrust/closed/en/1987.html | P275: https://db-comp.eu/document_1536.download | https://eur-lex.europa.eu/legal-content/EN/TXT/HTML/?uri=CELEX:31988D0109 | https://eur-lex.europa.eu/legal-content/EN/TXT/PDF/?uri=CELEX:31988D0109 | https://eur-lex.europa.eu/legal-content/DE/TXT/HTML/?uri=CELEX:31988D0109 | https://eur-lex.europa.eu/legal-content/DE/TXT/PDF/?uri=CELEX:31988D0109 | Q275: /home/edik/projects/eccjeu/data/raw/com_db_comp/files/31735-New-potatoes-_Dec-1987_.pdf | /home/edik/projects/eccjeu/data/raw/com_legacy/files/html/31988D0109_EN.html | /home/edik/projects/eccjeu/data/raw/com_legacy/files/pdfs/31988D0109_EN.pdf | /home/edik/projects/eccjeu/data/raw/com_legacy/files/html/31988D0109_DE.html | R275: /home/edik/projects/eccjeu/data/raw/com_db_comp/files/31735-New-potatoes-_Dec-1987_.pdf | /home/edik/projects/eccjeu/data/raw/com_legacy/files/html/31988D0109_EN.html | /home/edik/projects/eccjeu/data/raw/com_legacy/files/pdfs/31988D0109_EN.pdf | /home/edik/projects/eccjeu/data/raw/com_legacy/files/html/31988D0109_DE.html | S275: /home/edik/projects/eccjeu/input/andrea_input.csv | /home/edik/projects/eccjeu/output/com_db_comp/db_comp_metadata_manifest.csv | /home/edik/projects/eccjeu/output/com_legacy/download_case_manifest.csv
A276: 32133 | B276: =YEAR(A276) -> 1987 | C276: 27093 | D276: Renewal of exemption | Exemption Decision | E276: DE LAVAL STORK | DE LAVAL-STORK | F276: andrea | com_legacy | G276: 269 | com_legacy_1987_line_5 | H276: andrea:269 | com_legacy:com_legacy_1987_line_5 | I276: 27093 | IV/27093 | J276: 1987/12/22/27093 | K276: 1987/12/22/27093/andrea | 1987/12/22/27093/com_legacy | L276: TRUE | M276: TRUE | N276: reference_only | already_downloaded | O276: http://ec.europa.eu/competition/antitrust/closed/en/1987.html | P276: https://eur-lex.europa.eu/legal-content/EN/TXT/HTML/?uri=CELEX:31988D0110 | https://eur-lex.europa.eu/legal-content/EN/TXT/PDF/?uri=CELEX:31988D0110 | https://eur-lex.europa.eu/legal-content/DE/TXT/HTML/?uri=CELEX:31988D0110 | https://eur-lex.europa.eu/legal-content/DE/TXT/PDF/?uri=CELEX:31988D0110 | Q276: /home/edik/projects/eccjeu/data/raw/com_legacy/files/html/31988D0110_EN.html | /home/edik/projects/eccjeu/data/raw/com_legacy/files/pdfs/31988D0110_EN.pdf | /home/edik/projects/eccjeu/data/raw/com_legacy/files/html/31988D0110_DE.html | R276: /home/edik/projects/eccjeu/data/raw/com_legacy/files/html/31988D0110_EN.html | /home/edik/projects/eccjeu/data/raw/com_legacy/files/pdfs/31988D0110_EN.pdf | /home/edik/projects/eccjeu/data/raw/com_legacy/files/html/31988D0110_DE.html | S276: /home/edik/projects/eccjeu/input/andrea_input.csv | /home/edik/projects/eccjeu/output/com_legacy/download_case_manifest.csv
A277: 32133 | B277: =YEAR(A277) -> 1987 | C277: 30787; 31206; 31488 | D277: not_exclusion_candidate | Infringement | Prohibition Decision | Exemption | Exemption Decision | E277: Eurofix-Bauco v. Hilti | EUROFIX - BAUCO / HILTI | EUROFIX -BAUCO / HILTI | Rich Products / JUS-ROL | Rich Products/Jus-rol | F277: com_db_comp | andrea | com_legacy | G277: 1822 | 270 | com_legacy_1987_line_11 | 271 | 1562 | com_legacy_1987_line_17 | H277: com_db_comp:1822 | andrea:270 | com_legacy:com_legacy_1987_line_11 | andrea:271 | com_db_comp:1562 | com_legacy:com_legacy_1987_line_17 | I277: 30787 | 30787, 31488 | IV/30787 | IV/31488 | 31206 | IV/31206 | J277: 1987/12/22/30787 | 1987/12/22/30787/31488 | 1987/12/22/31206 | K277: 1987/12/22/30787/com_db_comp | 1987/12/22/30787/31488/andrea | 1987/12/22/30787/31488/com_legacy | 1987/12/22/31206/andrea | 1987/12/22/31206/com_db_comp | 1987/12/22/31206/com_legacy | L277: TRUE | M277: TRUE | N277: reference_only | already_downloaded | O277: https://db-comp.eu/document_1822.download | http://ec.europa.eu/competition/antitrust/closed/en/1987.html | https://db-comp.eu/document_1562.download | P277: https://db-comp.eu/document_1822.download | https://eur-lex.europa.eu/legal-content/EN/TXT/HTML/?uri=CELEX:31988D0138 | https://eur-lex.europa.eu/legal-content/EN/TXT/PDF/?uri=CELEX:31988D0138 | https://eur-lex.europa.eu/legal-content/DE/TXT/HTML/?uri=CELEX:31988D0138 | https://eur-lex.europa.eu/legal-content/DE/TXT/PDF/?uri=CELEX:31988D0138 | https://db-comp.eu/document_1562.download | https://eur-lex.europa.eu/legal-content/EN/TXT/HTML/?uri=CELEX:31988D0143 | https://eur-lex.europa.eu/legal-content/EN/TXT/PDF/?uri=CELEX:31988D0143 | https://eur-lex.europa.eu/legal-content/DE/TXT/HTML/?uri=CELEX:31988D0143 | https://eur-lex.europa.eu/legal-content/DE/TXT/PDF/?uri=CELEX:31988D0143 | Q277: /home/edik/projects/eccjeu/data/raw/com_db_comp/files/30787-Hilti.pdf | /home/edik/projects/eccjeu/data/raw/com_legacy/files/html/31988D0138_EN.html | /home/edik/projects/eccjeu/data/raw/com_legacy/files/pdfs/31988D0138_EN.pdf | /home/edik/projects/eccjeu/data/raw/com_legacy/files/html/31988D0138_DE.html | /home/edik/projects/eccjeu/data/raw/com_db_comp/files/31206-Rich-Products-Jus-rol-_Dec-1987_.pdf | /home/edik/projects/eccjeu/data/raw/com_legacy/files/html/31988D0143_EN.html | /home/edik/projects/eccjeu/data/raw/com_legacy/files/pdfs/31988D0143_EN.pdf | /home/edik/projects/eccjeu/data/raw/com_legacy/files/html/31988D0143_DE.html | R277: /home/edik/projects/eccjeu/data/raw/com_db_comp/files/30787-Hilti.pdf | /home/edik/projects/eccjeu/data/raw/com_legacy/files/html/31988D0138_EN.html | /home/edik/projects/eccjeu/data/raw/com_legacy/files/pdfs/31988D0138_EN.pdf | /home/edik/projects/eccjeu/data/raw/com_legacy/files/html/31988D0138_DE.html | /home/edik/projects/eccjeu/data/raw/com_db_comp/files/31206-Rich-Products-Jus-rol-_Dec-1987_.pdf | /home/edik/projects/eccjeu/data/raw/com_legacy/files/html/31988D0143_EN.html | /home/edik/projects/eccjeu/data/raw/com_legacy/files/pdfs/31988D0143_EN.pdf | /home/edik/projects/eccjeu/data/raw/com_legacy/files/html/31988D0143_DE.html | S277: /home/edik/projects/eccjeu/output/com_db_comp/db_comp_metadata_manifest.csv | /home/edik/projects/eccjeu/input/andrea_input.csv | /home/edik/projects/eccjeu/output/com_legacy/download_case_manifest.csv
A278: 32133 | B278: =YEAR(A278) -> 1987 | C278: 31846 | D278: Exemption | not_exclusion_candidate | Exemption Decision | E278: ENICHEM / ICI | Enichem/ICI | F278: andrea | com_db_comp | com_legacy | G278: 273 | 1532 | com_legacy_1987_line_8 | H278: andrea:273 | com_db_comp:1532 | com_legacy:com_legacy_1987_line_8 | I278: 31846 | IV/31846 | J278: 1987/12/22/31846 | K278: 1987/12/22/31846/andrea | 1987/12/22/31846/com_db_comp | 1987/12/22/31846/com_legacy | L278: TRUE | M278: TRUE | N278: reference_only | already_downloaded | O278: https://db-comp.eu/document_1532.download | http://ec.europa.eu/competition/antitrust/closed/en/1987.html | P278: https://db-comp.eu/document_1532.download | https://eur-lex.europa.eu/legal-content/EN/TXT/HTML/?uri=CELEX:31988D0087 | https://eur-lex.europa.eu/legal-content/EN/TXT/PDF/?uri=CELEX:31988D0087 | https://eur-lex.europa.eu/legal-content/DE/TXT/HTML/?uri=CELEX:31988D0087 | https://eur-lex.europa.eu/legal-content/DE/TXT/PDF/?uri=CELEX:31988D0087 | Q278: /home/edik/projects/eccjeu/data/raw/com_db_comp/files/31846-Enichem-ICI-_Dec-1987_.pdf | /home/edik/projects/eccjeu/data/raw/com_legacy/files/html/31988D0087_EN.html | /home/edik/projects/eccjeu/data/raw/com_legacy/files/pdfs/31988D0087_EN.pdf | /home/edik/projects/eccjeu/data/raw/com_legacy/files/html/31988D0087_DE.html | R278: /home/edik/projects/eccjeu/data/raw/com_db_comp/files/31846-Enichem-ICI-_Dec-1987_.pdf | /home/edik/projects/eccjeu/data/raw/com_legacy/files/html/31988D0087_EN.html | /home/edik/projects/eccjeu/data/raw/com_legacy/files/pdfs/31988D0087_EN.pdf | /home/edik/projects/eccjeu/data/raw/com_legacy/files/html/31988D0087_DE.html | S278: /home/edik/projects/eccjeu/input/andrea_input.csv | /home/edik/projects/eccjeu/output/com_db_comp/db_comp_metadata_manifest.csv | /home/edik/projects/eccjeu/output/com_legacy/download_case_manifest.csv
... A312: 32861 | B312: =YEAR(A312) -> 1989 | C312: 32414 | D312: Infringement | not_exclusion_candidate | Prohibition Decision | E312: Sugar Beet | Sugar beet | F312: andrea | com_db_comp | com_legacy | G312: 306 | 1506 | com_legacy_1989_line_8 | H312: andrea:306 | com_db_comp:1506 | com_legacy:com_legacy_1989_line_8 | I312: 32414 | IV/32414 | J312: 1989/12/19/32414 | K312: 1989/12/19/32414/andrea | 1989/12/19/32414/com_db_comp | 1989/12/19/32414/com_legacy | L312: TRUE | M312: TRUE | N312: reference_only | already_downloaded | O312: https://db-comp.eu/document_1506.download | http://ec.europa.eu/competition/antitrust/closed/en/1989.html | P312: https://db-comp.eu/document_1506.download | https://eur-lex.europa.eu/legal-content/EN/TXT/HTML/?uri=CELEX:31990D0045 | https://eur-lex.europa.eu/legal-content/EN/TXT/PDF/?uri=CELEX:31990D0045 | https://eur-lex.europa.eu/legal-content/DE/TXT/HTML/?uri=CELEX:31990D0045 | https://eur-lex.europa.eu/legal-content/DE/TXT/PDF/?uri=CELEX:31990D0045 | Q312: /home/edik/projects/eccjeu/data/raw/com_db_comp/files/32414-Sugar-beet-_Dec-1989_.pdf | /home/edik/projects/eccjeu/data/raw/com_legacy/files/html/31990D0045_EN.html | /home/edik/projects/eccjeu/data/raw/com_legacy/files/pdfs/31990D0045_EN.pdf | /home/edik/projects/eccjeu/data/raw/com_legacy/files/html/31990D0045_DE.html | R312: /home/edik/projects/eccjeu/data/raw/com_db_comp/files/32414-Sugar-beet-_Dec-1989_.pdf | /home/edik/projects/eccjeu/data/raw/com_legacy/files/html/31990D0045_EN.html | /home/edik/projects/eccjeu/data/raw/com_legacy/files/pdfs/31990D0045_EN.pdf | /home/edik/projects/eccjeu/data/raw/com_legacy/files/html/31990D0045_DE.html | S312: /home/edik/projects/eccjeu/input/andrea_input.csv | /home/edik/projects/eccjeu/output/com_db_comp/db_comp_metadata_manifest.csv | /home/edik/projects/eccjeu/output/com_legacy/download_case_manifest.csv
A313: 32862 | B313: =YEAR(A313) -> 1989 | D313: Infringement | E313: Provision in the Netherlands of express delivery services | F313: andrea | manual | G313: 307 | manual_000006 | H313: andrea:307 | manual:manual_000006 | J313: 1989/12/20/missing_case | K313: 1989/12/20/missing_case/andrea | 1989/12/20/missing_case/manual | L313: TRUE | M313: FALSE | N313: reference_only | manual_injection | P313: https://eur-lex.europa.eu/legal-content/EN/TXT/HTML/?uri=CELEX:31990D0016 | S313: /home/edik/projects/eccjeu/input/andrea_input.csv | /home/edik/projects/eccjeu/input/commission_manual_injection.csv
A314: 32862 | B314: =YEAR(A314) -> 1989 | C314: 32265 | D314: Exemption | not_exclusion_candidate | Exemption Decision | E314: Concordato Incendio | F314: andrea | com_db_comp | com_legacy | G314: 309 | 1513 | com_legacy_1989_line_2 | H314: andrea:309 | com_db_comp:1513 | com_legacy:com_legacy_1989_line_2 | I314: 32265 | IV/32265 | J314: 1989/12/20/32265 | K314: 1989/12/20/32265/andrea | 1989/12/20/32265/com_db_comp | 1989/12/20/32265/com_legacy | L314: TRUE | M314: TRUE | N314: reference_only | already_downloaded | O314: https://db-comp.eu/document_1513.download | http://ec.europa.eu/competition/antitrust/closed/en/1989.html | P314: https://db-comp.eu/document_1513.download | https://eur-lex.europa.eu/legal-content/EN/TXT/HTML/?uri=CELEX:31990D0025 | https://eur-lex.europa.eu/legal-content/EN/TXT/PDF/?uri=CELEX:31990D0025 | https://eur-lex.europa.eu/legal-content/DE/TXT/HTML/?uri=CELEX:31990D0025 | https://eur-lex.europa.eu/legal-content/DE/TXT/PDF/?uri=CELEX:31990D0025 | Q314: /home/edik/projects/eccjeu/data/raw/com_db_comp/files/32265-Concordato-Incendio-_Dec-1989_.pdf | /home/edik/projects/eccjeu/data/raw/com_legacy/files/html/31990D0025_EN.html | /home/edik/projects/eccjeu/data/raw/com_legacy/files/pdfs/31990D0025_EN.pdf | /home/edik/projects/eccjeu/data/raw/com_legacy/files/html/31990D0025_DE.html | R314: /home/edik/projects/eccjeu/data/raw/com_db_comp/files/32265-Concordato-Incendio-_Dec-1989_.pdf | /home/edik/projects/eccjeu/data/raw/com_legacy/files/html/31990D0025_EN.html | /home/edik/projects/eccjeu/data/raw/com_legacy/files/pdfs/31990D0025_EN.pdf | /home/edik/projects/eccjeu/data/raw/com_legacy/files/html/31990D0025_DE.html | S314: /home/edik/projects/eccjeu/input/andrea_input.csv | /home/edik/projects/eccjeu/output/com_db_comp/db_comp_metadata_manifest.csv | /home/edik/projects/eccjeu/output/com_legacy/download_case_manifest.csv
A315: 32862 | B315: =YEAR(A315) -> 1989 | C315: 32408 | D315: Exemption | not_exclusion_candidate | Exemption Decision | E315: TEKO | F315: andrea | com_db_comp | com_legacy | G315: 308 | 1507 | com_legacy_1989_line_5 | H315: andrea:308 | com_db_comp:1507 | com_legacy:com_legacy_1989_line_5 | I315: 32408 | IV/32408 | J315: 1989/12/20/32408 | K315: 1989/12/20/32408/andrea | 1989/12/20/32408/com_db_comp | 1989/12/20/32408/com_legacy | L315: TRUE | M315: TRUE | N315: reference_only | already_downloaded | O315: https://db-comp.eu/document_1507.download | http://ec.europa.eu/competition/antitrust/closed/en/1989.html | P315: https://db-comp.eu/document_1507.download | https://eur-lex.europa.eu/legal-content/EN/TXT/HTML/?uri=CELEX:31990D0022 | https://eur-lex.europa.eu/legal-content/EN/TXT/PDF/?uri=CELEX:31990D0022 | https://eur-lex.europa.eu/legal-content/DE/TXT/HTML/?uri=CELEX:31990D0022 | https://eur-lex.europa.eu/legal-content/DE/TXT/PDF/?uri=CELEX:31990D0022 | Q315: /home/edik/projects/eccjeu/data/raw/com_db_comp/files/32408-TEKO-_Dec-1989_.pdf | /home/edik/projects/eccjeu/data/raw/com_legacy/files/html/31990D0022_EN.html | /home/edik/projects/eccjeu/data/raw/com_legacy/files/pdfs/31990D0022_EN.pdf | /home/edik/projects/eccjeu/data/raw/com_legacy/files/html/31990D0022_DE.html | R315: /home/edik/projects/eccjeu/data/raw/com_db_comp/files/32408-TEKO-_Dec-1989_.pdf | /home/edik/projects/eccjeu/data/raw/com_legacy/files/html/31990D0022_EN.html | /home/edik/projects/eccjeu/data/raw/com_legacy/files/pdfs/31990D0022_EN.pdf | /home/edik/projects/eccjeu/data/raw/com_legacy/files/html/31990D0022_DE.html | S315: /home/edik/projects/eccjeu/input/andrea_input.csv | /home/edik/projects/eccjeu/output/com_db_comp/db_comp_metadata_manifest.csv | /home/edik/projects/eccjeu/output/com_legacy/download_case_manifest.csv
A316: 32885 | B316: =YEAR(A316) -> 1990 | C316: 32006 | D316: Exemption | not_exclusion_candidate | Exemption Decision | E316: Alcatel Espace / ANT Nachrichtentechnik | Alcatel Espace/ANT Nachrichtentechnik | F316: andrea | com_db_comp | com_legacy | G316: 310 | 1525 | com_legacy_1990_line_46 | H316: andrea:310 | com_db_comp:1525 | com_legacy:com_legacy_1990_line_46 | I316: 32006 | IV/32006 | J316: 1990/12/01/32006 | K316: 1990/12/01/32006/andrea | 1990/12/01/32006/com_db_comp | 1990/12/01/32006/com_legacy | L316: TRUE | M316: TRUE | N316: reference_only | already_downloaded | O316: https://db-comp.eu/document_1525.download | http://ec.europa.eu/competition/antitrust/closed/en/1990.html | P316: https://db-comp.eu/document_1525.download | https://eur-lex.europa.eu/legal-content/EN/TXT/HTML/?uri=CELEX:31990D0046 | https://eur-lex.europa.eu/legal-content/EN/TXT/PDF/?uri=CELEX:31990D0046 | https://eur-lex.europa.eu/legal-content/DE/TXT/HTML/?uri=CELEX:31990D0046 | https://eur-lex.europa.eu/legal-content/DE/TXT/PDF/?uri=CELEX:31990D0046 | http://ec.europa.eu/competition/search.html | http://ec.europa.eu/competition/antitrust/closed/en/1990.html#top | Q316: /home/edik/projects/eccjeu/data/raw/com_db_comp/files/32006-Alcatel-Espace-ANT-Nachrichtentechnik-_Jan-1990_.pdf | /home/edik/projects/eccjeu/data/raw/com_legacy/files/html/31990D0046_EN.html | /home/edik/projects/eccjeu/data/raw/com_legacy/files/pdfs/31990D0046_EN.pdf | /home/edik/projects/eccjeu/data/raw/com_legacy/files/html/31990D0046_DE.html | /home/edik/projects/eccjeu/data/raw/com_legacy/files/html/search.html | /home/edik/projects/eccjeu/data/raw/com_legacy/files/html/1990.html | R316: /home/edik/projects/eccjeu/data/raw/com_db_comp/files/32006-Alcatel-Espace-ANT-Nachrichtentechnik-_Jan-1990_.pdf | /home/edik/projects/eccjeu/data/raw/com_legacy/files/html/31990D0046_EN.html | /home/edik/projects/eccjeu/data/raw/com_legacy/files/pdfs/31990D0046_EN.pdf | /home/edik/projects/eccjeu/data/raw/com_legacy/files/html/31990D0046_DE.html | /home/edik/projects/eccjeu/data/raw/com_legacy/files/html/search.html | /home/edik/projects/eccjeu/data/raw/com_legacy/files/html/1990.html | S316: /home/edik/projects/eccjeu/input/andrea_input.csv | /home/edik/projects/eccjeu/output/com_db_comp/db_comp_metadata_manifest.csv | /home/edik/projects/eccjeu/output/com_legacy/download_case_manifest.csv
A317: 32955 | B317: =YEAR(A317) -> 1990 | C317: 32736 | D317: Exemption | not_exclusion_candidate | Exemption Decision | E317: MOOSEHEAD / WHITBREAD | Moosehead/Whitbread | MOOSEHEAD/WHITBREAD | F317: andrea | com_db_comp | com_legacy | G317: 311 | 1491 | com_legacy_1990_line_43 | H317: andrea:311 | com_db_comp:1491 | com_legacy:com_legacy_1990_line_43 | I317: 32736 | IV/32736 | J317: 1990/03/23/32736 | K317: 1990/03/23/32736/andrea | 1990/03/23/32736/com_db_comp | 1990/03/23/32736/com_legacy | L317: TRUE | M317: TRUE | N317: reference_only | already_downloaded | O317: https://db-comp.eu/document_1491.download | http://ec.europa.eu/competition/antitrust/closed/en/1990.html | P317: https://db-comp.eu/document_1491.download | https://eur-lex.europa.eu/legal-content/EN/TXT/HTML/?uri=CELEX:31990D0186 | https://eur-lex.europa.eu/legal-content/EN/TXT/PDF/?uri=CELEX:31990D0186 | https://eur-lex.europa.eu/legal-content/DE/TXT/HTML/?uri=CELEX:31990D0186 | https://eur-lex.europa.eu/legal-content/DE/TXT/PDF/?uri=CELEX:31990D0186 | Q317: /home/edik/projects/eccjeu/data/raw/com_db_comp/files/32736-Moosehead-Whitbread-_March-1990_.pdf | /home/edik/projects/eccjeu/data/raw/com_legacy/files/html/31990D0186_EN.html | /home/edik/projects/eccjeu/data/raw/com_legacy/files/pdfs/31990D0186_EN.pdf | /home/edik/projects/eccjeu/data/raw/com_legacy/files/html/31990D0186_DE.html | R317: /home/edik/projects/eccjeu/data/raw/com_db_comp/files/32736-Moosehead-Whitbread-_March-1990_.pdf | /home/edik/projects/eccjeu/data/raw/com_legacy/files/html/31990D0186_EN.html | /home/edik/projects/eccjeu/data/raw/com_legacy/files/pdfs/31990D0186_EN.pdf | /home/edik/projects/eccjeu/data/raw/com_legacy/files/html/31990D0186_DE.html | S317: /home/edik/projects/eccjeu/input/andrea_input.csv | /home/edik/projects/eccjeu/output/com_db_comp/db_comp_metadata_manifest.csv | /home/edik/projects/eccjeu/output/com_legacy/download_case_manifest.csv
A318: 33050 | B318: =YEAR(A318) -> 1990 | C318: 32846 | D318: Negative Clearance | not_exclusion_candidate | Negative Clearance Decision | E318: METALEUROPA SA | Metaleurop SA | METALEUROP SA | F318: andrea | com_db_comp | com_legacy | G318: 312 | 1888 | com_legacy_1990_line_40 | H318: andrea:312 | com_db_comp:1888 | com_legacy:com_legacy_1990_line_40 | I318: 32846 | IV/32846 | J318: 1990/06/26/32846 | K318: 1990/06/26/32846/andrea | 1990/06/26/32846/com_db_comp | 1990/06/26/32846/com_legacy | L318: TRUE | M318: TRUE | N318: reference_only | already_downloaded | O318: https://db-comp.eu/document_1888.download | http://ec.europa.eu/competition/antitrust/closed/en/1990.html | P318: https://db-comp.eu/document_1888.download | https://eur-lex.europa.eu/legal-content/EN/TXT/HTML/?uri=CELEX:31990D0363 | https://eur-lex.europa.eu/legal-content/EN/TXT/PDF/?uri=CELEX:31990D0363 | https://eur-lex.europa.eu/legal-content/DE/TXT/HTML/?uri=CELEX:31990D0363 | https://eur-lex.europa.eu/legal-content/DE/TXT/PDF/?uri=CELEX:31990D0363 | Q318: /home/edik/projects/eccjeu/data/raw/com_db_comp/files/32846-Metaleurop-SA-_clearance-merger_.pdf | /home/edik/projects/eccjeu/data/raw/com_legacy/files/html/31990D0363_EN.html | /home/edik/projects/eccjeu/data/raw/com_legacy/files/pdfs/31990D0363_EN.pdf | /home/edik/projects/eccjeu/data/raw/com_legacy/files/html/31990D0363_DE.html | R318: /home/edik/projects/eccjeu/data/raw/com_db_comp/files/32846-Metaleurop-SA-_clearance-merger_.pdf | /home/edik/projects/eccjeu/data/raw/com_legacy/files/html/31990D0363_EN.html | /home/edik/projects/eccjeu/data/raw/com_legacy/files/pdfs/31990D0363_EN.pdf | /home/edik/projects/eccjeu/data/raw/com_legacy/files/html/31990D0363_DE.html | S318: /home/edik/projects/eccjeu/input/andrea_input.csv | /home/edik/projects/eccjeu/output/com_db_comp/db_comp_metadata_manifest.csv | /home/edik/projects/eccjeu/output/com_legacy/download_case_manifest.csv
A319: 33067 | B319: =YEAR(A319) -> 1990 | C319: 32009 | D319: Negative Clearance | not_exclusion_candidate | Negative Clearance Decision | E319: ELOPAK / METAL BOX-ODIN | Elopak/Metal Box - Odin | ELOPAK/METAL BOX-ODIN | F319: andrea | com_db_comp | com_legacy | G319: 313 | 1524 | com_legacy_1990_line_37 | H319: andrea:313 | com_db_comp:1524 | com_legacy:com_legacy_1990_line_37 | I319: 32009 | IV/32009 | J319: 1990/07/13/32009 | K319: 1990/07/13/32009/andrea | 1990/07/13/32009/com_db_comp | 1990/07/13/32009/com_legacy | L319: TRUE | M319: TRUE | N319: reference_only | already_downloaded | O319: https://db-comp.eu/document_1524.download | http://ec.europa.eu/competition/antitrust/closed/en/1990.html | P319: https://db-comp.eu/document_1524.download | https://eur-lex.europa.eu/legal-content/EN/TXT/HTML/?uri=CELEX:31990D0410 | https://eur-lex.europa.eu/legal-content/EN/TXT/PDF/?uri=CELEX:31990D0410 | https://eur-lex.europa.eu/legal-content/DE/TXT/HTML/?uri=CELEX:31990D0410 | https://eur-lex.europa.eu/legal-content/DE/TXT/PDF/?uri=CELEX:31990D0410 | Q319: /home/edik/projects/eccjeu/data/raw/com_db_comp/files/32009-Elopak-Metal-Box-Odin-_July-1990_.pdf | /home/edik/projects/eccjeu/data/raw/com_legacy/files/html/31990D0410_EN.html | /home/edik/projects/eccjeu/data/raw/com_legacy/files/pdfs/31990D0410_EN.pdf | /home/edik/projects/eccjeu/data/raw/com_legacy/files/html/31990D0410_DE.html | R319: /home/edik/projects/eccjeu/data/raw/com_db_comp/files/32009-Elopak-Metal-Box-Odin-_July-1990_.pdf | /home/edik/projects/eccjeu/data/raw/com_legacy/files/html/31990D0410_EN.html | /home/edik/projects/eccjeu/data/raw/com_legacy/files/pdfs/31990D0410_EN.pdf | /home/edik/projects/eccjeu/data/raw/com_legacy/files/html/31990D0410_DE.html | S319: /home/edik/projects/eccjeu/input/andrea_input.csv | /home/edik/projects/eccjeu/output/com_db_comp/db_comp_metadata_manifest.csv | /home/edik/projects/eccjeu/output/com_legacy/download_case_manifest.csv
A320: 33081 | B320: =YEAR(A320) -> 1990 | C320: 32688 | D320: Negative Clearance | not_exclusion_candidate | Negative Clearance Decision | E320: KONSORTIUM ECR 900 | Konsortium ECR 900 | F320: andrea | com_db_comp | com_legacy | G320: 314 | 1494 | com_legacy_1990_line_34 | H320: andrea:314 | com_db_comp:1494 | com_legacy:com_legacy_1990_line_34 | I320: 32688 | IV/32688 | J320: 1990/07/27/32688 | K320: 1990/07/27/32688/andrea | 1990/07/27/32688/com_db_comp | 1990/07/27/32688/com_legacy | L320: TRUE | M320: TRUE | N320: reference_only | already_downloaded | O320: https://db-comp.eu/document_1494.download | http://ec.europa.eu/competition/antitrust/closed/en/1990.html | P320: https://db-comp.eu/document_1494.download | https://eur-lex.europa.eu/legal-content/EN/TXT/HTML/?uri=CELEX:31990D0446 | https://eur-lex.europa.eu/legal-content/EN/TXT/PDF/?uri=CELEX:31990D0446 | https://eur-lex.europa.eu/legal-content/DE/TXT/HTML/?uri=CELEX:31990D0446 | https://eur-lex.europa.eu/legal-content/DE/TXT/PDF/?uri=CELEX:31990D0446 | Q320: /home/edik/projects/eccjeu/data/raw/com_db_comp/files/32688-Konsortium-ECR-900-_July-1990_.pdf | /home/edik/projects/eccjeu/data/raw/com_legacy/files/html/31990D0446_EN.html | /home/edik/projects/eccjeu/data/raw/com_legacy/files/pdfs/31990D0446_EN.pdf | /home/edik/projects/eccjeu/data/raw/com_legacy/files/html/31990D0446_DE.html | R320: /home/edik/projects/eccjeu/data/raw/com_db_comp/files/32688-Konsortium-ECR-900-_July-1990_.pdf | /home/edik/projects/eccjeu/data/raw/com_legacy/files/html/31990D0446_EN.html | /home/edik/projects/eccjeu/data/raw/com_legacy/files/pdfs/31990D0446_EN.pdf | /home/edik/projects/eccjeu/data/raw/com_legacy/files/html/31990D0446_DE.html | S320: /home/edik/projects/eccjeu/input/andrea_input.csv | /home/edik/projects/eccjeu/output/com_db_comp/db_comp_metadata_manifest.csv | /home/edik/projects/eccjeu/output/com_legacy/download_case_manifest.csv
A321: 33161 | B321: =YEAR(A321) -> 1990 | C321: 32681 | D321: Exemption | not_exclusion_candidate | Exemption Decision | E321: CEKACAN | Cekacan | F321: andrea | com_db_comp | com_legacy | G321: 315 | 1495 | com_legacy_1990_line_29 | H321: andrea:315 | com_db_comp:1495 | com_legacy:com_legacy_1990_line_29 | I321: 32681 | IV/32681 | J321: 1990/10/15/32681 | K321: 1990/10/15/32681/andrea | 1990/10/15/32681/com_db_comp | 1990/10/15/32681/com_legacy | L321: TRUE | M321: TRUE | N321: reference_only | already_downloaded | O321: https://db-comp.eu/document_1495.download | http://ec.europa.eu/competition/antitrust/closed/en/1990.html | P321: https://db-comp.eu/document_1495.download | https://eur-lex.europa.eu/legal-content/EN/TXT/HTML/?uri=CELEX:31990D0535 | https://eur-lex.europa.eu/legal-content/EN/TXT/PDF/?uri=CELEX:31990D0535 | https://eur-lex.europa.eu/legal-content/DE/TXT/HTML/?uri=CELEX:31990D0535 | https://eur-lex.europa.eu/legal-content/DE/TXT/PDF/?uri=CELEX:31990D0535 | Q321: /home/edik/projects/eccjeu/data/raw/com_db_comp/files/32681-Cekacan-_Oct-1990_.pdf | /home/edik/projects/eccjeu/data/raw/com_legacy/files/html/31990D0535_EN.html | /home/edik/projects/eccjeu/data/raw/com_legacy/files/pdfs/31990D0535_EN.pdf | /home/edik/projects/eccjeu/data/raw/com_legacy/files/html/31990D0535_DE.html | R321: /home/edik/projects/eccjeu/data/raw/com_db_comp/files/32681-Cekacan-_Oct-1990_.pdf | /home/edik/projects/eccjeu/data/raw/com_legacy/files/html/31990D0535_EN.html | /home/edik/projects/eccjeu/data/raw/com_legacy/files/pdfs/31990D0535_EN.pdf | /home/edik/projects/eccjeu/data/raw/com_legacy/files/html/31990D0535_DE.html | S321: /home/edik/projects/eccjeu/input/andrea_input.csv | /home/edik/projects/eccjeu/output/com_db_comp/db_comp_metadata_manifest.csv | /home/edik/projects/eccjeu/output/com_legacy/download_case_manifest.csv
A322: 33205 | B322: =YEAR(A322) -> 1990 | C322: 32877 | D322: Infringement | not_exclusion_candidate | Prohibition Decision | E322: BAYER DENTAL | Bayer Dental | F322: andrea | com_db_comp | com_legacy | G322: 316 | 1485 | com_legacy_1990_line_26 | H322: andrea:316 | com_db_comp:1485 | com_legacy:com_legacy_1990_line_26 | I322: 32877 | IV/32877 | J322: 1990/11/28/32877 | K322: 1990/11/28/32877/andrea | 1990/11/28/32877/com_db_comp | 1990/11/28/32877/com_legacy | L322: TRUE | M322: TRUE | N322: reference_only | already_downloaded | O322: https://db-comp.eu/document_1485.download | http://ec.europa.eu/competition/antitrust/closed/en/1990.html | P322: https://db-comp.eu/document_1485.download | https://eur-lex.europa.eu/legal-content/EN/TXT/HTML/?uri=CELEX:31990D0645 | https://eur-lex.europa.eu/legal-content/EN/TXT/PDF/?uri=CELEX:31990D0645 | https://eur-lex.europa.eu/legal-content/DE/TXT/HTML/?uri=CELEX:31990D0645 | https://eur-lex.europa.eu/legal-content/DE/TXT/PDF/?uri=CELEX:31990D0645 | Q322: /home/edik/projects/eccjeu/data/raw/com_db_comp/files/32877-Bayer-Dental-_Nov-1990_.pdf | /home/edik/projects/eccjeu/data/raw/com_legacy/files/html/31990D0645_EN.html | /home/edik/projects/eccjeu/data/raw/com_legacy/files/pdfs/31990D0645_EN.pdf | /home/edik/projects/eccjeu/data/raw/com_legacy/files/html/31990D0645_DE.html | R322: /home/edik/projects/eccjeu/data/raw/com_db_comp/files/32877-Bayer-Dental-_Nov-1990_.pdf | /home/edik/projects/eccjeu/data/raw/com_legacy/files/html/31990D0645_EN.html | /home/edik/projects/eccjeu/data/raw/com_legacy/files/pdfs/31990D0645_EN.pdf | /home/edik/projects/eccjeu/data/raw/com_legacy/files/html/31990D0645_DE.html | S322: /home/edik/projects/eccjeu/input/andrea_input.csv | /home/edik/projects/eccjeu/output/com_db_comp/db_comp_metadata_manifest.csv | /home/edik/projects/eccjeu/output/com_legacy/download_case_manifest.csv
A323: 33219 | B323: =YEAR(A323) -> 1990 | C323: 32363 | D323: Exemption | not_exclusion_candidate | Exemption Decision | E323: KSB / GOULDS LOWARA / ITT | KSB/Goulds/Lowara/ITT | KSB/GOULDS / LOWARA / ITT | F323: andrea | com_db_comp | com_legacy | G323: 317 | 1509 | com_legacy_1990_line_23 | H323: andrea:317 | com_db_comp:1509 | com_legacy:com_legacy_1990_line_23 | I323: 32363 | IV/32363 | J323: 1990/12/12/32363 | K323: 1990/12/12/32363/andrea | 1990/12/12/32363/com_db_comp | 1990/12/12/32363/com_legacy | L323: TRUE | M323: TRUE | N323: reference_only | already_downloaded | O323: https://db-comp.eu/document_1509.download | http://ec.europa.eu/competition/antitrust/closed/en/1990.html | P323: https://db-comp.eu/document_1509.download | https://eur-lex.europa.eu/legal-content/EN/TXT/HTML/?uri=CELEX:31991D0038 | https://eur-lex.europa.eu/legal-content/EN/TXT/PDF/?uri=CELEX:31991D0038 | https://eur-lex.europa.eu/legal-content/DE/TXT/HTML/?uri=CELEX:31991D0038 | https://eur-lex.europa.eu/legal-content/DE/TXT/PDF/?uri=CELEX:31991D0038 | Q323: /home/edik/projects/eccjeu/data/raw/com_db_comp/files/32363-KSB-Goulds-Lowara-ITT-_Dec-1990_.pdf | /home/edik/projects/eccjeu/data/raw/com_legacy/files/html/31991D0038_EN.html | /home/edik/projects/eccjeu/data/raw/com_legacy/files/pdfs/31991D0038_EN.pdf | /home/edik/projects/eccjeu/data/raw/com_legacy/files/html/31991D0038_DE.html | R323: /home/edik/projects/eccjeu/data/raw/com_db_comp/files/32363-KSB-Goulds-Lowara-ITT-_Dec-1990_.pdf | /home/edik/projects/eccjeu/data/raw/com_legacy/files/html/31991D0038_EN.html | /home/edik/projects/eccjeu/data/raw/com_legacy/files/pdfs/31991D0038_EN.pdf | /home/edik/projects/eccjeu/data/raw/com_legacy/files/html/31991D0038_DE.html | S323: /home/edik/projects/eccjeu/input/andrea_input.csv | /home/edik/projects/eccjeu/output/com_db_comp/db_comp_metadata_manifest.csv | /home/edik/projects/eccjeu/output/com_legacy/download_case_manifest.csv
A324: 33226 | B324: =YEAR(A324) -> 1990 | C324: 32450 | D324: Infringement | Procedural Decision | E324: SECRETAMA | F324: andrea | com_legacy | G324: 319 | com_legacy_1990_line_8 | H324: andrea:319 | com_legacy:com_legacy_1990_line_8 | I324: 32450 | IV/32450 | J324: 1990/12/19/32450 | K324: 1990/12/19/32450/andrea | 1990/12/19/32450/com_legacy | L324: TRUE | M324: TRUE | N324: reference_only | already_downloaded | O324: http://ec.europa.eu/competition/antitrust/closed/en/1990.html | P324: https://eur-lex.europa.eu/legal-content/EN/TXT/HTML/?uri=CELEX:31991D0055 | https://eur-lex.europa.eu/legal-content/EN/TXT/PDF/?uri=CELEX:31991D0055 | https://eur-lex.europa.eu/legal-content/DE/TXT/HTML/?uri=CELEX:31991D0055 | https://eur-lex.europa.eu/legal-content/DE/TXT/PDF/?uri=CELEX:31991D0055 | Q324: /home/edik/projects/eccjeu/data/raw/com_legacy/files/html/31991D0055_EN.html | /home/edik/projects/eccjeu/data/raw/com_legacy/files/pdfs/31991D0055_EN.pdf | /home/edik/projects/eccjeu/data/raw/com_legacy/files/html/31991D0055_DE.html | R324: /home/edik/projects/eccjeu/data/raw/com_legacy/files/html/31991D0055_EN.html | /home/edik/projects/eccjeu/data/raw/com_legacy/files/pdfs/31991D0055_EN.pdf | /home/edik/projects/eccjeu/data/raw/com_legacy/files/html/31991D0055_DE.html | S324: /home/edik/projects/eccjeu/input/andrea_input.csv | /home/edik/projects/eccjeu/output/com_legacy/download_case_manifest.csv
A325: 33226 | B325: =YEAR(A325) -> 1990 | C325: 32595 | D325: Negative Clearance | not_exclusion_candidate | Negative Clearance Decision | E325: D'Ieteren motor oils | D'leteren motor oils | D' Ieteren motor oils | F325: andrea | com_db_comp | com_legacy | G325: 318 | 1497 | com_legacy_1990_line_5 | H325: andrea:318 | com_db_comp:1497 | com_legacy:com_legacy_1990_line_5 | I325: 32595 | IV/32595 | J325: 1990/12/19/32595 | K325: 1990/12/19/32595/andrea | 1990/12/19/32595/com_db_comp | 1990/12/19/32595/com_legacy | L325: TRUE | M325: TRUE | N325: reference_only | already_downloaded | O325: https://db-comp.eu/document_1497.download | http://ec.europa.eu/competition/antitrust/closed/en/1990.html | P325: https://db-comp.eu/document_1497.download | https://eur-lex.europa.eu/legal-content/EN/TXT/HTML/?uri=CELEX:31991D0039 | https://eur-lex.europa.eu/legal-content/EN/TXT/PDF/?uri=CELEX:31991D0039 | https://eur-lex.europa.eu/legal-content/DE/TXT/HTML/?uri=CELEX:31991D0039 | https://eur-lex.europa.eu/legal-content/DE/TXT/PDF/?uri=CELEX:31991D0039 | Q325: /home/edik/projects/eccjeu/data/raw/com_db_comp/files/32595-d-Ieteren-motor-oils-_Dec-1990_.pdf | /home/edik/projects/eccjeu/data/raw/com_legacy/files/html/31991D0039_EN.html | /home/edik/projects/eccjeu/data/raw/com_legacy/files/pdfs/31991D0039_EN.pdf | /home/edik/projects/eccjeu/data/raw/com_legacy/files/html/31991D0039_DE.html | R325: /home/edik/projects/eccjeu/data/raw/com_db_comp/files/32595-d-Ieteren-motor-oils-_Dec-1990_.pdf | /home/edik/projects/eccjeu/data/raw/com_legacy/files/html/31991D0039_EN.html | /home/edik/projects/eccjeu/data/raw/com_legacy/files/pdfs/31991D0039_EN.pdf | /home/edik/projects/eccjeu/data/raw/com_legacy/files/html/31991D0039_DE.html | S325: /home/edik/projects/eccjeu/input/andrea_input.csv | /home/edik/projects/eccjeu/output/com_db_comp/db_comp_metadata_manifest.csv | /home/edik/projects/eccjeu/output/com_legacy/download_case_manifest.csv
... A376: 34297 | B376: =YEAR(A376) -> 1993 | C376: 32031; 32366; 32404 | D376: not_exclusion_candidate | Infringement | Mixed Final Decision | E376: Auditel | F376: com_db_comp | andrea | com_legacy | G376: 1522 | 369 | com_legacy_1993_line_8 | H376: com_db_comp:1522 | andrea:369 | com_legacy:com_legacy_1993_line_8 | I376: 32031 | 32031, 32366, 32404 | IV/32031 | IV/32366 | IV/32404 | J376: 1993/11/24/32031 | 1993/11/24/32031/32366/32404 | K376: 1993/11/24/32031/com_db_comp | 1993/11/24/32031/32366/32404/andrea | 1993/11/24/32031/32366/32404/com_legacy | L376: TRUE | M376: TRUE | N376: reference_only | already_downloaded | O376: https://db-comp.eu/document_1522.download | http://ec.europa.eu/competition/antitrust/closed/en/1993.html | P376: https://db-comp.eu/document_1522.download | https://eur-lex.europa.eu/legal-content/EN/TXT/HTML/?uri=CELEX:31993D0668 | https://eur-lex.europa.eu/legal-content/EN/TXT/PDF/?uri=CELEX:31993D0668 | https://eur-lex.europa.eu/legal-content/DE/TXT/HTML/?uri=CELEX:31993D0668 | https://eur-lex.europa.eu/legal-content/DE/TXT/PDF/?uri=CELEX:31993D0668 | Q376: /home/edik/projects/eccjeu/data/raw/com_db_comp/files/32031-Auditel-_Nov-1993_.pdf | /home/edik/projects/eccjeu/data/raw/com_legacy/files/html/31993D0668_EN.html | /home/edik/projects/eccjeu/data/raw/com_legacy/files/pdfs/31993D0668_EN.pdf | /home/edik/projects/eccjeu/data/raw/com_legacy/files/html/31993D0668_DE.html | R376: /home/edik/projects/eccjeu/data/raw/com_db_comp/files/32031-Auditel-_Nov-1993_.pdf | /home/edik/projects/eccjeu/data/raw/com_legacy/files/html/31993D0668_EN.html | /home/edik/projects/eccjeu/data/raw/com_legacy/files/pdfs/31993D0668_EN.pdf | /home/edik/projects/eccjeu/data/raw/com_legacy/files/html/31993D0668_DE.html | S376: /home/edik/projects/eccjeu/output/com_db_comp/db_comp_metadata_manifest.csv | /home/edik/projects/eccjeu/input/andrea_input.csv | /home/edik/projects/eccjeu/output/com_legacy/download_case_manifest.csv
A377: 34324 | B377: =YEAR(A377) -> 1993 | D377: Infringement | E377: Rodby | F377: andrea | manual | G377: 371 | manual_000007 | H377: andrea:371 | manual:manual_000007 | J377: 1993/12/21/missing_case | K377: 1993/12/21/missing_case/andrea | 1993/12/21/missing_case/manual | L377: TRUE | M377: FALSE | N377: reference_only | manual_injection | P377: https://eur-lex.europa.eu/legal-content/EN/TXT/HTML/?uri=CELEX:31994D0119 | S377: /home/edik/projects/eccjeu/input/andrea_input.csv | /home/edik/projects/eccjeu/input/commission_manual_injection.csv
A378: 34324 | B378: =YEAR(A378) -> 1993 | C378: 29420 | D378: Exemption | Exemption Decision | E378: GRUNDIG (SYSTEME DE DISTRIBUTION) | F378: andrea | com_legacy | G378: 370 | com_legacy_1993_line_2 | H378: andrea:370 | com_legacy:com_legacy_1993_line_2 | I378: 29420 | IV/29420 | J378: 1993/12/21/29420 | K378: 1993/12/21/29420/andrea | 1993/12/21/29420/com_legacy | L378: TRUE | M378: TRUE | N378: reference_only | already_downloaded | O378: http://ec.europa.eu/competition/antitrust/closed/en/1993.html | P378: https://eur-lex.europa.eu/legal-content/EN/TXT/HTML/?uri=CELEX:31994D0029 | https://eur-lex.europa.eu/legal-content/EN/TXT/PDF/?uri=CELEX:31994D0029 | https://eur-lex.europa.eu/legal-content/DE/TXT/HTML/?uri=CELEX:31994D0029 | https://eur-lex.europa.eu/legal-content/DE/TXT/PDF/?uri=CELEX:31994D0029 | Q378: /home/edik/projects/eccjeu/data/raw/com_legacy/files/html/31994D0029_EN.html | /home/edik/projects/eccjeu/data/raw/com_legacy/files/pdfs/31994D0029_EN.pdf | /home/edik/projects/eccjeu/data/raw/com_legacy/files/html/31994D0029_DE.html | R378: /home/edik/projects/eccjeu/data/raw/com_legacy/files/html/31994D0029_EN.html | /home/edik/projects/eccjeu/data/raw/com_legacy/files/pdfs/31994D0029_EN.pdf | /home/edik/projects/eccjeu/data/raw/com_legacy/files/html/31994D0029_DE.html | S378: /home/edik/projects/eccjeu/input/andrea_input.csv | /home/edik/projects/eccjeu/output/com_legacy/download_case_manifest.csv
A379: 34324 | B379: =YEAR(A379) -> 1993 | C379: 34689 | D379: Interim Measures Decision | E379: Sea Containers / Stena Line | F379: com_legacy | G379: com_legacy_1993_line_5 | H379: com_legacy:com_legacy_1993_line_5 | I379: IV/34689 | J379: 1993/12/21/34689 | K379: 1993/12/21/34689/com_legacy | L379: TRUE | M379: TRUE | N379: already_downloaded | O379: http://ec.europa.eu/competition/antitrust/closed/en/1993.html | P379: https://eur-lex.europa.eu/legal-content/EN/TXT/HTML/?uri=CELEX:31994D0019 | https://eur-lex.europa.eu/legal-content/EN/TXT/PDF/?uri=CELEX:31994D0019 | https://eur-lex.europa.eu/legal-content/DE/TXT/HTML/?uri=CELEX:31994D0019 | https://eur-lex.europa.eu/legal-content/DE/TXT/PDF/?uri=CELEX:31994D0019 | Q379: /home/edik/projects/eccjeu/data/raw/com_legacy/files/html/31994D0019_EN.html | /home/edik/projects/eccjeu/data/raw/com_legacy/files/pdfs/31994D0019_EN.pdf | /home/edik/projects/eccjeu/data/raw/com_legacy/files/html/31994D0019_DE.html | R379: /home/edik/projects/eccjeu/data/raw/com_legacy/files/html/31994D0019_EN.html | /home/edik/projects/eccjeu/data/raw/com_legacy/files/pdfs/31994D0019_EN.pdf | /home/edik/projects/eccjeu/data/raw/com_legacy/files/html/31994D0019_DE.html | S379: /home/edik/projects/eccjeu/output/com_legacy/download_case_manifest.csv
A380: 34386 | B380: =YEAR(A380) -> 1994 | C380: 30525 | D380: Exemption | Exemption Decision | E380: International Energy Agency | F380: andrea | com_legacy | G380: 372 | com_legacy_1994_line_76 | H380: andrea:372 | com_legacy:com_legacy_1994_line_76 | I380: 30525 | IV/30525 | J380: 1994/02/21/30525 | K380: 1994/02/21/30525/andrea | 1994/02/21/30525/com_legacy | L380: TRUE | M380: TRUE | N380: reference_only | already_downloaded | O380: http://ec.europa.eu/competition/antitrust/closed/en/1994.html | P380: https://eur-lex.europa.eu/legal-content/EN/TXT/HTML/?uri=CELEX:31994D0153 | https://eur-lex.europa.eu/legal-content/EN/TXT/PDF/?uri=CELEX:31994D0153 | https://eur-lex.europa.eu/legal-content/DE/TXT/HTML/?uri=CELEX:31994D0153 | https://eur-lex.europa.eu/legal-content/DE/TXT/PDF/?uri=CELEX:31994D0153 | http://ec.europa.eu/competition/search.html | http://ec.europa.eu/competition/antitrust/closed/en/1994.html#top | Q380: /home/edik/projects/eccjeu/data/raw/com_legacy/files/html/31994D0153_EN.html | /home/edik/projects/eccjeu/data/raw/com_legacy/files/pdfs/31994D0153_EN.pdf | /home/edik/projects/eccjeu/data/raw/com_legacy/files/html/31994D0153_DE.html | /home/edik/projects/eccjeu/data/raw/com_legacy/files/html/search.html | /home/edik/projects/eccjeu/data/raw/com_legacy/files/html/1994.html | R380: /home/edik/projects/eccjeu/data/raw/com_legacy/files/html/31994D0153_EN.html | /home/edik/projects/eccjeu/data/raw/com_legacy/files/pdfs/31994D0153_EN.pdf | /home/edik/projects/eccjeu/data/raw/com_legacy/files/html/31994D0153_DE.html | /home/edik/projects/eccjeu/data/raw/com_legacy/files/html/search.html | /home/edik/projects/eccjeu/data/raw/com_legacy/files/html/1994.html | S380: /home/edik/projects/eccjeu/input/andrea_input.csv | /home/edik/projects/eccjeu/output/com_legacy/download_case_manifest.csv
A381: 34422 | B381: =YEAR(A381) -> 1994 | C381: 33941 | D381: Infringement | not_exclusion_candidate | Prohibition Decision | E381: HOV SVZ / MCN | HOV SVZ/MCN | F381: andrea | com_db_comp | com_legacy | G381: 373 | 1450 | com_legacy_1994_line_71 | H381: andrea:373 | com_db_comp:1450 | com_legacy:com_legacy_1994_line_71 | I381: 33941 | IV/33941 | J381: 1994/03/29/33941 | K381: 1994/03/29/33941/andrea | 1994/03/29/33941/com_db_comp | 1994/03/29/33941/com_legacy | L381: TRUE | M381: TRUE | N381: reference_only | already_downloaded | O381: https://db-comp.eu/document_1450.download | http://ec.europa.eu/competition/antitrust/closed/en/1994.html | P381: https://db-comp.eu/document_1450.download | https://eur-lex.europa.eu/legal-content/EN/TXT/HTML/?uri=CELEX:31994D0210 | https://eur-lex.europa.eu/legal-content/EN/TXT/PDF/?uri=CELEX:31994D0210 | https://eur-lex.europa.eu/legal-content/DE/TXT/HTML/?uri=CELEX:31994D0210 | https://eur-lex.europa.eu/legal-content/DE/TXT/PDF/?uri=CELEX:31994D0210 | Q381: /home/edik/projects/eccjeu/data/raw/com_db_comp/files/33941-HOV-SVZ-MCN-_March-1994_.pdf | /home/edik/projects/eccjeu/data/raw/com_legacy/files/html/31994D0210_EN.html | /home/edik/projects/eccjeu/data/raw/com_legacy/files/pdfs/31994D0210_EN.pdf | /home/edik/projects/eccjeu/data/raw/com_legacy/files/html/31994D0210_DE.html | R381: /home/edik/projects/eccjeu/data/raw/com_db_comp/files/33941-HOV-SVZ-MCN-_March-1994_.pdf | /home/edik/projects/eccjeu/data/raw/com_legacy/files/html/31994D0210_EN.html | /home/edik/projects/eccjeu/data/raw/com_legacy/files/pdfs/31994D0210_EN.pdf | /home/edik/projects/eccjeu/data/raw/com_legacy/files/html/31994D0210_DE.html | S381: /home/edik/projects/eccjeu/input/andrea_input.csv | /home/edik/projects/eccjeu/output/com_db_comp/db_comp_metadata_manifest.csv | /home/edik/projects/eccjeu/output/com_legacy/download_case_manifest.csv
A382: 34437 | B382: =YEAR(A382) -> 1994 | C382: 34179 | D382: Infringement | Procedural Decision | E382: Stichting Certificatie Kraanverhuurbedrijf and FNK | F382: andrea | com_legacy | G382: 374 | com_legacy_1994_line_68 | H382: andrea:374 | com_legacy:com_legacy_1994_line_68 | I382: 34179 | IV/34179 | J382: 1994/04/13/34179 | K382: 1994/04/13/34179/andrea | 1994/04/13/34179/com_legacy | L382: TRUE | M382: TRUE | N382: reference_only | already_downloaded | O382: http://ec.europa.eu/competition/antitrust/closed/en/1994.html | P382: https://eur-lex.europa.eu/legal-content/EN/TXT/HTML/?uri=CELEX:31994D0272 | https://eur-lex.europa.eu/legal-content/EN/TXT/PDF/?uri=CELEX:31994D0272 | https://eur-lex.europa.eu/legal-content/DE/TXT/HTML/?uri=CELEX:31994D0272 | https://eur-lex.europa.eu/legal-content/DE/TXT/PDF/?uri=CELEX:31994D0272 | Q382: /home/edik/projects/eccjeu/data/raw/com_legacy/files/html/31994D0272_EN.html | /home/edik/projects/eccjeu/data/raw/com_legacy/files/pdfs/31994D0272_EN.pdf | /home/edik/projects/eccjeu/data/raw/com_legacy/files/html/31994D0272_DE.html | R382: /home/edik/projects/eccjeu/data/raw/com_legacy/files/html/31994D0272_EN.html | /home/edik/projects/eccjeu/data/raw/com_legacy/files/pdfs/31994D0272_EN.pdf | /home/edik/projects/eccjeu/data/raw/com_legacy/files/html/31994D0272_DE.html | S382: /home/edik/projects/eccjeu/input/andrea_input.csv | /home/edik/projects/eccjeu/output/com_legacy/download_case_manifest.csv
A383: 34453 | B383: =YEAR(A383) -> 1994 | C383: 34456 | D383: Exemption | not_exclusion_candidate | Exemption Decision | E383: STICHTING BAKSTEEN | Stichting Baksteen | F383: andrea | com_db_comp | com_legacy | G383: 375 | 1439 | com_legacy_1994_line_65 | H383: andrea:375 | com_db_comp:1439 | com_legacy:com_legacy_1994_line_65 | I383: 34456 | IV/34456 | J383: 1994/04/29/34456 | K383: 1994/04/29/34456/andrea | 1994/04/29/34456/com_db_comp | 1994/04/29/34456/com_legacy | L383: TRUE | M383: TRUE | N383: reference_only | already_downloaded | O383: https://db-comp.eu/document_1439.download | http://ec.europa.eu/competition/antitrust/closed/en/1994.html | P383: https://db-comp.eu/document_1439.download | https://eur-lex.europa.eu/legal-content/EN/TXT/HTML/?uri=CELEX:31994D0296 | https://eur-lex.europa.eu/legal-content/EN/TXT/PDF/?uri=CELEX:31994D0296 | https://eur-lex.europa.eu/legal-content/DE/TXT/HTML/?uri=CELEX:31994D0296 | https://eur-lex.europa.eu/legal-content/DE/TXT/PDF/?uri=CELEX:31994D0296 | Q383: /home/edik/projects/eccjeu/data/raw/com_db_comp/files/34456-Stichting-Baksteen-_April-1994_.pdf | /home/edik/projects/eccjeu/data/raw/com_legacy/files/html/31994D0296_EN.html | /home/edik/projects/eccjeu/data/raw/com_legacy/files/pdfs/31994D0296_EN.pdf | /home/edik/projects/eccjeu/data/raw/com_legacy/files/html/31994D0296_DE.html | R383: /home/edik/projects/eccjeu/data/raw/com_db_comp/files/34456-Stichting-Baksteen-_April-1994_.pdf | /home/edik/projects/eccjeu/data/raw/com_legacy/files/html/31994D0296_EN.html | /home/edik/projects/eccjeu/data/raw/com_legacy/files/pdfs/31994D0296_EN.pdf | /home/edik/projects/eccjeu/data/raw/com_legacy/files/html/31994D0296_DE.html | S383: /home/edik/projects/eccjeu/input/andrea_input.csv | /home/edik/projects/eccjeu/output/com_db_comp/db_comp_metadata_manifest.csv | /home/edik/projects/eccjeu/output/com_legacy/download_case_manifest.csv
A384: 34472 | B384: =YEAR(A384) -> 1994 | C384: 33640 | D384: Exemption | not_exclusion_candidate | Exemption Decision | E384: EXXON / SHELL | Exxon/Shell | F384: andrea | com_db_comp | com_legacy | G384: 376 | 1461 | com_legacy_1994_line_62 | H384: andrea:376 | com_db_comp:1461 | com_legacy:com_legacy_1994_line_62 | I384: 33640 | IV/33640 | J384: 1994/05/18/33640 | K384: 1994/05/18/33640/andrea | 1994/05/18/33640/com_db_comp | 1994/05/18/33640/com_legacy | L384: TRUE | M384: TRUE | N384: reference_only | already_downloaded | O384: https://db-comp.eu/document_1461.download | http://ec.europa.eu/competition/antitrust/closed/en/1994.html | P384: https://db-comp.eu/document_1461.download | https://eur-lex.europa.eu/legal-content/EN/TXT/HTML/?uri=CELEX:31994D0322 | https://eur-lex.europa.eu/legal-content/EN/TXT/PDF/?uri=CELEX:31994D0322 | https://eur-lex.europa.eu/legal-content/DE/TXT/HTML/?uri=CELEX:31994D0322 | https://eur-lex.europa.eu/legal-content/DE/TXT/PDF/?uri=CELEX:31994D0322 | Q384: /home/edik/projects/eccjeu/data/raw/com_db_comp/files/33640-Exxon-Shell-_May-1994_.pdf | /home/edik/projects/eccjeu/data/raw/com_legacy/files/html/31994D0322_EN.html | /home/edik/projects/eccjeu/data/raw/com_legacy/files/pdfs/31994D0322_EN.pdf | /home/edik/projects/eccjeu/data/raw/com_legacy/files/html/31994D0322_DE.html | R384: /home/edik/projects/eccjeu/data/raw/com_db_comp/files/33640-Exxon-Shell-_May-1994_.pdf | /home/edik/projects/eccjeu/data/raw/com_legacy/files/html/31994D0322_EN.html | /home/edik/projects/eccjeu/data/raw/com_legacy/files/pdfs/31994D0322_EN.pdf | /home/edik/projects/eccjeu/data/raw/com_legacy/files/html/31994D0322_DE.html | S384: /home/edik/projects/eccjeu/input/andrea_input.csv | /home/edik/projects/eccjeu/output/com_db_comp/db_comp_metadata_manifest.csv | /home/edik/projects/eccjeu/output/com_legacy/download_case_manifest.csv
A385: 34491 | B385: =YEAR(A385) -> 1994 | C385: 32075 | D385: Exemption | Exemption Decision | E385: BAYER / BP Chemicals | F385: andrea | com_legacy | G385: 377 | com_legacy_1994_line_59 | H385: andrea:377 | com_legacy:com_legacy_1994_line_59 | I385: 32075 | IV/32075 | J385: 1994/06/06/32075 | K385: 1994/06/06/32075/andrea | 1994/06/06/32075/com_legacy | L385: TRUE | M385: TRUE | N385: reference_only | already_downloaded | O385: http://ec.europa.eu/competition/antitrust/closed/en/1994.html | P385: https://eur-lex.europa.eu/legal-content/EN/TXT/HTML/?uri=CELEX:31994D0384 | https://eur-lex.europa.eu/legal-content/EN/TXT/PDF/?uri=CELEX:31994D0384 | https://eur-lex.europa.eu/legal-content/DE/TXT/HTML/?uri=CELEX:31994D0384 | https://eur-lex.europa.eu/legal-content/DE/TXT/PDF/?uri=CELEX:31994D0384 | Q385: /home/edik/projects/eccjeu/data/raw/com_legacy/files/html/31994D0384_EN.html | /home/edik/projects/eccjeu/data/raw/com_legacy/files/pdfs/31994D0384_EN.pdf | /home/edik/projects/eccjeu/data/raw/com_legacy/files/html/31994D0384_DE.html | R385: /home/edik/projects/eccjeu/data/raw/com_legacy/files/html/31994D0384_EN.html | /home/edik/projects/eccjeu/data/raw/com_legacy/files/pdfs/31994D0384_EN.pdf | /home/edik/projects/eccjeu/data/raw/com_legacy/files/html/31994D0384_DE.html | S385: /home/edik/projects/eccjeu/input/andrea_input.csv | /home/edik/projects/eccjeu/output/com_legacy/download_case_manifest.csv
A386: 34528 | B386: =YEAR(A386) -> 1994 | C386: 33833 | D386: Infringement | not_exclusion_candidate | Prohibition Decision | E386: CARTONBOARD | Cartonboard EU | F386: andrea | com_db_comp | com_legacy | G386: 378 | 1453 | com_legacy_1994_line_54 | H386: andrea:378 | com_db_comp:1453 | com_legacy:com_legacy_1994_line_54 | I386: 33833 | IV/33833 | J386: 1994/07/13/33833 | K386: 1994/07/13/33833/andrea | 1994/07/13/33833/com_db_comp | 1994/07/13/33833/com_legacy | L386: TRUE | M386: TRUE | N386: reference_only | already_downloaded | O386: https://db-comp.eu/document_1453.download | http://ec.europa.eu/competition/antitrust/closed/en/1994.html | P386: https://db-comp.eu/document_1453.download | https://eur-lex.europa.eu/legal-content/EN/TXT/HTML/?uri=CELEX:31994D0601 | https://eur-lex.europa.eu/legal-content/EN/TXT/PDF/?uri=CELEX:31994D0601 | https://eur-lex.europa.eu/legal-content/DE/TXT/HTML/?uri=CELEX:31994D0601 | https://eur-lex.europa.eu/legal-content/DE/TXT/PDF/?uri=CELEX:31994D0601 | Q386: /home/edik/projects/eccjeu/data/raw/com_db_comp/files/33833-Cartonboard-_July-1994_.pdf | /home/edik/projects/eccjeu/data/raw/com_legacy/files/html/31994D0601_EN.html | /home/edik/projects/eccjeu/data/raw/com_legacy/files/pdfs/31994D0601_EN.pdf | /home/edik/projects/eccjeu/data/raw/com_legacy/files/html/31994D0601_DE.html | R386: /home/edik/projects/eccjeu/data/raw/com_db_comp/files/33833-Cartonboard-_July-1994_.pdf | /home/edik/projects/eccjeu/data/raw/com_legacy/files/html/31994D0601_EN.html | /home/edik/projects/eccjeu/data/raw/com_legacy/files/pdfs/31994D0601_EN.pdf | /home/edik/projects/eccjeu/data/raw/com_legacy/files/html/31994D0601_DE.html | S386: /home/edik/projects/eccjeu/input/andrea_input.csv | /home/edik/projects/eccjeu/output/com_db_comp/db_comp_metadata_manifest.csv | /home/edik/projects/eccjeu/output/com_legacy/download_case_manifest.csv
A387: 34542 | B387: =YEAR(A387) -> 1994 | C387: 31865 | D387: Infringement | Prohibition Decision | E387: PVC | F387: andrea | com_legacy | G387: 381 | com_legacy_1994_line_51 | H387: andrea:381 | com_legacy:com_legacy_1994_line_51 | I387: 31865 | IV/31865 | J387: 1994/07/27/31865 | K387: 1994/07/27/31865/andrea | 1994/07/27/31865/com_legacy | L387: TRUE | M387: TRUE | N387: reference_only | already_downloaded | O387: http://ec.europa.eu/competition/antitrust/closed/en/1994.html | P387: https://eur-lex.europa.eu/legal-content/EN/TXT/HTML/?uri=CELEX:31994D0599 | https://eur-lex.europa.eu/legal-content/EN/TXT/PDF/?uri=CELEX:31994D0599 | https://eur-lex.europa.eu/legal-content/DE/TXT/HTML/?uri=CELEX:31994D0599 | https://eur-lex.europa.eu/legal-content/DE/TXT/PDF/?uri=CELEX:31994D0599 | Q387: /home/edik/projects/eccjeu/data/raw/com_legacy/files/html/31994D0599_EN.html | /home/edik/projects/eccjeu/data/raw/com_legacy/files/pdfs/31994D0599_EN.pdf | /home/edik/projects/eccjeu/data/raw/com_legacy/files/html/31994D0599_DE.html | R387: /home/edik/projects/eccjeu/data/raw/com_legacy/files/html/31994D0599_EN.html | /home/edik/projects/eccjeu/data/raw/com_legacy/files/pdfs/31994D0599_EN.pdf | /home/edik/projects/eccjeu/data/raw/com_legacy/files/html/31994D0599_DE.html | S387: /home/edik/projects/eccjeu/input/andrea_input.csv | /home/edik/projects/eccjeu/output/com_legacy/download_case_manifest.csv
A388: 34542 | B388: =YEAR(A388) -> 1994 | C388: 34518 | D388: Exemption | not_exclusion_candidate | Exemption Decision | E388: ACI | F388: andrea | com_db_comp | com_legacy | G388: 380 | 1433 | com_legacy_1994_line_45 | H388: andrea:380 | com_db_comp:1433 | com_legacy:com_legacy_1994_line_45 | I388: 34518 | IV/34518 | J388: 1994/07/27/34518 | K388: 1994/07/27/34518/andrea | 1994/07/27/34518/com_db_comp | 1994/07/27/34518/com_legacy | L388: TRUE | M388: TRUE | N388: reference_only | already_downloaded | O388: https://db-comp.eu/document_1433.download | http://ec.europa.eu/competition/antitrust/closed/en/1994.html | P388: https://db-comp.eu/document_1433.download | https://eur-lex.europa.eu/legal-content/EN/TXT/HTML/?uri=CELEX:31994D0594 | https://eur-lex.europa.eu/legal-content/EN/TXT/PDF/?uri=CELEX:31994D0594 | https://eur-lex.europa.eu/legal-content/DE/TXT/HTML/?uri=CELEX:31994D0594 | https://eur-lex.europa.eu/legal-content/DE/TXT/PDF/?uri=CELEX:31994D0594 | Q388: /home/edik/projects/eccjeu/data/raw/com_db_comp/files/34518-ACI-_July-1994_.pdf | /home/edik/projects/eccjeu/data/raw/com_legacy/files/html/31994D0594_EN.html | /home/edik/projects/eccjeu/data/raw/com_legacy/files/pdfs/31994D0594_EN.pdf | /home/edik/projects/eccjeu/data/raw/com_legacy/files/html/31994D0594_DE.html | R388: /home/edik/projects/eccjeu/data/raw/com_db_comp/files/34518-ACI-_July-1994_.pdf | /home/edik/projects/eccjeu/data/raw/com_legacy/files/html/31994D0594_EN.html | /home/edik/projects/eccjeu/data/raw/com_legacy/files/pdfs/31994D0594_EN.pdf | /home/edik/projects/eccjeu/data/raw/com_legacy/files/html/31994D0594_DE.html | S388: /home/edik/projects/eccjeu/input/andrea_input.csv | /home/edik/projects/eccjeu/output/com_db_comp/db_comp_metadata_manifest.csv | /home/edik/projects/eccjeu/output/com_legacy/download_case_manifest.csv
A389: 34542 | B389: =YEAR(A389) -> 1994 | C389: 34857 | D389: Exemption and Negative Claerance | not_exclusion_candidate | Mixed Exemption / Negative Clearance Decision | E389: BT & MCI | BT/MCI | BT | MCI | F389: andrea | com_db_comp | com_legacy | G389: 379 | 1425 | com_legacy_1994_line_48 | H389: andrea:379 | com_db_comp:1425 | com_legacy:com_legacy_1994_line_48 | I389: 34857 | IV/34857 | J389: 1994/07/27/34857 | K389: 1994/07/27/34857/andrea | 1994/07/27/34857/com_db_comp | 1994/07/27/34857/com_legacy | L389: TRUE | M389: TRUE | N389: reference_only | already_downloaded | O389: https://db-comp.eu/document_1425.download | http://ec.europa.eu/competition/antitrust/closed/en/1994.html | P389: https://db-comp.eu/document_1425.download | https://eur-lex.europa.eu/legal-content/EN/TXT/HTML/?uri=CELEX:31994D0579 | https://eur-lex.europa.eu/legal-content/EN/TXT/PDF/?uri=CELEX:31994D0579 | https://eur-lex.europa.eu/legal-content/DE/TXT/HTML/?uri=CELEX:31994D0579 | https://eur-lex.europa.eu/legal-content/DE/TXT/PDF/?uri=CELEX:31994D0579 | Q389: /home/edik/projects/eccjeu/data/raw/com_db_comp/files/34857-PT-MCI-_July-1994_.pdf | /home/edik/projects/eccjeu/data/raw/com_legacy/files/html/31994D0579_EN.html | /home/edik/projects/eccjeu/data/raw/com_legacy/files/pdfs/31994D0579_EN.pdf | /home/edik/projects/eccjeu/data/raw/com_legacy/files/html/31994D0579_DE.html | R389: /home/edik/projects/eccjeu/data/raw/com_db_comp/files/34857-PT-MCI-_July-1994_.pdf | /home/edik/projects/eccjeu/data/raw/com_legacy/files/html/31994D0579_EN.html | /home/edik/projects/eccjeu/data/raw/com_legacy/files/pdfs/31994D0579_EN.pdf | /home/edik/projects/eccjeu/data/raw/com_legacy/files/html/31994D0579_DE.html | S389: /home/edik/projects/eccjeu/input/andrea_input.csv | /home/edik/projects/eccjeu/output/com_db_comp/db_comp_metadata_manifest.csv | /home/edik/projects/eccjeu/output/com_legacy/download_case_manifest.csv
... A406: 34835 | B406: =YEAR(A406) -> 1995 | C406: 35388 | D406: Interim Measures Decision | not_exclusion_candidate | E406: Irish Continental Group v./ CCI Morlaix (Roscoff) | Irish Continental Group v. CCI Morlaix | F406: com_antitrust | com_db_comp | G406: AT.35388+16-05-1995 | 1991 | H406: com_antitrust:AT.35388+16-05-1995 | com_db_comp:1991 | I406: AT.35388 | 35388 | J406: 1995/05/16/35388 | K406: 1995/05/16/35388/com_antitrust | 1995/05/16/35388/com_db_comp | L406: TRUE | M406: TRUE | N406: already_exists | O406: https://ec.europa.eu/competition/antitrust/cases/dec_docs/35388/35388_9_5.pdf | https://db-comp.eu/document_1991.download | P406: https://ec.europa.eu/competition/antitrust/cases/dec_docs/35388/35388_9_5.pdf | https://db-comp.eu/document_1991.download | Q406: /home/edik/projects/eccjeu/data/raw/com_antitrust/COM39_AT.35388_16-05-1995_decision_interim_measures_decision_main_cfa33006a6.pdf | /home/edik/projects/eccjeu/data/raw/com_db_comp/files/35388-Irish-Continental-Group-_interim-measures_.pdf | R406: /home/edik/projects/eccjeu/data/raw/com_antitrust/COM39_AT.35388_16-05-1995_decision_interim_measures_decision_main_cfa33006a6.pdf | /home/edik/projects/eccjeu/data/raw/com_db_comp/files/35388-Irish-Continental-Group-_interim-measures_.pdf | S406: /home/edik/projects/eccjeu/output/com_antitrust/download_com_antitrust_decisions.csv | /home/edik/projects/eccjeu/output/com_db_comp/db_comp_metadata_manifest.csv
A407: 34878 | B407: =YEAR(A407) -> 1995 | D407: Infringement | E407: Zaventem | F407: andrea | manual | G407: 397 | manual_000003 | H407: andrea:397 | manual:manual_000003 | J407: 1995/06/28/missing_case | K407: 1995/06/28/missing_case/andrea | 1995/06/28/missing_case/manual | L407: TRUE | M407: FALSE | N407: reference_only | manual_injection | P407: https://eur-lex.europa.eu/legal-content/EN/TXT/HTML/?from=FR&uri=CELEX%3A31995D0364 | S407: /home/edik/projects/eccjeu/input/andrea_input.csv | /home/edik/projects/eccjeu/input/commission_manual_injection.csv
A408: 34892 | B408: =YEAR(A408) -> 1995 | C408: 33802 | D408: Infringement | not_exclusion_candidate | Prohibition Decision | E408: BASF Lacke & Farben AG, Accinauto Sa | BASF Lacke and Farben | BASF Lacke+Farben AG, and Accinauto SA | F408: andrea | com_db_comp | com_legacy | G408: 398 | 1455 | com_legacy_1995_line_19 | H408: andrea:398 | com_db_comp:1455 | com_legacy:com_legacy_1995_line_19 | I408: 33802 | IV/33802 | J408: 1995/12/07/33802 | K408: 1995/12/07/33802/andrea | 1995/12/07/33802/com_db_comp | 1995/12/07/33802/com_legacy | L408: TRUE | M408: TRUE | N408: reference_only | already_downloaded | O408: https://db-comp.eu/document_1455.download | http://ec.europa.eu/competition/antitrust/closed/en/1995.html | P408: https://db-comp.eu/document_1455.download | https://eur-lex.europa.eu/legal-content/EN/TXT/HTML/?uri=CELEX:31995D0477 | https://eur-lex.europa.eu/legal-content/EN/TXT/PDF/?uri=CELEX:31995D0477 | https://eur-lex.europa.eu/legal-content/DE/TXT/HTML/?uri=CELEX:31995D0477 | https://eur-lex.europa.eu/legal-content/DE/TXT/PDF/?uri=CELEX:31995D0477 | Q408: /home/edik/projects/eccjeu/data/raw/com_db_comp/files/33802-BASF-Lacke-and-Farben-_July-1995_.pdf | /home/edik/projects/eccjeu/data/raw/com_legacy/files/html/31995D0477_EN.html | /home/edik/projects/eccjeu/data/raw/com_legacy/files/pdfs/31995D0477_EN.pdf | /home/edik/projects/eccjeu/data/raw/com_legacy/files/html/31995D0477_DE.html | R408: /home/edik/projects/eccjeu/data/raw/com_db_comp/files/33802-BASF-Lacke-and-Farben-_July-1995_.pdf | /home/edik/projects/eccjeu/data/raw/com_legacy/files/html/31995D0477_EN.html | /home/edik/projects/eccjeu/data/raw/com_legacy/files/pdfs/31995D0477_EN.pdf | /home/edik/projects/eccjeu/data/raw/com_legacy/files/html/31995D0477_DE.html | S408: /home/edik/projects/eccjeu/input/andrea_input.csv | /home/edik/projects/eccjeu/output/com_db_comp/db_comp_metadata_manifest.csv | /home/edik/projects/eccjeu/output/com_legacy/download_case_manifest.csv
A409: 34976 | B409: =YEAR(A409) -> 1995 | D409: Infringement | E409: GSM Italia | F409: andrea | manual | G409: 399 | manual_000008 | H409: andrea:399 | manual:manual_000008 | J409: 1995/04/10/missing_case | K409: 1995/04/10/missing_case/andrea | 1995/04/10/missing_case/manual | L409: TRUE | M409: FALSE | N409: reference_only | manual_injection | P409: https://eur-lex.europa.eu/legal-content/EN/TXT/HTML/?uri=CELEX:31995D0489&qid=1783330076967 | S409: /home/edik/projects/eccjeu/input/andrea_input.csv | /home/edik/projects/eccjeu/input/commission_manual_injection.csv
A410: 35032 | B410: =YEAR(A410) -> 1995 | C410: 34179; 34202; 34216 | D410: Prohibition Decision | not_exclusion_candidate | Infringement | E410: SCK/FNK | Stichting Certificatie Kraanverhuurbedrijf and the Federatie van Nederlandse Kraanverhuurbedrijven | SCK / FNK | F410: com_legacy | com_db_comp | andrea | G410: com_legacy_1995_line_8 | 1446 | 400 | H410: com_legacy:com_legacy_1995_line_8 | com_db_comp:1446 | andrea:400 | I410: IV/34216 | IV/34179 | IV/34202 | 34179 | 34202 | 34216, 34179, 34202 | J410: 1995/11/29/216/34179/34202 | 1995/11/29/34179/34202 | 1995/11/29/34179/34202/34216 | K410: 1995/11/29/216/34179/34202/com_legacy | 1995/11/29/34179/34202/com_db_comp | 1995/11/29/34179/34202/34216/andrea | L410: TRUE | M410: TRUE | N410: already_downloaded | reference_only | O410: http://ec.europa.eu/competition/antitrust/closed/en/1995.html | https://db-comp.eu/document_1446.download | P410: https://eur-lex.europa.eu/legal-content/EN/TXT/HTML/?uri=CELEX:31995D0551 | https://eur-lex.europa.eu/legal-content/EN/TXT/PDF/?uri=CELEX:31995D0551 | https://eur-lex.europa.eu/legal-content/DE/TXT/HTML/?uri=CELEX:31995D0551 | https://eur-lex.europa.eu/legal-content/DE/TXT/PDF/?uri=CELEX:31995D0551 | https://db-comp.eu/document_1446.download | Q410: /home/edik/projects/eccjeu/data/raw/com_legacy/files/html/31995D0551_EN.html | /home/edik/projects/eccjeu/data/raw/com_legacy/files/pdfs/31995D0551_EN.pdf | /home/edik/projects/eccjeu/data/raw/com_legacy/files/html/31995D0551_DE.html | /home/edik/projects/eccjeu/data/raw/com_db_comp/files/34179-34202-Stichting-Certificatie-Kraanverhuurbedrijf-and-the-Federatie-van-Nederlandse-Kraanverhuurbedrijven-_Nov-1995_.pdf | R410: /home/edik/projects/eccjeu/data/raw/com_legacy/files/html/31995D0551_EN.html | /home/edik/projects/eccjeu/data/raw/com_legacy/files/pdfs/31995D0551_EN.pdf | /home/edik/projects/eccjeu/data/raw/com_legacy/files/html/31995D0551_DE.html | /home/edik/projects/eccjeu/data/raw/com_db_comp/files/34179-34202-Stichting-Certificatie-Kraanverhuurbedrijf-and-the-Federatie-van-Nederlandse-Kraanverhuurbedrijven-_Nov-1995_.pdf | S410: /home/edik/projects/eccjeu/output/com_legacy/download_case_manifest.csv | /home/edik/projects/eccjeu/output/com_db_comp/db_comp_metadata_manifest.csv | /home/edik/projects/eccjeu/input/andrea_input.csv
A411: 35039 | B411: =YEAR(A411) -> 1995 | C411: 35808 | D411: Exemption without condition (Reg 17/62) | E411: MEDSAP Consortium | F411: com_antitrust | G411: AT.35808+06-12-1995 | H411: com_antitrust:AT.35808+06-12-1995 | I411: AT.35808 | J411: 1995/06/12/35808 | K411: 1995/06/12/35808/com_antitrust | L411: TRUE | M411: TRUE | N411: already_exists | O411: https://ec.europa.eu/competition/antitrust/cases1/202508/AT_35808_2560764_5_4.pdf | P411: https://ec.europa.eu/competition/antitrust/cases1/202508/AT_35808_2560764_5_4.pdf | Q411: /home/edik/projects/eccjeu/data/raw/com_antitrust/COM58_AT.35808_06-12-1995_case_attachment_exemption_without_condition_reg_17-62_main_99fb8b2e30.pdf | R411: /home/edik/projects/eccjeu/data/raw/com_antitrust/COM58_AT.35808_06-12-1995_case_attachment_exemption_without_condition_reg_17-62_main_99fb8b2e30.pdf | S411: /home/edik/projects/eccjeu/output/com_antitrust/download_com_antitrust_decisions.csv
A412: 35074 | B412: =YEAR(A412) -> 1996 | C412: 34279 | D412: Infringement | not_exclusion_candidate | Prohibition Decision | E412: ADALAT | F412: andrea | com_db_comp | com_legacy | G412: 401 | 1443 | com_legacy_1996_line_52 | H412: andrea:401 | com_db_comp:1443 | com_legacy:com_legacy_1996_line_52 | I412: 34279 | IV/34279 | J412: 1996/10/01/34279 | K412: 1996/10/01/34279/andrea | 1996/10/01/34279/com_db_comp | 1996/10/01/34279/com_legacy | L412: TRUE | M412: TRUE | N412: reference_only | already_downloaded | O412: https://db-comp.eu/document_1443.download | http://ec.europa.eu/competition/antitrust/closed/en/1996.html | P412: https://db-comp.eu/document_1443.download | https://eur-lex.europa.eu/legal-content/EN/TXT/HTML/?uri=CELEX:31996D0478 | https://eur-lex.europa.eu/legal-content/EN/TXT/PDF/?uri=CELEX:31996D0478 | https://eur-lex.europa.eu/legal-content/DE/TXT/HTML/?uri=CELEX:31996D0478 | https://eur-lex.europa.eu/legal-content/DE/TXT/PDF/?uri=CELEX:31996D0478 | http://ec.europa.eu/competition/search.html | http://ec.europa.eu/competition/antitrust/closed/en/1996.html#top | Q412: /home/edik/projects/eccjeu/data/raw/com_db_comp/files/34279-ADALAT-_Jan-1996_.pdf | /home/edik/projects/eccjeu/data/raw/com_legacy/files/html/31996D0478_EN.html | /home/edik/projects/eccjeu/data/raw/com_legacy/files/pdfs/31996D0478_EN.pdf | /home/edik/projects/eccjeu/data/raw/com_legacy/files/html/31996D0478_DE.html | /home/edik/projects/eccjeu/data/raw/com_legacy/files/html/search.html | /home/edik/projects/eccjeu/data/raw/com_legacy/files/html/1996.html | R412: /home/edik/projects/eccjeu/data/raw/com_db_comp/files/34279-ADALAT-_Jan-1996_.pdf | /home/edik/projects/eccjeu/data/raw/com_legacy/files/html/31996D0478_EN.html | /home/edik/projects/eccjeu/data/raw/com_legacy/files/pdfs/31996D0478_EN.pdf | /home/edik/projects/eccjeu/data/raw/com_legacy/files/html/31996D0478_DE.html | /home/edik/projects/eccjeu/data/raw/com_legacy/files/html/search.html | /home/edik/projects/eccjeu/data/raw/com_legacy/files/html/1996.html | S412: /home/edik/projects/eccjeu/input/andrea_input.csv | /home/edik/projects/eccjeu/output/com_db_comp/db_comp_metadata_manifest.csv | /home/edik/projects/eccjeu/output/com_legacy/download_case_manifest.csv
A413: 35080 | B413: =YEAR(A413) -> 1996 | C413: 35545 | D413: Exemption | not_exclusion_candidate | Exemption Decision | E413: Lufthansa & SAS | LH/SAS | Luftansa+SAS | F413: andrea | com_db_comp | com_legacy | G413: 402 | 1411 | com_legacy_1996_line_49 | H413: andrea:402 | com_db_comp:1411 | com_legacy:com_legacy_1996_line_49 | I413: 35545 | IV/35545 | J413: 1996/01/16/35545 | K413: 1996/01/16/35545/andrea | 1996/01/16/35545/com_db_comp | 1996/01/16/35545/com_legacy | L413: TRUE | M413: TRUE | N413: reference_only | already_downloaded | O413: https://db-comp.eu/document_1411.download | http://ec.europa.eu/competition/antitrust/closed/en/1996.html | P413: https://db-comp.eu/document_1411.download | https://eur-lex.europa.eu/legal-content/EN/TXT/HTML/?uri=CELEX:31996D0180 | https://eur-lex.europa.eu/legal-content/EN/TXT/PDF/?uri=CELEX:31996D0180 | https://eur-lex.europa.eu/legal-content/DE/TXT/HTML/?uri=CELEX:31996D0180 | https://eur-lex.europa.eu/legal-content/DE/TXT/PDF/?uri=CELEX:31996D0180 | Q413: /home/edik/projects/eccjeu/data/raw/com_db_comp/files/35545-LH-SAS-_Jan-1996_.pdf | /home/edik/projects/eccjeu/data/raw/com_legacy/files/html/31996D0180_EN.html | /home/edik/projects/eccjeu/data/raw/com_legacy/files/pdfs/31996D0180_EN.pdf | /home/edik/projects/eccjeu/data/raw/com_legacy/files/html/31996D0180_DE.html | R413: /home/edik/projects/eccjeu/data/raw/com_db_comp/files/35545-LH-SAS-_Jan-1996_.pdf | /home/edik/projects/eccjeu/data/raw/com_legacy/files/html/31996D0180_EN.html | /home/edik/projects/eccjeu/data/raw/com_legacy/files/pdfs/31996D0180_EN.pdf | /home/edik/projects/eccjeu/data/raw/com_legacy/files/html/31996D0180_DE.html | S413: /home/edik/projects/eccjeu/input/andrea_input.csv | /home/edik/projects/eccjeu/output/com_db_comp/db_comp_metadata_manifest.csv | /home/edik/projects/eccjeu/output/com_legacy/download_case_manifest.csv
A414: 35093 | B414: =YEAR(A414) -> 1996 | C414: 35803 | D414: Exemption without condition (Reg 17/62) | E414: IPEX Consortium | F414: com_antitrust | G414: AT.35803+29-01-1996 | H414: com_antitrust:AT.35803+29-01-1996 | I414: AT.35803 | J414: 1996/01/29/35803 | K414: 1996/01/29/35803/com_antitrust | L414: TRUE | M414: TRUE | N414: already_exists | O414: https://ec.europa.eu/competition/antitrust/cases1/202508/AT_35803_2560633_5_4.pdf | P414: https://ec.europa.eu/competition/antitrust/cases1/202508/AT_35803_2560633_5_4.pdf | Q414: /home/edik/projects/eccjeu/data/raw/com_antitrust/COM56_AT.35803_29-01-1996_case_attachment_exemption_without_condition_reg_17-62_main_0fe9b1edd2.pdf | R414: /home/edik/projects/eccjeu/data/raw/com_antitrust/COM56_AT.35803_29-01-1996_case_attachment_exemption_without_condition_reg_17-62_main_0fe9b1edd2.pdf | S414: /home/edik/projects/eccjeu/output/com_antitrust/download_com_antitrust_decisions.csv
A415: 35124 | B415: =YEAR(A415) -> 1996 | C415: 35202 | D415: Negative Clearance Decision (Reg 17/62) | E415: Dampskibsselskabet Öresund | SweFerry | F415: com_antitrust | G415: AT.35202+29-02-1996 | H415: com_antitrust:AT.35202+29-02-1996 | I415: AT.35202 | J415: 1996/02/29/35202 | K415: 1996/02/29/35202/com_antitrust | L415: TRUE | M415: TRUE | N415: already_exists | O415: https://ec.europa.eu/competition/antitrust/cases1/202508/AT_35202_2560181_10_9.pdf | P415: https://ec.europa.eu/competition/antitrust/cases1/202508/AT_35202_2560181_10_9.pdf | Q415: /home/edik/projects/eccjeu/data/raw/com_antitrust/COM32_AT.35202_29-02-1996_case_attachment_negative_clearance_decision_reg_17-62_main_961a0b1276.pdf | R415: /home/edik/projects/eccjeu/data/raw/com_antitrust/COM32_AT.35202_29-02-1996_case_attachment_negative_clearance_decision_reg_17-62_main_961a0b1276.pdf | S415: /home/edik/projects/eccjeu/output/com_antitrust/download_com_antitrust_decisions.csv
A416: 35128 | B416: =YEAR(A416) -> 1996 | C416: 35807 | D416: Exemption without condition (Reg 17/62) | E416: MEDECS agreement | F416: com_antitrust | G416: AT.35807+04-03-1996 | H416: com_antitrust:AT.35807+04-03-1996 | I416: AT.35807 | J416: 1996/04/03/35807 | K416: 1996/04/03/35807/com_antitrust | L416: TRUE | M416: TRUE | N416: already_exists | O416: https://ec.europa.eu/competition/antitrust/cases1/202508/AT_35807_2560775_6_4.pdf | P416: https://ec.europa.eu/competition/antitrust/cases1/202508/AT_35807_2560775_6_4.pdf | Q416: /home/edik/projects/eccjeu/data/raw/com_antitrust/COM57_AT.35807_04-03-1996_case_attachment_exemption_without_condition_reg_17-62_main_9779f199b1.pdf | R416: /home/edik/projects/eccjeu/data/raw/com_antitrust/COM57_AT.35807_04-03-1996_case_attachment_exemption_without_condition_reg_17-62_main_9779f199b1.pdf | S416: /home/edik/projects/eccjeu/output/com_antitrust/download_com_antitrust_decisions.csv
A417: 35151 | B417: =YEAR(A417) -> 1996 | C417: 35754 | D417: Exemption without condition (Reg 17/62) | Exemption Decision | E417: Consortium East Africa Container Service (EACS) | EACS | F417: com_antitrust | com_legacy | G417: AT.35754+27-03-1996 | com_legacy_1996_line_45 | H417: com_antitrust:AT.35754+27-03-1996 | com_legacy:com_legacy_1996_line_45 | I417: AT.35754 | IV/35754 | J417: 1996/03/27/35754 | K417: 1996/03/27/35754/com_antitrust | 1996/03/27/35754/com_legacy | L417: TRUE | M417: TRUE | N417: already_exists | no_download_candidate | O417: https://ec.europa.eu/competition/antitrust/cases1/202508/AT_35754_2560095_5_6.pdf | http://ec.europa.eu/competition/antitrust/closed/en/1996.html | P417: https://ec.europa.eu/competition/antitrust/cases1/202508/AT_35754_2560095_5_6.pdf | Q417: /home/edik/projects/eccjeu/data/raw/com_antitrust/COM49_AT.35754_27-03-1996_case_attachment_exemption_without_condition_reg_17-62_main_31c1c8254e.pdf | R417: /home/edik/projects/eccjeu/data/raw/com_antitrust/COM49_AT.35754_27-03-1996_case_attachment_exemption_without_condition_reg_17-62_main_31c1c8254e.pdf | S417: /home/edik/projects/eccjeu/output/com_antitrust/download_com_antitrust_decisions.csv | /home/edik/projects/eccjeu/output/com_legacy/download_case_manifest.csv
A418: 35156 | B418: =YEAR(A418) -> 1996 | C418: 35768 | D418: Exemption Decision | Exemption without condition (Reg 17/62) | E418: A. Weir Shipping | Euro Africa Shipping Line | Joint Pool Agreement | F418: com_legacy | com_antitrust | G418: com_legacy_1996_line_41 | AT.35768+03-04-1996 | H418: com_legacy:com_legacy_1996_line_41 | com_antitrust:AT.35768+03-04-1996 | I418: IV/35768 | AT.35768 | J418: 1996/01/04/35768 | 1996/03/04/35768 | K418: 1996/01/04/35768/com_legacy | 1996/03/04/35768/com_antitrust | L418: TRUE | M418: TRUE | N418: no_download_candidate | already_exists | O418: http://ec.europa.eu/competition/antitrust/closed/en/1996.html | https://ec.europa.eu/competition/antitrust/cases1/202508/AT_35768_2560740_6_4.pdf | P418: https://ec.europa.eu/competition/antitrust/cases1/202508/AT_35768_2560740_6_4.pdf | Q418: /home/edik/projects/eccjeu/data/raw/com_antitrust/COM52_AT.35768_03-04-1996_case_attachment_exemption_without_condition_reg_17-62_main_e7a0c6f59d.pdf | R418: /home/edik/projects/eccjeu/data/raw/com_antitrust/COM52_AT.35768_03-04-1996_case_attachment_exemption_without_condition_reg_17-62_main_e7a0c6f59d.pdf | S418: /home/edik/projects/eccjeu/output/com_legacy/download_case_manifest.csv | /home/edik/projects/eccjeu/output/com_antitrust/download_com_antitrust_decisions.csv
A419: 35157 | B419: =YEAR(A419) -> 1996 | C419: 35762 | D419: Exemption Decision | Exemption without condition (Reg 17/62) | E419: JMCS | Joint Mediterranean Canada Service | F419: com_legacy | com_antitrust | G419: com_legacy_1996_line_39 | AT.35762+03-04-1996 | H419: com_legacy:com_legacy_1996_line_39 | com_antitrust:AT.35762+03-04-1996 | I419: IV/35762 | AT.35762 | J419: 1996/02/04/35762 | 1996/03/04/35762 | K419: 1996/02/04/35762/com_legacy | 1996/03/04/35762/com_antitrust | L419: TRUE | M419: TRUE | N419: no_download_candidate | already_exists | O419: http://ec.europa.eu/competition/antitrust/closed/en/1996.html | https://ec.europa.eu/competition/antitrust/cases1/202508/AT_35762_2560241_5_7.pdf | P419: https://ec.europa.eu/competition/antitrust/cases1/202508/AT_35762_2560241_5_7.pdf | Q419: /home/edik/projects/eccjeu/data/raw/com_antitrust/COM50_AT.35762_03-04-1996_case_attachment_exemption_without_condition_reg_17-62_main_bbea30e994.pdf | R419: /home/edik/projects/eccjeu/data/raw/com_antitrust/COM50_AT.35762_03-04-1996_case_attachment_exemption_without_condition_reg_17-62_main_bbea30e994.pdf | S419: /home/edik/projects/eccjeu/output/com_legacy/download_case_manifest.csv | /home/edik/projects/eccjeu/output/com_antitrust/download_com_antitrust_decisions.csv
A420: 35165 | B420: =YEAR(A420) -> 1996 | C420: 35680 | D420: Exemption without condition (Reg 17/62) | E420: Baltic Liner Conference Agreement | F420: com_antitrust | G420: AT.35680+10-04-1996 | H420: com_antitrust:AT.35680+10-04-1996 | I420: AT.35680 | J420: 1996/10/04/35680 | K420: 1996/10/04/35680/com_antitrust | L420: TRUE | M420: TRUE | N420: already_exists | O420: https://ec.europa.eu/competition/antitrust/cases1/202508/AT_35680_2560405_6_5.pdf | P420: https://ec.europa.eu/competition/antitrust/cases1/202508/AT_35680_2560405_6_5.pdf | Q420: /home/edik/projects/eccjeu/data/raw/com_antitrust/COM44_AT.35680_10-04-1996_case_attachment_exemption_without_condition_reg_17-62_main_674f5761bd.pdf | R420: /home/edik/projects/eccjeu/data/raw/com_antitrust/COM44_AT.35680_10-04-1996_case_attachment_exemption_without_condition_reg_17-62_main_674f5761bd.pdf | S420: /home/edik/projects/eccjeu/output/com_antitrust/download_com_antitrust_decisions.csv
A421: 35208 | B421: =YEAR(A421) -> 1996 | C421: 35812 | D421: Exemption without condition (Reg 17/62) | E421: G & C Consortium Agreement | F421: com_antitrust | G421: AT.35812+23-05-1996 | H421: com_antitrust:AT.35812+23-05-1996 | I421: AT.35812 | J421: 1996/05/23/35812 | K421: 1996/05/23/35812/com_antitrust | L421: TRUE | M421: TRUE | N421: already_exists | O421: https://ec.europa.eu/competition/antitrust/cases1/202508/AT_35812_2560629_5_4.pdf | P421: https://ec.europa.eu/competition/antitrust/cases1/202508/AT_35812_2560629_5_4.pdf | Q421: /home/edik/projects/eccjeu/data/raw/com_antitrust/COM59_AT.35812_23-05-1996_case_attachment_exemption_without_condition_reg_17-62_main_cf508c91f9.pdf | R421: /home/edik/projects/eccjeu/data/raw/com_antitrust/COM59_AT.35812_23-05-1996_case_attachment_exemption_without_condition_reg_17-62_main_cf508c91f9.pdf | S421: /home/edik/projects/eccjeu/output/com_antitrust/download_com_antitrust_decisions.csv
... A427: 35368 | B427: =YEAR(A427) -> 1996 | C427: 34503 | D427: Infringement | not_exclusion_candidate | Prohibition Decision | E427: Ferry Operators | Ferry operators - Currency surcharges | F427: andrea | com_db_comp | com_legacy | G427: 407 | 1434 | com_legacy_1996_line_12 | H427: andrea:407 | com_db_comp:1434 | com_legacy:com_legacy_1996_line_12 | I427: 34503 | IV/34503 | J427: 1996/10/30/34503 | K427: 1996/10/30/34503/andrea | 1996/10/30/34503/com_db_comp | 1996/10/30/34503/com_legacy | L427: TRUE | M427: TRUE | N427: reference_only | already_downloaded | O427: https://db-comp.eu/document_1434.download | http://ec.europa.eu/competition/antitrust/closed/en/1996.html | P427: https://db-comp.eu/document_1434.download | https://eur-lex.europa.eu/legal-content/EN/TXT/HTML/?uri=CELEX:31997D0084 | https://eur-lex.europa.eu/legal-content/EN/TXT/PDF/?uri=CELEX:31997D0084 | https://eur-lex.europa.eu/legal-content/DE/TXT/HTML/?uri=CELEX:31997D0084 | https://eur-lex.europa.eu/legal-content/DE/TXT/PDF/?uri=CELEX:31997D0084 | Q427: /home/edik/projects/eccjeu/data/raw/com_db_comp/files/34503-Ferry-operators-Currency-surcharges-_Oct-1996_.pdf | /home/edik/projects/eccjeu/data/raw/com_legacy/files/html/31997D0084_EN.html | /home/edik/projects/eccjeu/data/raw/com_legacy/files/pdfs/31997D0084_EN.pdf | /home/edik/projects/eccjeu/data/raw/com_legacy/files/html/31997D0084_DE.html | R427: /home/edik/projects/eccjeu/data/raw/com_db_comp/files/34503-Ferry-operators-Currency-surcharges-_Oct-1996_.pdf | /home/edik/projects/eccjeu/data/raw/com_legacy/files/html/31997D0084_EN.html | /home/edik/projects/eccjeu/data/raw/com_legacy/files/pdfs/31997D0084_EN.pdf | /home/edik/projects/eccjeu/data/raw/com_legacy/files/html/31997D0084_DE.html | S427: /home/edik/projects/eccjeu/input/andrea_input.csv | /home/edik/projects/eccjeu/output/com_db_comp/db_comp_metadata_manifest.csv | /home/edik/projects/eccjeu/output/com_legacy/download_case_manifest.csv
...

Sheet andrea
A1: case_id | B1: case_number | C1: investigation_started | D1: decision_date | E1: year | F1: duration_months | G1: case_name | H1: parties_name | I1: parties_count | J1: report_route | K1: decision_type | L1: article_infringed | M1: offense_nature | N1: commissioner | O1: commissioner_id | P1: appeal | Q1: court_case_linked
A2: 1 | B2: 61 | C2: 21797 | D2: 23447 | E2: 1964 | F2: 54 | G2: Grosfillex & Fillistorf | H2: Grosfillex | I2: 1 | J2: Notification | K2: Negative Clearance | L2: 81 | M2: agreement between two companies (vertical) | N2: Walter Hallstein (P) | O2: 1 | P2: 0
A3: 2 | B3: 12868 | C3: 23036 | D3: 23529 | E3: 1964 | F3: 16 | G3: Bendix & Meertens and Straet | H3: Bendix International Division ; Mertens & Straet | I3: 2 | J3: Notification | K3: Negative Clearance | L3: 81 | M3: agreement between two companies (vertical) | N3: Walter Hallstein (P) | O3: 1 | P3: 0
A4: 3 | B4: 95 | C4: 22838 | D4: 23588 | E4: 1964 | F4: 25 | G4: Nicholas Frères & Vitapro | H4: Société Nicholas | I4: 1 | J4: Notification | K4: Negative Clearance | L4: 81 | M4: agreement between two companies | N4: Walter Hallstein (P) | O4: 1 | P4: 0
A5: 4 | B5: 3344 | C5: 23040 | D5: 23643 | E5: 1964 | F5: 20 | G5: Grundig-Consten | H5: Grundig Verkaufs GmbH; Êts. Consten s.à.r.l. | I5: 2 | J5: Notification | K5: Infringement | L5: 81 | M5: agreement between two companies (vertical) | N5: Walter Hallstein (P) | O5: 1 | P5: 1 | Q5: 56/64, 58/64
A6: 5 | B6: 71 | C6: 23085 | D6: 23672 | E6: 1964 | F6: 19 | G6: Deca | H6: N.V. Amsterdamsche Ballast Maatschappij; van Hattum en Blankevoort N.V.; Hollandsche Beton Maatschappij N.V.; De Verenigde Bedrijven Bredero N.V. | I6: 4 | J6: Notification | K6: Negative Clearance | L6: 81 | M6: Change in official rules of Deca (horizontal) | N6: Walter Hallstein (P) | O6: 1 | P6: 0
A7: 6 | B7: 3036 | C7: 23039 | D7: 23931 | E7: 1965 | F7: 29 | G7: Dru-Blondel | H7: Koninklijke Fabrieken Diepenbrock en Reigers N.V.; Établissements Blondel SA | I7: 2 | J7: Notification | K7: Exemption | L7: 81 | M7: agreement between two companies (vertical) | N7: Walter Hallstein (P) | O7: 1 | P7: 0
A8: 7 | B8: 2702 | C8: 23041 | D8: 24002 | E8: 1965 | F8: 32 | G8: Hummel-Isbecque | H8: Ludwig-Hummel; Edmond Isbecque | I8: 2 | J8: Notification | K8: Exemption | L8: 81 | M8: agreement between two companies (vertical) | N8: Walter Hallstein (P) | O8: 1 | P8: 0
A9: 8 | B9: 22491 | C9: 23061 | D9: 24093 | E9: 1965 | F9: 34 | G9: Maison Jallatte | H9: Maison Jalatte SA; Hans Voss KG; SA Éts Vandeputte | I9: 3 | J9: Notification | K9: Exemption | L9: 81 | M9: Distribution agreement (vertical) | N9: Walter Hallstein (P) | O9: 1 | P9: 0
A10: 9 | B10: 223 | C10: 24367 | D10: 24650 | E10: 1967 | F10: 9 | G10: Transocean Marine Paint Association | H10: Koninklijke Lak-, Vernis- en Verffabriek Molijn en Co. NV; J.C. de Coninck et fils SA; Astral, Société de peintures, vernis et encres d'imprimerie; Gioacchino Veneziani SpA; Farbenfabriken Hansa-Höeg; Storry Smithson Group of Companies; Alf Bjercke; C. Ljungdahls AB; Teknos-Mallit Oy; Urruzola SA; The National Lacquer and Paint Products Co. Ltd.; P.A.R. Malayan Paintworks Ltd.; Pacific Products Inc.; Nippon Paidnt Co. Ltd.; Spartan Paints Pty.Ltd.; Superior Paint and Varnish Corporation; Fuller Istmena SA; Antilliaanse Verffabriek NV | I10: 18 | J10: Notification | K10: Exemption | L10: 81 | M10: Horizontal agreement | N10: Walter Hallstein (P) | O10: 1 | P10: 0
A11: 10 | B11: 26352 | C11: 22815 | D11: 24894 | E11: 1968 | F11: 68 | G11: Eurogypsum | H11: Eurogypsum | I11: 1 | J11: Notification | K11: Negative Clearance | L11: 81 | M11: Agreement between several companies (horizontal distribution agreement) | N11: Jean Rey (P) | O11: 2 | P11: 0
A12: 11 | B12: 25140 | C12: 23476 | D12: 25036 | E12: 1968 | F12: 52 | G12: Alliance Constructeurs Francais de Machines-Outils | H12: Ateliers G.S.P.; Société gambin; Établissements A. Huard; Société Ramo; Établissements Rouchaud et Lamassiaude; Établissements Vernet; Établissements Arduino; Établissements W. Gillet; Société Microrex | I12: 9 | J12: Notification | K12: Negative Clearance | L12: 81 | M12: Agreement between several companies (horizontal distribution agreement) | N12: Jean Rey (P) | O12: 2 | P12: 0
A13: 12 | B13: 129 | C13: 22941 | D13: 25036 | E13: 1968 | F13: 69 | G13: Socemas | H13: SOCEMAS | I13: 1 | J13: Notification | K13: Negative Clearance | L13: 81 | M13: Vertical restraints | N13: Jean Rey (P) | O13: 2 | P13: 0
A14: 13 | B14: 26045 | C14: 22719 | D14: 25036 | E14: 1968 | F14: 77 | G14: Acec-Berliet | H14: Acec; Berliet | I14: 2 | J14: Notification | K14: Exemption | L14: 81 | M14: Horizontal production agreement | N14: Jean Rey (P) | O14: 2 | P14: 0
A15: 14 | B15: 565 | C15: 23820 | D15: 25148 | E15: 1968 | F15: 43 | G15: Cobelaz-Usines de Synthese | H15: Fédération belge des producteurs d'azote SC; Comptoir belge de l'azote SC; Ammoniaque synthétique et dérivés SA; Société belge de l'azote et des produits chimique SA; Société carbochimique SA; Société anonyme pour la fabrication des engrais azotés; Société des usines chimique Ugine-Kuhlmann SA; UCB - union chimique - Chemische bedrijven SA | I15: 8 | J15: Notification | K15: Negative Clearance | L15: 81 | M15: Agreement between several companies (horizontal production facility sharing) | N15: Jean Rey (P) | O15: 2 | P15: 0
A16: 15 | B16: 507 | C16: 23519 | D16: 25148 | E16: 1968 | F16: 53 | G16: Cobelaz-Cokeries | H16: Comptoir belge de l'azote; Ammoniaque synthétique et dérivés SA; Cockerill-Ougrée-Providence SA; Société métallurgique Hainaut-Sambre; SA des fours à coke de Zeebrugge; Forges de Thy-Marcinelle et Monceau SA; Cokeries du Marly SA; Société métallurgique d'Espérance-Longdoz SA; Houillères d'Anderlues SA; Carbonisation centrale SA; SA des charbonnages du Borinage; Forges de Clabecq; Usines Gustave Boël SA; Les cokeries du Brabant; André Dumont SA; SA des charbonnages du Bois-du-Luc; SA Zolder; Charbonnages d'Hensies-Pommeroeul SA; Limbourg-Meuse SA | I16: 19 | J16: Notification | K16: Negative Clearance | L16: 81 | M16: Vertical restraints | N16: Jean Rey (P) | O16: 2 | P16: 0
A17: 16 | B17: 23077 | C17: 23178 | D17: 25148 | E17: 1968 | F17: 64 | G17: Rieckermann /AEG-Elotherm | H17: Kommanditgesellschaft Johs. Rieckermann; AEG-Elotherm GmbH | I17: 2 | J17: Notification | K17: Negative Clearance | L17: 81 | M17: Vertical restraints | N17: Jean Rey (P) | O17: 2 | P17: 0
... A19: 18 | B19: 93 | C19: 22939 | D19: 25275 | E19: 1969 | F19: 76 | G19: EEMO | H19: Verein Deutscherr Werkzeugmaschinenfabriken; Fachverband der Maschinen- und Stahl- und Eisenbauindustrie Österreichs; Syndicat des constructeurs belges de machinesoutils pour le travail des métaux; Foreningen af Danske Vaerktöjsmaskinfabrikanter; Syndicat des constructeurs français de machines-outils; The Machine Tool Trades Association (Metalworking Machine Tool Manufacturers' Section; Unione Costruttori Italiani Macchine Utensili; Vereniging van Metaal-Industrieën (Groep Gereedschapswerktuigen); Föreningen Svenska Verktygmaskintillverkare; Verein Schweizerischer Maschinen-Industrieller; Asociación Espanola de Fabricantes de Máguinas-Herramientas; Centrol de Cooperaçao des Industriais de Maquinas-Ferramientas | I19: 12 | J19: Notification | K19: Exemption | L19: 81 | M19: Exclusive dealing contracts Association of associations | N19: Jean Rey (P) | O19: 2 | P19: 0
A20: 19 | B20: 242, 295 | C20: 22950 | D20: 25328 | E20: 1969 | F20: 78 | G20: Convention Chaufourniers | H20: SA en liquidation Carrières Dufour; SA Carrières, chaux et ciments de la Velorie; SA Carrières, chaux et ciments des Prés et de la Roguette; SA Compagnie des Ciments Portland de Vaulx et Antoing; SPRL F. Sherrington et Cie; SA Ciments Portland du Tournaisis; SA Anciens établissements Liévin Vanderdoodt; SPRL Éts Brébart Dapsens; SPRL Éts Jean Agache Lampe; SA Société française des chaux hydrauliques et diments; SA The Antwerp Portland Cement Company; Madame Veuve Fernand Duthoit Staquet; SA en liquidation Briquetereis et cemtnteries de Bruyelles-lez-Antoing | I20: 13 | J20: Notification | K20: Negative Clearance | L20: 81 | M20: Horizontal restraints | N20: Jean Rey (P) | O20: 2 | P20: 0
A21: 20 | B21: 22548 | C21: 23064 | D21: 25372 | E21: 1969 | F21: 76 | G21: Christiani and Nielsen | H21: Christiani & Nielsen à Copenhagen; Christiani & Nielsen à La Haye | I21: 2 | J21: Notification | K21: Negative Clearance | L21: 81 | M21: Horizontal export restraints | N21: Jean Rey (P) | O21: 2 | P21: 0
A22: 21 | B22: 597 | C22: 22950 | D22: 25379 | E22: 1969 | F22: 80 | G22: VVVF | H22: VVVF (Vereniging van Vernis- en Verffabrikanten in Nederland) | I22: 1 | J22: Notification | K22: Negative Clearance | L22: 81 | M22: Horizontal export restraints | N22: Jean Rey (P) | O22: 2 | P22: 0
A23: 22 | B23: 704, 25410 | C23: 23629 | D23: 25384 | E23: 1969 | F23: 58 | G23: Seifa | H23: Seifa SpA; Montecatini Edison SpA; APE, Elettrochimica ligure SpA; SINCAT, Società industriale catanese SpA; Rumianca SpA; Caffaro SpA, Società per l'industria chimica et elettrochimica; Snia Viscasa SpA; Vetrocoke Cokapuania SpA; Carlo Marchi Società in accomandita semplice; ISPEA Industria sali potassici et affini SpA | I23: 10 | J23: Notification | K23: Negative Clearance | L23: 81 | M23: Horizontal restraints | N23: Jean Rey (P) | O23: 2 | P23: 0
A24: 23 | B24: 26623 | C24: 25048 | D24: 25400 | E24: 1969 | F24: 12 | G24: Quinine | H24: NV Nederlandse Combinatie voor Chemische Industrie; Boehringer Mannheim GmbH; Buchler & Co. ; Société chimique Pointet-Girard SA; Société nogentaise de produits chimiques; Pharmacie centrale de France | I24: 6 | J24: Commission own initiative | K24: Infringement | L24: 81 | M24: Horizontal market sharing, quota arrangements and price fixing | N24: Jean Rey (P) | O24: 2 | P24: 1 | Q24: 41/69, 44/69, 45/69
A25: 24 | B25: 26625 | C25: 24930 | D25: 25406 | E25: 1969 | F25: 16 | G25: Clima Chappee-Buderus | H25: Clima Chappée; AG Buderus'sche Eisenwerke | I25: 2 | J25: Notification | K25: Exemption | L25: 81 | M25: Horizontal restraints, via producton sharing | N25: Jean Rey (P) | O25: 2 | P25: 0
A26: 25 | B26: 26437 | C26: 24551 | D26: 25406 | E26: 1969 | F26: 28 | G26: Jaz-Peter I | H26: Jaz SA; Peter-Uhren GmbH | I26: 2 | J26: Notification | K26: Exemption | L26: 81 | M26: Horizontal restraints, via producton sharing | N26: Jean Rey (P) | O26: 2 | P26: 0
A27: 26 | B27: 26267 | C27: 24623 | D27: 25408 | E27: 1969 | F27: 26 | G27: Matieres colorantes, Dyestuffs | H27: Badische Anilin- und Soda-Fabrik (BASF); Cassella Farbwerke Mainkur AG; Farbenfabriken Bayer AG; Farbwerke Hoechst AG; Française des matières solorantes SA; Aziende Colori Nazionali Affini SpA; SA Ciba; J.R. Geigy SA; Sandoz SA; Imperial Chemical Industries Ltd. (I.C.I.) | I27: 10 | J27: Commission own initiative | K27: Infringement | L27: 81 | M27: Horizontal price fixing | N27: Jean Rey (P) | O27: 2 | P27: 1 | Q27: 48/69, 49/69, 51/69, 54/69, 55/69, 56/69, 57/69
A28: 27 | B28: 24470, 24471 | C28: 25246 | D28: 25542 | E28: 1969 | F28: 10 | G28: Pirelli-Dunlop | H28: Pirelli SpA Milan; SA des pneumatiques Dunlop; SA Pirelli France; Società Italiana Dunlop | I28: 4 | J28: Notification | K28: Negative Clearance | L28: 81 | M28: Horizontal restraints | N28: Jean Rey (P) | O28: 2 | P28: 0
A29: 28 | B29: 412 | C29: 25367 | D29: 25748 | E29: 1970 | F29: 13 | G29: ASBL Tube d'Acier Soudé Electr. | H29: SA des usines à tubes de la Meuse; Aciéries réunies de Burbach-Eich-Dedelange "Arbed"; SA des tubes de Nimy; Ateliers Remy Claeys | I29: 4 | J29: Notification | K29: Negative Clearance | L29: 81 | M29: Use of same brand name | N29: Jean Rey (P) | O29: 2 | P29: 0
A30: 29 | B30: 24055 | C30: 23137 | D30: 25749 | E30: 1970 | F30: 86 | G30: Kodak | H30: Kodak-Pathé Parijs, Kodak AG Stuttgart; Kodak SA Brussel; Kodak SpA Milaan; Kodak NV Den Haag | I30: 5 | J30: Notification | K30: Negative Clearance | L30: 81 | M30: Vertical restraints | N30: Jean Rey (P) | O30: 2 | P30: 0
A31: 30 | B31: 299 | C31: 22950 | D31: 25749 | E31: 1970 | F31: 92 | G31: ASPA | H31: ASPA | I31: 1 | J31: Notification | K31: Negative Clearance | L31: 81 | M31: Horizontal restraints | N31: Jean Rey (P) | O31: 2 | P31: 0
A32: 31 | B32: 128, 1968 | C32: 23315 | D32: 25869 | E32: 1970 | F32: 84 | G32: Julien / Van Katwijk | H32: Van Katwijk's Industrieën NV; SA Tuberies Louis Julien | I32: 2 | J32: Notification | K32: Infringement | L32: 81 | M32: Market sharing | N32: Franco M. Malfatti (P) | O32: 3 | P32: 0
A33: 32 | B33: 3213, 10498, 11546, 12992, 17394, 17395, 17971, 18772, 18888 | C33: N/A | D33: 25869 | E33: 1970 | F33: 93 | G33: Omega | H33: SA Omega Louis Brendt et Frères; SA Maison Brandt Frères; SpA De Marchi Fratelli; SA Ultimo Watch; Uhren-Handelsgesellschaft mbH; A. Kinsbergen NV | I33: 6 | J33: Notification | K33: Exemption | L33: 81 | M33: Exclusive distribution | N33: Franco M. Malfatti (P) | O33: 3 | P33: 0
A34: 33 | B34: 337 | C34: 25611 | D34: 25925 | E34: 1970 | F34: 10 | G34: Supexie | H34: Supexie; Péchiney Saint Gobain; Ugine-Kuhlmann; Société des fertilisants de l'Ouest; Établissements Linet | I34: 5 | J34: Notification | K34: Negative Clearance | L34: 81 | M34: Vertical export ban and price fixing | N34: Franco M. Malfatti (P) | O34: 3 | P34: 0
A35: 34 | B35: 25107 | C35: 23461 | D35: 25931 | E35: 1970 | F35: 81 | G35: Carreaux Ceramiques (Interest Grouping of German Ceramic Tile Manufacturer) | H35: AG Norddeutsche Steingutfabrik; AGROB AG für Grob- und Feinkeramik; Albertwerke Klingenberg Keramische Fliesen und Sosaik GmbH; Wilhelm Gail'sche Tonwerke KGaA; Marienberger Mosaikplattenfabrik AG; OSTARA Fliesen GmbH; Servais-Werke AG; Steinzeug- und Mosaikplattenfabrik GmbH; Steuler-Industriewerke GmbH; Velleroy und Bosch Keramische Werke KG; Wandplattenfabrik Engers GmbH; Wessel-Werk GmbH | I35: 12 | J35: Notification | K35: Infringement | L35: 81 | M35: Price fixing agreements (horizontal) | N35: Franco M. Malfatti (P) | O35: 3 | P35: 0
A36: 35 | B36: 26792 | C36: 25531 | D36: 25965 | E36: 1971 | F36: 14 | G36: CICG-Zeiv / ZPÜ | H36: ZPÜ | I36: 1 | J36: Notification | K36: Infringement | L36: 12 | M36: Did not supply information | N36: Franco M. Malfatti (P) | O36: 3 | P36: 0
A37: 36 | B37: 26624 | C37: 24924 | D37: 26081 | E37: 1971 | F37: 38 | G37: FN / CF | H37: (FN)Fabrique nationale d'armes de guerre SA; (CF)Cartoucherie française | I37: 2 | J37: Notification | K37: Exemption | L37: 81 | M37: Horizontal export ban and capacity utilization | N37: Franco M. Malfatti (P) | O37: 3 | P37: 0
A38: 37 | B38: 26760 | C38: 25728 | D38: 26086 | E38: 1971 | F38: 12 | G38: Gema | H38: GEMA (Gesellschaft für musikalische Aufführungs- und mechanische Vervielfältigungsrechte) | I38: 1 | J38: Commission own initiative | K38: Infringement | L38: 82 | M38: Creating Horizontal and vertical restraints by abuse of dominance | N38: Franco M. Malfatti (P) | O38: 3 | P38: 0
A39: 38 | B39: 399 | C39: 25485 | D39: 26102 | E39: 1971 | F39: 21 | G39: Albra-Brasserie Espérance | H39: Albra-Brasserie Espérance | I39: 1 | J39: Commission own initiative | K39: Infringement | L39: 11 | M39: Did not supply information | N39: Franco M. Malfatti (P) | O39: 3 | P39: 0
A40: 39 | B40: 399 | C40: 25485 | D40: 26102 | E40: 1971 | F40: 21 | G40: Union des Brasseries | H40: Union des Brasseries | I40: 1 | J40: Commission own initiative | K40: Infringement | L40: 11 | M40: Did not supply information | N40: Franco M. Malfatti (P) | O40: 3 | P40: 0
A41: 40 | B41: 399 | C41: 25485 | D41: 26102 | E41: 1971 | F41: 21 | G41: Brasserie MAES | H41: Brasserie Maes NV | I41: 1 | J41: Commission own initiative | K41: Infringement | L41: 11 | M41: Did not supply information | N41: Franco M. Malfatti (P) | O41: 3 | P41: 0
A42: 41 | B42: 239 | C42: 25974 | D42: 26116 | E42: 1971 | F42: 5 | G42: Asphaltoïd-Keller | H42: Asphaltoïd-Keller | I42: 1 | J42: Commission own initiative | K42: Infringement | L42: 11 | M42: Did not supply information | N42: Franco M. Malfatti (P) | O42: 3 | P42: 0
A43: 42 | B43: 181 | C43: 22944 | D43: 26200 | E43: 1971 | F43: 107 | G43: CEMATEX | H43: Fachgemeinschaft Textilmaschinen im Verein Deutscher Maschinenbau-Anstalten FN (VDMA); Syndicat des Constructeurs belges de machines textiles (SYMATEX); Union des Constructeurs de matériel textile de France; TREX British Textile Machinery Organisation; Associazione Construttori Italiani di Macchinario per l'Industria Tessile (ACIMIT); Vereniging van Metaal-Industrieën, Groep Textielmachines; Société suisse des Constructeurs de machines groupe "Industrie des machines textiles" | I43: 7 | J43: Notification | K43: Exemption | L43: 81 | M43: Horizontal restraints | N43: Franco M. Malfatti (P) | O43: 3 | P43: 0
A44: 43 | B44: 26909 | C44: 26094 | D44: 26246 | E44: 1971 | F44: 5 | G44: SIAE | H44: Comité européen des Constructeurs de matériel textile (CEMATEX); Fachgemeinschaft Textilmaschinen im Verein Deutscher Maschinenbau-Anstalten FN (VDMA); Syndicat des Constructeurs belges de machines textiles (SYMATEX); Union des Constructeurs de matériel textile de France; TREX British Textile Machinery Organisation; Associazione Construttori Italiani di Macchinario per l'Industria Tessile (ACIMIT); Vereniging van Metaal-Industrieën, Groep Textielmachines; Société suisse des Constructeurs de machines groupe "Industrie des machines textiles" | I44: 8 | J44: Commission own initiative | K44: Infringement | L44: 11 | M44: Did not supply information | N44: Franco M. Malfatti (P) | O44: 3 | P44: 0
A45: 44 | B45: 26811 | C45: 25667 | D45: 26276 | E45: 1971 | F45: 20 | G45: Continental Can Company | H45: Continental Can Company | I45: 1 | J45: Commission own initiative | K45: Infringement | L45: 82 | M45: Attempt to monopolize via shares | N45: Franco M. Malfatti (P) | O45: 3 | P45: 1 | Q45: 26451
A46: 45 | B46: 324 | C46: 24093 | D46: 26283 | E46: 1971 | F46: 72 | G46: Vereeniging van Cementhandelaren | H46: Vereeniging van Cementhandelaren | I46: 1 | J46: Notification | K46: Infringement | L46: 81 | M46: Vertical export ban | N46: Franco M. Malfatti (P) | O46: 3 | P46: 1 | Q46: 26512
A47: 46 | B47: 23514 | C47: 23088 | D47: 26283 | E47: 1971 | F47: 105 | G47: SAFCO | H47: Sàrl Bouclet fils, Zunequin & Cie.; SA Brisoux et Cie.; Sàrl Dupont-Cuveliez fils; SA Établissements Robert Durand; SA Nouveaux Établissements J. Duvet; SA F. Poulain et Cie.; SA La Semeuse | I47: 7 | J47: Notification | K47: Negative Clearance | L47: 81 | M47: Agreement between several small companies (horizontal) | N47: Franco M. Malfatti (P) | O47: 3 | P47: 0
A48: 47 | B48: 5400 | C48: 23042 | D48: 26289 | E48: 1971 | F48: 107 | G48: BURROUGHS-DELPLANQUE | H48: Établissements L. Delplanque et fils; Burroughs Corporation | I48: 2 | J48: Notification | K48: Negative Clearance | L48: 81 | M48: Vertical restraints Licences | N48: Franco M. Malfatti (P) | O48: 3 | P48: 0
A49: 48 | B49: 5405 | C49: 23042 | D49: 26289 | E49: 1971 | F49: 107 | G49: BURROUGHS / GEHA-WERKE | H49: Geha-Werke GmbH; Burroughs Corporation | I49: 2 | J49: Notification | K49: Negative Clearance | L49: 81 | M49: Vertical restraints Licences | N49: Franco M. Malfatti (P) | O49: 3 | P49: 0
A50: 49 | B50: 26917 | C50: 26079 | D50: 26290 | E50: 1971 | F50: 7 | G50: HENKEL / COLGATE | H50: Henkel et Cie. GmbH; Colgate-Palmolive Cie New York; SpA Colgate-Palmolive Milaan | I50: 3 | J50: Notification | K50: Exemption | L50: 81 | M50: Joint venture in R&D | N50: Franco M. Malfatti (P) | O50: 3 | P50: 0
A51: 50 | B51: 595 | C51: 22950 | D51: 26290 | E51: 1971 | F51: 110 | G51: Nederlandse Cement-Handelsmaatschappij | H51: Nederlandse Cement-Handelsmaatschappij; Alsen'sche Portland-Cement-Fabriken KG; Anneliese Portland-Cement- und Wasserkalkwerke AG; Beckumer Portland-Zementwerk Bomke & Bleckmann KG; Bonner Portland-Zementwerk AG; Breitenburger Portland-Cement-Fabrik; "Burania" Portlandzement- und Kalkwerk Betriebs-GmbH; Dyckerhoff Zementwerke AG; Elsa Zement- und Kalkwerke SA; Evers Portlandzement- und Kalkwerke Betriebs-GmbH; "Felsenfest" Westfälische Portland-Zement- und Kalkwerke GmbH; "Fortuna"Portland-Zementwerke GmbH; Germania Zementwerke AG; Hannoverische Portland-Cementfabrik AG; Portland-Zementwerke Heidelberg AG; Portland-Cenmentwerk "Heilbach" Feldmann & Co.; Portland Cementfabrik Hemmoor; Hoesch AG Uüttenwerke; Holsteinische Portland-Cement-Fabrik GmbH; Zementwerk "Ilse" Friedrich-Wilhelm Mohn; Klöckner-Werke AG Hütte Bremen; Klöckner-Werke AG Georgsmarienwerke; Friedr. Krupp Hüttenwerke AG; C. Mersmann Portland-Zementwerk; Hermann Milke KG; Nordcement AG; Portland-Zement- und Kalkwerk "Nord" Ruhr & Co.; Portland-Zementwerke "Nordstern" Josef Spenner; Hüttenwerk Oberhausen AG; Phoenix Zementwerke Krogbeumker KG; Rheinstahl Hüttenwerke AG; Teutonia Misburger Portland-Cementwerk; August Thyssen-Hütte AG; Tubag Trass-Zement- und Steinwerke AG; E. Schwenk Zementwerke GmbH; Westdeutsche Kalk- und Portlandzement-Werke AG; Westdeutsche Portland-Zement- und Kalkwerke Gebr. Gröne; Westfälische Portlandzementwerke Kohle & Co.; Portlandzementwerk Wittekind | I51: 39 | J51: Notification | K51: Negative Clearance | L51: 81 | M51: Distribution cartel | N51: Franco M. Malfatti (P) | O51: 3 | P51: 0
A52: 51 | B52: 26612 | C52: 23447 | D52: 26315 | E52: 1972 | F52: 96 | G52: MAN / SAVIEM | H52: (MAN) Maschinenfabrik Augsburg-Nürnberg AG; (SAVIEM) SA de véhicules industriels et d'ëquipements mécanique | I52: 2 | J52: Notification | K52: Exemption | L52: 81 | M52: Horizontal co-operation | N52: Franco M. Malfatti (P) | O52: 3 | P52: 0
A53: 52 | B53: 26844 | C53: 25751 | D53: 26352 | E53: 1972 | F53: 23 | G53: WILD-LEITZ | H53: Sàarl Wild; SA E. Leitz | I53: 2 | J53: Notification | K53: Negative Clearance | L53: 81 | M53: Agreement between two daughter companies | N53: Franco M. Malfatti (P) | O53: 3 | P53: 0
A54: 53 | B54: 6964, 17448, 17545, 18673, 26858, 26890 | C54: 23041 | D54: 26459 | E54: 1972 | F54: 112 | G54: DAVIDSON RUBBER CO | H54: Davidson Rubber Company; Gebr. Happich GmbH; Gallino SpA; Maglum SA; CIM 3; Stampaggio Fesine Speciali SpA | I54: 6 | J54: Notification | K54: Exemption and Negative Clearance | L54: 81 | M54: Exclusive licensing | N54: Franco M. Malfatti (P) | O54: 3 | P54: 0
A55: 54 | B55: 26813 | C55: 25639 | D55: 26459 | E55: 1972 | F55: 28 | G55: RAYMOND-NAGOYA | H55: SA Raymond; Nagoya Rubber Co. Ltd | I55: 2 | J55: Notification | K55: Negative Clearance | L55: 81 | M55: Exclusive licensing | N55: S.L. Mansholt (P) | O55: 4 | P55: 0
A56: 55 | B56: 642 | C56: 26008 | D56: 26506 | E56: 1972 | F56: 18 | G56: Papier Mince | H56: Papeteries Bolloré SA; Job SA; Société des anciens établissements Braunstein Frères SA; Papeteries de Mauduit SA; SA des Papiers Abadie | I56: 5 | J56: Notification | K56: Exemption | L56: 81 | M56: Quality agreements (horizontal) | N56: S.L. Mansholt (P) | O56: 4 | P56: 0
A57: 56 | B57: 8818, 8822 | C57: 23042 | D57: 26570 | E57: 1972 | F57: 116 | G57: Rodenstock | H57: Optische Werke G. Rodenstock; Emilio Ciliotta; NV Nehom | I57: 3 on page 322 a list of 15 companies ?? | J57: Notification | K57: Infringement | L57: 11 | M57: Did not supply information | N57: S.L. Mansholt (P) | O57: 4 | P57: 0
A58: 57 | B58: 24171 | C58: 23042 | D58: 26570 | E58: 1972 | F58: 116 | G58: MISAL | H58: NV Nederlandsche Hasler Mij.; Gosselaar's Industrie en Handelsonderneming NV; Agentura Kabelapparatuur; Orenstein & Koppel NV; Motor Supplies Rotterdam; Ingenieursbureau W. Merkens; NV Spaan en Van Heyst; Ingenieursbureau J. & C. Vrins NV; Van der Spek Amsterdam NV; NV Nehom; Jan Wevers; Van Rietschoten & Houwens; Snikkers'Handel Mij. NV; Akaha- Den Haag NV; NV Handelsonderneming Gronfa; MA Pon Motoren NV; NV Industriële Handelsonderneming Witra; Franco Nigris & Cie.; Emilio Ciliotta; Scoopmobile Italiana SpA; Pozzonini, Parmarini & Cie Spa; NPT Turin; Silverstar Ltd.; Spa Az. Oscar Linke OLSA; G. Jost Goffredo; Spa Alberto rocca; Srl Italauto Milan; Codagex; Établissement J. Baille; Paul Schmedding KG; Arnold Otto Meyer Im- und Export; Travalair GmbH & Co. KG; Costagusa - Rudolf Lehmann GmbH; Office d'étude et de transactions internationales Paris; SA Française pour l'Importation du Caoutchouc Safic Alcan et Cie; Ateliers Bariquant & Marre; Ophtal SA; Société d'équipement industriel électro-mécanique Paris; Sarl Centre de diffusion de produits européens Boulogne; L.& B. Baehn; Central Photo SA Paris; Société Tractor Paris; Établissements A. Olier; Firma Carl Georg Schröder | I58: 45 | J58: Commssion own initative | K58: Infringement | L58: 11 | M58: Did not supply information | N58: S.L. Mansholt (P) | O58: 4 | P58: 0
A59: 58 | B59: 496, 498, 511, 532, 26238, 26577 | C59: 24793 | D59: 26592 | E59: 1972 | F59: 59 | G59: Chauffage Central (Central Heating B) | H59: Éts Defounes; Éts Chavée; Éts Verbeeck; SA Ateliers ACV; SA Acomal; Usines Antverpia; SA Cérac; SA Thomas Defawes; SA Heurtey; SA Idéal-Standard; SA Usines et fonderies Saint-Roch; SA Socother; NV Sogaz; SA Tubes de Nimy; SA Warneton Chappee; Éts Ritschie; NV Société Rateau; Sprl Soudron-Sacré; NV Veha; NV Eurocalor | I59: 20 | J59: Notification | K59: Infringement | L59: 81 | M59: Agreement, could ease vertical and horizontal restraints (more horizontal, vertical in sense of consumers only) | N59: S.L. Mansholt (P) | O59: 4 | P59: 0
A60: 59 | B60: 26876, 26892, 26894 | C60: 25939 | D60: 26626 | E60: 1972 | F60: 23 | G60: Pittsburgh Corning Europe-Formica Belgium-Hertel | H60: Pittsburgh Corning Europe SA; SA Formica Belgium NV; NV Hertel en Co. | I60: 3 | J60: Notification | K60: Infringement | L60: 81, 11 | M60: Vertical price fixing plus export issues | N60: S. L. Mansholt (P) | O60: 4 | P60: 0
A61: 60 | B61: 26911 | C61: 26031 | D61: 26647 | E61: 1972 | F61: 20 | G61: ZOJA / CSC-ICI, Commercial Solvents | H61: Commercial Solvents Corporation; Instituto Chemioterapico Italiano | I61: 2 | J61: Complaint | K61: Infringement | L61: 82 | M61: Refusal to supply (horizontal) | N61: S. L. Mansholt (P) | O61: 4 | P61: 1 | Q61: 6/73, 7/73
A62: 61 | B62: 581 | C62: 25934 | D62: 26651 | E62: 1972 | F62: 24 | G62: Cementregeling voor Nederland (CRN) | H62: ENCI NV; Cemij NV; Cementfabriek Rozenburg NV; La Cimenterie belge "Cimbel" SA; SA Cimenteries CBR Brussel; SA Ciments d'Obourg; SA Ciments de Thieu; SA Ciments Portland liégeois; SA Ciments de Visé; SA Compagnie des Ciments belges Gaurain-Ramecroix; SA Ciments Portland J. van den Heuvel; SA Sté ge'nérale des ciments Portland de l'Escaut; SA Carrières et cimenteries Lemay; Nederlandse Cement-Handelsmaatschappij NV Den Haag; Alsen'sche Portland-Cement-Fabriken KG; Anneliese Portland-Cement- und Wasserkalkwerke AG; Bonner Zementwerk AG; Breitenburger Portland-Cement-Fabrik; Burania Portlandzement- und Kalkwerk Betriebs-GmbH; Dyckerhoff Zementwerke AG; Elsa Zement- und Kalkwerke AG; Evers Portlandzement- und Kalkwerke Betriebs-GmbH; Felsenfest Westfälische Portland-Zement- und Kalkwerke GmbH, Germania Zementwerke AG; Westdeutsche Portland-Zement- und Kalkwerke Gebr. Gröne; Hannoverische Portland-Cementfabrik AG; Portland-Cementwerke Hellbach Feldmann & Co.; Portland-Zementwerke Heidelberg AG; Hemmoor Zement AG; Holsteinische Portland-Cement-Fabrik GmbH; Ilse Baustoffvertriebs-GmbH; W. Kalthöner Portland-Zement- und Kalkwerke; Klöckner-Werke AG Hütte Bremen; Westfälische Portland-Zementwerke Kohle & Co.; C. Mersmann Zement- und Kalkwerke GmbH; Hermann Milke KG; Montanzement-Vertriebs-GmbH; Hoesch AG Hüttenwerke; Klöckner-Werke AG, Georgsmarienwerke; Friedr. Krupp Hüttenwerke AG; Hüttenwerke Oberhausen AG; Rheinstahl Hüttenwerke AG; August Thyssen-Hütte AG; Nordcement AG; Portland Zementwerke Nordstern Josef Spenner; Phoenix Zementwerke Krogbeumker KG; E. Schwenk Zement- und Steinwerke KG; Teutonia Mesburger Portland-Cementwerk; Tubag Trass-Zement- und Steinwerke KG; Portland-Zementwerke Westfalen Schonlau & Co. KG; Portlandzementwerk Wittekind Hugo Miebach Söhne | I62: 53 | J62: Complaint | K62: Infringement | L62: 81 | M62: Quota agreement and price fixing (horizontal) | N62: S.L. Mansholt (P) | O62: 4 | P62: 0
A63: 62 | B63: 243, 244, 245 | C63: 24485 | D63: 26655 | E63: 1972 | F63: 72 | G63: CIMBEL | H63: la Cimenterie belge - Cimbel SA; SA Cimenteries CBR Cementbedrijven NV; SA Ciments d'Obourg; SA Ciments de Thieu; SA Ciments Portland liégeois; SA Ciments de Visé; SA Compagnie des Ciments belges - CCB; SA Ciments Portland J. Van den Heuvel; SA Société générale des ciments Portland de l'Escaut; SA Carrières et Cimenteries Lemay | I63: 10 | J63: Notification | K63: Infringement | L63: 81 | M63: Quota agreement and price fixing (horizontal) | N63: S.L. Mansholt (P) | O63: 4 | P63: 0
A64: 63 | B64: 89, 26349 | C64: 26464 | D64: 26655 | E64: 1972 | F64: 7 | G64: GISA | H64: GISA (Groothandelaren in Sanitaire Artikelen) | I64: 1 | J64: Commssion own initative | K64: Infringement | L64: 81 | M64: Quota agreement and price fixing (horizontal) | N64: S.L. Mansholt (P) | O64: 4 | P64: 0
A65: 64 | B65: 26992 | C65: 26500 | D65: 26655 | E65: 1972 | F65: 5 | G65: WEA-FILIPACCHI MUSIC | H65: COGEDEP Paris; SA d'exploitation des Éts Gavelle et Cie Discobole; FNAC SA; Au Bon Marché; Au Printemps; Magenta Musique; Codimusic SA; S. Wolf; CMN Comptoir musical de Normandie; Ëts Discoparade; Disco-Centre A. Tessanne; Insturments Claude Ridel; Desforges et Co SA; Société centrale de distribution matérial radio-télévision ; Éts Erbel; DEM Grossiste Disques; Éts Téléglobe; Maison Raphaël | I65: 18 | J65: Commission own initiative | K65: Infringement | L65: 81 | M65: Vertical export ban | N65: S. L. Mansholt (P) | O65: 4 | P65: 0
A66: 65 | B66: 26918 | C66: 26450 | D66: 26666 | E66: 1973 | F66: 7 | G66: EUROPEAN SUGAR INDUSTRY | H66: Raffinerie Tirlemontoise SA; NV Centrale Suiker Maatschappij NV; Cooperatieve Vereniging Suiker Unie UA; Westdeutsche Zuckervertriebsgesellschaft mbH & Co KG; Pfeifer & Langen; Südzucker Verkauf GmbH; Süddeutsche Zucker AG; Zückerfabrik Franken GmbH; Sucre-Union SA; Société des Raffineries et Sucreries Say; Société F. Béghin SA; Générale Sucrière SA; Société Nouvelle de Faffinerie Lebaudy-Sommier SA; Groupement d'Intérèt Economique Lebaudy-SUC; Sucres & Denrées SA; Eridania Zuccherifici Naxionali SpA; Società Generale di Zuccherifici (Société Générale de Sucreries); Cavarzere-Produzioni Industriali; Società Italiana per l'Industria degli Zuccheri SpA; Romana Zucchero SpA; Zuccherificio del Volano SpA; SADAM SpA; Zuccherificio di Sermide SpA | I66: 24 | J66: Commission own initiative | K66: Infringement | L66: 81, 82 | M66: Horizontal market sharing, price fixing and collusive tendering; Exerting pressure to restrict intra-Community trade | N66: S. L. Mansholt (P) | O66: 4 | P66: 1 | Q66: 40/73, 41/73, 42/73, 43/73, 44/73, 45/73, 46/73, 47/73, 48/73, 49/73, 50/73, 54/73, 55/73, 56/73, 111/73, 113/73, 114/73
A67: 66 | B67: 791, 1373, 1374, 1498, 1499, 1500 | C67: 23036 | D67: 26795 | E67: 1973 | F67: 123 | G67: SCPA - Kali und Salz | H67: Verenigte Kaliwerke Salzdetfurth AG; Bergwerksgesellschaft Mariaglück GmbH; Wintershall AG; Gewerkschaft Winterhall; Burbach-Kaliwerke AG; Kali-Chemie AG; Gewerkschaft Baden; Gewerkschaft Markgräfler | I67: 8 | J67: Complaint and Notification | K67: Infringement | L67: 81 | M67: Horizontal practices | N67: Francois-Xavier Ortoli (P) | O67: 5 | P67: 0
A68: 67 | B68: 14111 | C68: 23042 | D68: 26829 | E68: 1973 | F68: 124 | G68: Du Pont de Nemours (Deutschland) | H68: Du Pont de Nemours (Deutschland | I68: 1 | J68: Notification | K68: Negative Clearance | L68: 81 | M68: Vertical Restraints | N68: Francois-Xavier Ortoli (P) | O68: 5 | P68: 0
A69: 68 | B69: 25963 | C69: 35067 | D69: 26848 | E69: 1973 | F69: 270 | G69: Gas Water-Heaters and Bath-Heaters | H69: SPRL Le Renova; SA Contigea; SNCR Joski et Fils; SA Etablissements, Guillaume Prist; SAB Chafforeaux et Maury | I69: 5 | J69: Notification | K69: Infringement | L69: 81 | M69: Vertical restraints | N69: Francois-Xavier Ortoli (P) | O69: 5 | P69: 0
A70: 69 | B70: 27010 | C70: 26506 | D70: 26942 | E70: 1973 | F70: 14 | G70: Deutsche PHILIPS GmbH | H70: Deutssche Philips GmbH Hamburg | I70: 1 | J70: Commission own initiative | K70: Infringement | L70: 81 | M70: Vertical export ban | N70: Francois-Xavier Ortoli (P) | O70: 5 | P70: 0
A71: 70 | B71: 26825 | C71: 25667 | D71: 26945 | E71: 1973 | F71: 42 | G71: PRYM-BEKA | H71: William Prym-Werke KG; SA Manufacture Belge d'Aiguilles Beka | I71: 2 | J71: Notification | K71: Exemption | L71: 81 | M71: Horizontal restraints | N71: Francois-Xavier Ortoli (P) | O71: 5 | P71: 0
A72: 71 | B72: 223 | C72: 26599 | D72: 27019 | E72: 1973 | F72: 14 | G72: Transocean Marine Paint Association | H72: Molijn & Co. NV; J.C. de Coninck en Zonen NV; Astral, Société de Peintures, Vernis et Encres d'Imprimerie; Veneziani Zonca S.p.A.; Farbenfabriken Hansa-Hoëg; Storry Smithson Group of Companies; Sadolin & Holmblad A/S; C.Ljungdahls AB; Urruzola SA; The National Lacquer and Paint Products Co. Ltd.; Pacific Products Inc.; Nippon Paint Co. Ltd. Osaka; Nippon Paint Ltd. Singapore; Nippon Paint Malaysia; Nippon Paint Co. Ltd. Thailand; Spartan Paints Pty.Ltd Melbourne; Patterson-Sargent; Galleon Paints Co. Ltd.; Mauvilac & Co. Ltd.; Antillian Paint Factory Ltd. | I72: 20 | J72: Notification | K72: Exemption | L72: 81 | M72: Horizontal agreement | N72: Francois-Xavier Ortoli (P) | O72: 5 | P72: 1 | Q72: 17/74
A73: 72 | B73: 795 | C73: 26620 | D73: 27019 | E73: 1973 | F73: 13 | G73: Kali und Salz / Kali-Chemie | H73: Kali und Salz AG; Kali Chemie AG | I73: 2 | J73: Commission own initiative | K73: Infringement | L73: 81 | M73: Horizontal market sharing | N73: Francois-Xavier Ortoli (P) | O73: 5 | P73: 1 | Q73: 19/74, 20/74
A74: 73 | B74: 400 | C74: 22949 | D74: 27164 | E74: 1974 | F74: 139 | G74: Manufacturers of Glass Containers (IFTRA) | H74: Gerresheimer Glas Aktiengesellschaft; Veba-Glas AG; H. Heye Glasfabrik "Schauenstein"; Himly, Holscher & Co KG; Beyerische Glaschen-Glashüttenwerke Wiegand & Söhne GmbH; Carl.Aug. Heinz Glashüttenwerke; Lüner Glashüttenwerke GmbH; Glashüttenwerke Ernst W. Müller GmbH; Noelle & von Campe Glashütte GmbH; Oberland-Glas GmbH; Spessarter Hohlglaswerke GmbH; Tettauer Glashüttenwerke AG; Weck Glaswerk GmbH; Verlica-Momignies S.A.; Boutteilleries Belges Réunies S.A.; N.V. Vereenigde Glasfabrieken (United Glasswork); Boussois-Souchon-Neuvesel (BSN) S.A.; Saint-Gobain Emballage S.A.; Verreries de Blanc-Misseron S.A.; Verrerie Ouvrière d'Albi S.A.; Verreries du Pay-de Dôme S.A.; Bordoni Miva Vetrerie Riunite SpA; Aziende Vetrarie Italiane Ricciardi AVIR SpA; Vetreria Italiana VETR.I. SpA | I74: 24 | J74: Notification | K74: Infringement | L74: 81 | M74: Price fixing, discrimination and verticel export ban | N74: Francois-Xavier Ortoli (P) | O74: 5 | P74: 0
A75: 74 | B75: 426 | C75: 26829 | D75: 27233 | E75: 1974 | F75: 14 | G75: Papier peints de Belgique | H75: S.C. Usines Peters-Lacroix S.A.; Les Papeteries de Genval S.A.; Ets. Vanderborght Frères S.A.; Papiers peints Brepols S.A. | I75: 4 | J75: Commission own initiative | K75: Infringement | L75: 81 | M75: Horizontal aggregated rebate cartel and collective boycot | N75: Francois-Xavier Ortoli (P) | O75: 5 | P75: 1 | Q75: 73/74
A76: 75 | B76: 28374 | C76: 27025 | D76: 27234 | E76: 1974 | F76: 7 | G76: Advocaat Zwarte Kip | H76: Van Olffen VB; Cinoco SA | I76: 2 | J76: Notification | K76: Infringement | L76: 81 | M76: Vertical export ban Market-sharing | N76: Francois-Xavier Ortoli (P) | O76: 5 | P76: 0
A77: 76 | B77: 26602 | C77: 24876 | D77: 27235 | E77: 1974 | F77: 78 | G77: Frubo | H77: Algemene Vruchten Import Mij (AVIM) N.V.; Fruit- en Groenten Maatschappij Jac. Van den Berg B.V.; Jan van den Brink B.V.; Citronas B.V.; De la Bella & Co. B.V.; P. van Hoeckel & Co's Im- en Exporthandel B.V.; Van der Horst's Fruitimport "Hofrim"B.V.; B.V. Internationale Fruit Maatschappij; Kooy Rotterdam B.V. p/a Diskomarkt Groothandelsmarkt "Spaanse Polder"; T. Port B.V.; B.V. Solbandera Valencia Sinaasappelen Import Maatschappij; Velleman & Tas B.V. | I77: 12 | J77: Notification | K77: Infringement | L77: 81 | M77: Discrimination and agreements (horizontal) | N77: Francois-Xavier Ortoli (P) | O77: 5 | P77: 1 | Q77: 71/74
A78: 77 | B78: 27095 | C78: 26921 | D78: 27362 | E78: 1974 | F78: 15 | G78: Entente Fr. Jap Roulements a billes (ballbearing) | H78: SKF Compagnie d'applications mécaniques SA; SNR Société nouvelle de roulements; Chambre syndicale nationale de la mécanique de haute précision; Nippon Seiko Kaisha; Koyo Seiko Co. Ltd.; Fujikoshi Ltd.; NTN Toyo Bearing C. Ltd.; The Japan Bearing Industrial Association | I78: 8 | J78: Commission own initiative | K78: Infringement | L78: 81 | M78: Price fixing (horizontal and international) | N78: Francois-Xavier Ortoli (P) | O78: 5 | P78: 0
